Workbook

Sheet List
A1: Name | B1: Description | C1: Percentage | D1: Difficulty | E1: Points | F1: Difficulty (nb) | G1: unique_perct_1 | H1: unique_perct_2 | I1: unique_perct_3 | J1: unique_perct_3_done | K1: unique_perct_3_not_done | L1: unique_diff_1 | M1: unique_diff_1_done | N1: unique_diff_1_not_done | O1: Done? | P1: Started with | Q1: Starting conditions | R1: Completion requirements | S1: Notes1 | T1: Notes2 | U1: unique_perct_3_E | V1: unique_perct_3_M | W1: unique_perct_3_H | X1: unique_perct_3_VE | Y1: listed alreeady?
A2: Mayapahit? | B2: Starting as any Mayan country, form Maya and own or have a subject own the island of Java. | C2: 0.002 | D2: H | E2: =(30-C2*100)*VLOOKUP($D2,Calc!$A$1:$C$6,3,FALSE) -> 149 | F2: =VLOOKUP(D2,Calc!$A$1:$B$6,2,FALSE) -> 4 | G2: =C2+F2/10000 -> 0.0024 | H2: =( (CODE(UPPER(LEFT(A2,1)))-64)+(CODE(UPPER(RIGHT(LEFT(A2,2),1)))-64)+(CODE(UPPER(RIGHT(LEFT(A2,3),1)))-64)+(CODE(UPPER(RIGHT(LEFT(A2,4),1)))-64)+(CODE(UPPER(RIGHT(LEFT(A2,5),1)))-64)+(CODE(UPPER(RIGHT(LEFT(A2,6),1)))-64)+(CODE(UPPER(RIGHT(LEFT(A2,7),1)))-64)+(CODE(UPPER(RIGHT(LEFT(A2,8),1)))-64) )/1000000 -> 7.4e-05 | I2: =G2+H2/10 -> 0.0024074 | J2: =IF($O2="","",I2) -> 0.0024074 | K2: =IF($O2="",I2,"") | L2: =F2-I2 -> 3.9975926 | M2: =IF($O2="","",L2) -> 3.9975926 | N2: =IF($O2="",L2,"") | O2: Y | P2: Huastec | Q2: - Religion is Mayan | R2: - Is *or* was Maya - All provinces in the Banten, East Java, Central Java, Surabaya & West Java areas, except Madura (2692): - Province is owned by the player's country *or* its non-tributary subjects | U2: =IF($D2="E",K2,"") | V2: =IF($D2="M",K2,"") | W2: =IF($D2="H",K2,"") | X2: =IF($D2="VE",K2,"") | Y2: =VLOOKUP($A2,Runs!$G:$G,1,FALSE) -> #N/A
A3: Desert Power | B3: Starting as an Arabian Tribe, have the Oasis privilege enacted, and more than 1000 development in the Arabian Region. | C3: 0.002 | D3: H | E3: =(30-C3*100)*VLOOKUP($D3,Calc!$A$1:$C$6,3,FALSE) -> 149 | F3: =VLOOKUP(D3,Calc!$A$1:$B$6,2,FALSE) -> 4 | G3: =C3+F3/10000 -> 0.0024 | H3: =( (CODE(UPPER(LEFT(A3,1)))-64)+(CODE(UPPER(RIGHT(LEFT(A3,2),1)))-64)+(CODE(UPPER(RIGHT(LEFT(A3,3),1)))-64)+(CODE(UPPER(RIGHT(LEFT(A3,4),1)))-64)+(CODE(UPPER(RIGHT(LEFT(A3,5),1)))-64)+(CODE(UPPER(RIGHT(LEFT(A3,6),1)))-64)+(CODE(UPPER(RIGHT(LEFT(A3,7),1)))-64)+(CODE(UPPER(RIGHT(LEFT(A3,8),1)))-64) )/1000000 -> 5.5e-05 | I3: =G3+H3/10 -> 0.0024055 | J3: =IF($O3="","",I3) -> 0.0024055 | K3: =IF($O3="",I3,"") | L3: =F3-I3 -> 3.9975945 | M3: =IF($O3="","",L3) -> 3.9975945 | N3: =IF($O3="",L3,"") | O3: Y | P3: Najd | Q3: - Capital in the Arabia region - Is tribal | R3: - Has granted the Burghers privilege "Oasis Development" - Provinces in the Arabia region that have Desert or Coastal Desert terrain: - Have at least 1000 total development | S3: "Oasis Development" privilege requires the Arabian mission "The Harsh Desert" to be completed. Note that while not mentioned in the description, only the development of Desert and Coastal Desert provinces is counted for the purposes of this achievement. This means that only 44 provinces are valid to develop, requiring a average of 23 (22.7) development in each of these provinces. | U3: =IF($D3="E",K3,"") | V3: =IF($D3="M",K3,"") | W3: =IF($D3="H",K3,"") | X3: =IF($D3="VE",K3,"") | Y3: =VLOOKUP($A3,Runs!$G:$G,1,FALSE) -> #N/A
A4: Legacy of Saint George | B4: As Georgia, have as vassals Genoa, Aragon, England and Trier or their successors, and control Wales. | C4: 0.002 | D4: VH | E4: =(30-C4*100)*VLOOKUP($D4,Calc!$A$1:$C$6,3,FALSE) -> 298 | F4: =VLOOKUP(D4,Calc!$A$1:$B$6,2,FALSE) -> 5 | G4: =C4+F4/10000 -> 0.0025 | H4: =( (CODE(UPPER(LEFT(A4,1)))-64)+(CODE(UPPER(RIGHT(LEFT(A4,2),1)))-64)+(CODE(UPPER(RIGHT(LEFT(A4,3),1)))-64)+(CODE(UPPER(RIGHT(LEFT(A4,4),1)))-64)+(CODE(UPPER(RIGHT(LEFT(A4,5),1)))-64)+(CODE(UPPER(RIGHT(LEFT(A4,6),1)))-64)+(CODE(UPPER(RIGHT(LEFT(A4,7),1)))-64)+(CODE(UPPER(RIGHT(LEFT(A4,8),1)))-64) )/1000000 -> 3.6e-05 | I4: =G4+H4/10 -> 0.0025036 | J4: =IF($O4="","",I4) | K4: =IF($O4="",I4,"") -> 0.0025036 | L4: =F4-I4 -> 4.9974964 | M4: =IF($O4="","",L4) | N4: =IF($O4="",L4,"") -> 4.9974964 | R4: - Is Georgia - Has the following countries (or countries formed by them) as vassals: - - Genoa - Aragon - England - Trier - All provinces in the Wales area: - Are owned by the country or its non-tributary subjects | S4: If one of the countries forms another country(e.g. England forms Great Britain), the new country can be vassalized to get the achievement. If one of the countries dies, care must be taken that the cores don't expire, especially for Trier which is not the primary tag of its culture. | U4: =IF($D4="E",K4,"") | V4: =IF($D4="M",K4,"") | W4: =IF($D4="H",K4,"") | X4: =IF($D4="VE",K4,"") | Y4: =VLOOKUP($A4,Runs!$G:$G,1,FALSE) -> Legacy of Saint George
A5: From Frankfurt to the Andes | B5: Starting as Frankfurt, form Jerusalem, and then form the Inca while owning Mallorca. | C5: 0.002 | D5: VH | E5: =(30-C5*100)*VLOOKUP($D5,Calc!$A$1:$C$6,3,FALSE) -> 298 | F5: =VLOOKUP(D5,Calc!$A$1:$B$6,2,FALSE) -> 5 | G5: =C5+F5/10000 -> 0.0025 | H5: =( (CODE(UPPER(LEFT(A5,1)))-64)+(CODE(UPPER(RIGHT(LEFT(A5,2),1)))-64)+(CODE(UPPER(RIGHT(LEFT(A5,3),1)))-64)+(CODE(UPPER(RIGHT(LEFT(A5,4),1)))-64)+(CODE(UPPER(RIGHT(LEFT(A5,5),1)))-64)+(CODE(UPPER(RIGHT(LEFT(A5,6),1)))-64)+(CODE(UPPER(RIGHT(LEFT(A5,7),1)))-64)+(CODE(UPPER(RIGHT(LEFT(A5,8),1)))-64) )/1000000 -> 4.5e-05 | I5: =G5+H5/10 -> 0.0025045 | J5: =IF($O5="","",I5) -> 0.0025045 | K5: =IF($O5="",I5,"") | L5: =F5-I5 -> 4.9974955 | M5: =IF($O5="","",L5) -> 4.9974955 | N5: =IF($O5="",L5,"") | O5: Y | P5: Frankfurt | Q5: Playing as Frankfurt | R5: - Was Frankfurt - Was Jerusalem - Is Inca - Own Mallorca (333) | S5: - Hardest part of this achievement is finding and fulfilling conditions for different tag formation. - To form Jerusalem, you need to get into coring range of Jerusalem area (vassalize an Italian minor and conquer a province next to it), own and state Jerusalem area, move capital to Arabia, Egypt or Mashriq and switch from Republic to Monarchy. And this has to be done before the Age of Reformation ends, because Frankfurt can't form Jerusalem later. - To form Inca you need to move your capital to the New World, own cores on required provinces, culture shift to Andean culture and change your religion to a pagan faith via rebels. - Switching to play as a released vassal will invalidate the achievement. | U5: =IF($D5="E",K5,"") | V5: =IF($D5="M",K5,"") | W5: =IF($D5="H",K5,"") | X5: =IF($D5="VE",K5,"") | Y5: =VLOOKUP($A5,Runs!$G:$G,1,FALSE) -> From Frankfurt to the Andes
A6: Timurizz | B6: Starting as the Timurids, have 75 prestige, and 5 allies with 100 Trust and 150 opinion. | C6: 0.003 | D6: E | E6: =(30-C6*100)*VLOOKUP($D6,Calc!$A$1:$C$6,3,FALSE) -> 29.7 | F6: =VLOOKUP(D6,Calc!$A$1:$B$6,2,FALSE) -> 2 | G6: =C6+F6/10000 -> 0.0032 | H6: =( (CODE(UPPER(LEFT(A6,1)))-64)+(CODE(UPPER(RIGHT(LEFT(A6,2),1)))-64)+(CODE(UPPER(RIGHT(LEFT(A6,3),1)))-64)+(CODE(UPPER(RIGHT(LEFT(A6,4),1)))-64)+(CODE(UPPER(RIGHT(LEFT(A6,5),1)))-64)+(CODE(UPPER(RIGHT(LEFT(A6,6),1)))-64)+(CODE(UPPER(RIGHT(LEFT(A6,7),1)))-64)+(CODE(UPPER(RIGHT(LEFT(A6,8),1)))-64) )/1000000 -> 0.000142 | I6: =G6+H6/10 -> 0.0032142 | J6: =IF($O6="","",I6) | K6: =IF($O6="",I6,"") -> 0.0032142 | L6: =F6-I6 -> 1.9967858 | M6: =IF($O6="","",L6) | N6: =IF($O6="",L6,"") -> 1.9967858 | Q6: - Is Timurids | R6: - Prestige is at least *+75* - Has at least 5 allies with 100 trust which have at least *+150* opinion of our country | S6: The allies which have the trust have to be the same allies which have the opinion Trust can be gained by honoring calls to arms or by using the *Influence nation* interaction as a great power, or with The Cossacks or Leviathan by trading favors for trust. If neither The Cossacks nor Leviathan are active, trust with allies grows slowly over time. | U6: =IF($D6="E",K6,"") -> 0.0032142 | V6: =IF($D6="M",K6,"") | W6: =IF($D6="H",K6,"") | X6: =IF($D6="VE",K6,"") | Y6: =VLOOKUP($A6,Runs!$G:$G,1,FALSE) -> Timurizz
A7: Ultimate Military | B7: As Songhai, have Prussia and Nepal as marches! | C7: 0.003 | D7: H | E7: =(30-C7*100)*VLOOKUP($D7,Calc!$A$1:$C$6,3,FALSE) -> 148.5 | F7: =VLOOKUP(D7,Calc!$A$1:$B$6,2,FALSE) -> 4 | G7: =C7+F7/10000 -> 0.0034 | H7: =( (CODE(UPPER(LEFT(A7,1)))-64)+(CODE(UPPER(RIGHT(LEFT(A7,2),1)))-64)+(CODE(UPPER(RIGHT(LEFT(A7,3),1)))-64)+(CODE(UPPER(RIGHT(LEFT(A7,4),1)))-64)+(CODE(UPPER(RIGHT(LEFT(A7,5),1)))-64)+(CODE(UPPER(RIGHT(LEFT(A7,6),1)))-64)+(CODE(UPPER(RIGHT(LEFT(A7,7),1)))-64)+(CODE(UPPER(RIGHT(LEFT(A7,8),1)))-64) )/1000000 -> 0.000101 | I7: =G7+H7/10 -> 0.0034101 | J7: =IF($O7="","",I7) -> 0.0034101 | K7: =IF($O7="",I7,"") | L7: =F7-I7 -> 3.9965899 | M7: =IF($O7="","",L7) -> 3.9965899 | N7: =IF($O7="",L7,"") | O7: Y | P7: Songhai | Q7: Playing as Songhai | R7: - Is Songhai - Have Prussia*and*Nepal as marches. | S7: This achievement is only visible if the Origins DLC is active, but it is possible to get the achievement without that DLC. Songhai has a strong starting position, the main difficulty is making sure both Prussia and Nepal exist. Note that only Prussia can be formed by a subject nation, so you are better off giving a Nepali minor the required provinces by calling them to war as ally before subjugating them. | U7: =IF($D7="E",K7,"") | V7: =IF($D7="M",K7,"") | W7: =IF($D7="H",K7,"") | X7: =IF($D7="VE",K7,"") | Y7: =VLOOKUP($A7,Runs!$G:$G,1,FALSE) -> Ultimate Military
A8: Triple the Rome | B8: As Russia, be the Emperor of China and the HRE. | C8: 0.003 | D8: H | E8: =(30-C8*100)*VLOOKUP($D8,Calc!$A$1:$C$6,3,FALSE) -> 148.5 | F8: =VLOOKUP(D8,Calc!$A$1:$B$6,2,FALSE) -> 4 | G8: =C8+F8/10000 -> 0.0034 | H8: =( (CODE(UPPER(LEFT(A8,1)))-64)+(CODE(UPPER(RIGHT(LEFT(A8,2),1)))-64)+(CODE(UPPER(RIGHT(LEFT(A8,3),1)))-64)+(CODE(UPPER(RIGHT(LEFT(A8,4),1)))-64)+(CODE(UPPER(RIGHT(LEFT(A8,5),1)))-64)+(CODE(UPPER(RIGHT(LEFT(A8,6),1)))-64)+(CODE(UPPER(RIGHT(LEFT(A8,7),1)))-64)+(CODE(UPPER(RIGHT(LEFT(A8,8),1)))-64) )/1000000 -> 6.8e-05 | I8: =G8+H8/10 -> 0.0034068 | J8: =IF($O8="","",I8) -> 0.0034068 | K8: =IF($O8="",I8,"") | L8: =F8-I8 -> 3.9965932 | M8: =IF($O8="","",L8) -> 3.9965932 | N8: =IF($O8="",L8,"") | O8: Y | P8: Oirat | R8: - Is Russia - Is Emperor of China - Is the emperor of the Holy Roman Empire | S8: To be Emperor of China, you must be in the Pagan or Eastern religion group, whilst to be the HRE Emperor, you generally must be Catholic unless Protestants won the league war, or sometimes other Christian denominations given specific circumstances (see League war), so a religion switch will be necessary to complete the achievement. Switching to a non-Christian religion as HRE Emperor will cause the emperorship to be lost unless the Erbkaisertum reform has been passed, while changing religion as Emperor of China allows you to retain the title. As such, it may be easiest to start as an atypical nation to form Russia such as Oirat, which starts off as Tengri and can use horde mechanics to relatively easily expand into the territories needed to form Russia. It is recommended to not seize the mandate until the needed provinces are conquered since seizing the mandate will change your government to Celestial Empire and disable horde mechanics. At this point, culture shift to Muscovite, Novgorodian or Ryazanian culture and form Russia once you hit admin tech 10. At some point you will need to conquer a Catholic province, perhaps from the Scandinavian or the Baltic regions, which will allow you to convert to Catholic via rebels. After seizing the Mandate of Heaven, convert to Catholicism, then ally or vassalize enough HRE electors to get yourself elected Holy Roman Emperor. | U8: =IF($D8="E",K8,"") | V8: =IF($D8="M",K8,"") | W8: =IF($D8="H",K8,"") | X8: =IF($D8="VE",K8,"") | Y8: =VLOOKUP($A8,Runs!$G:$G,1,FALSE) -> Triple the Rome
A9: The Zoro-Austrians | B9: Starting as Austria, convert to Zoroastrianism, and complete the Persian Zoroastrian missions. | C9: 0.003 | D9: H | E9: =(30-C9*100)*VLOOKUP($D9,Calc!$A$1:$C$6,3,FALSE) -> 148.5 | F9: =VLOOKUP(D9,Calc!$A$1:$B$6,2,FALSE) -> 4 | G9: =C9+F9/10000 -> 0.0034 | H9: =( (CODE(UPPER(LEFT(A9,1)))-64)+(CODE(UPPER(RIGHT(LEFT(A9,2),1)))-64)+(CODE(UPPER(RIGHT(LEFT(A9,3),1)))-64)+(CODE(UPPER(RIGHT(LEFT(A9,4),1)))-64)+(CODE(UPPER(RIGHT(LEFT(A9,5),1)))-64)+(CODE(UPPER(RIGHT(LEFT(A9,6),1)))-64)+(CODE(UPPER(RIGHT(LEFT(A9,7),1)))-64)+(CODE(UPPER(RIGHT(LEFT(A9,8),1)))-64) )/1000000 -> 7.5e-05 | I9: =G9+H9/10 -> 0.0034075 | J9: =IF($O9="","",I9) | K9: =IF($O9="",I9,"") -> 0.0034075 | L9: =F9-I9 -> 3.9965925 | M9: =IF($O9="","",L9) | N9: =IF($O9="",L9,"") -> 3.9965925 | Q9: Is Austria | R9: - Is Persia*or*Eranshahr - Has completed the mission A New Eranshahr mission - Has completed the An Asha Empire mission | U9: =IF($D9="E",K9,"") | V9: =IF($D9="M",K9,"") | W9: =IF($D9="H",K9,"") -> 0.0034075 | X9: =IF($D9="VE",K9,"") | Y9: =VLOOKUP($A9,Runs!$G:$G,1,FALSE) -> The Zoro-Austrians
A10: The Freest Man in the World | B10: Ensure that no colonized province in the world produces slaves while having the War Against the World Doctrine government reform enacted. | C10: 0.003 | D10: H | E10: =(30-C10*100)*VLOOKUP($D10,Calc!$A$1:$C$6,3,FALSE) -> 148.5 | F10: =VLOOKUP(D10,Calc!$A$1:$B$6,2,FALSE) -> 4 | G10: =C10+F10/10000 -> 0.0034 | H10: =( (CODE(UPPER(LEFT(A10,1)))-64)+(CODE(UPPER(RIGHT(LEFT(A10,2),1)))-64)+(CODE(UPPER(RIGHT(LEFT(A10,3),1)))-64)+(CODE(UPPER(RIGHT(LEFT(A10,4),1)))-64)+(CODE(UPPER(RIGHT(LEFT(A10,5),1)))-64)+(CODE(UPPER(RIGHT(LEFT(A10,6),1)))-64)+(CODE(UPPER(RIGHT(LEFT(A10,7),1)))-64)+(CODE(UPPER(RIGHT(LEFT(A10,8),1)))-64) )/1000000 -> 3.5e-05 | I10: =G10+H10/10 -> 0.0034035 | J10: =IF($O10="","",I10) | K10: =IF($O10="",I10,"") -> 0.0034035 | L10: =F10-I10 -> 3.9965965 | M10: =IF($O10="","",L10) | N10: =IF($O10="",L10,"") -> 3.9965965 | R10: - Has enacted the Pirate Republic government reform - Has enacted the War Against the World Doctrine government reform - No fully colonized province in the world produces slaves | S10: Almost all slave provinces are on the African continent (except Azov). Palembang has a quick event which converts them into pirate republic, but they are Hindu and have mediocre ideas. An easier way is to start as Pasai and hoist the black flag: Pasai has better starting provinces, better ideas, and is Muslim, which makes alliance and AE easier. Alternatively, Gotland also becomes a pirate nation through event. Azov and the Ivory Coast are areas of contention with slaves which need to be rushed to asap. Kilwa has the best starting location and missions in Africa. Complete Prepare the Invasion mission to secure five provinces in Madagascar. Move Kilwa's capital to Zanzibar or Madagascar. Give the remaining provinces to Sofala and release the vassal, then Hoist the Black Flag Can be done easily by releasing and playing as Cornwall after you conquer all slave provinces and abolish slavery, e.g. as England/Great Britain, because Cornwall's pirate event requires just 3 ships privateering. Maghrebi nation such as Tunis can sell non coastal provinces to meet the requirements, an alliance with the Ottomans and a proximity to Genoa help gaining Azov early in the game. | T10: *or* | U10: =IF($D10="E",K10,"") | V10: =IF($D10="M",K10,"") | W10: =IF($D10="H",K10,"") -> 0.0034035 | X10: =IF($D10="VE",K10,"") | Y10: =VLOOKUP($A10,Runs!$G:$G,1,FALSE) -> The Freest Man in the World
A11: Baborg | B11: As the Mughals, assimilate at least 12 culture groups. | C11: 0.003 | D11: H | E11: =(30-C11*100)*VLOOKUP($D11,Calc!$A$1:$C$6,3,FALSE) -> 148.5 | F11: =VLOOKUP(D11,Calc!$A$1:$B$6,2,FALSE) -> 4 | G11: =C11+F11/10000 -> 0.0034 | H11: =( (CODE(UPPER(LEFT(A11,1)))-64)+(CODE(UPPER(RIGHT(LEFT(A11,2),1)))-64)+(CODE(UPPER(RIGHT(LEFT(A11,3),1)))-64)+(CODE(UPPER(RIGHT(LEFT(A11,4),1)))-64)+(CODE(UPPER(RIGHT(LEFT(A11,5),1)))-64)+(CODE(UPPER(RIGHT(LEFT(A11,6),1)))-64)+(CODE(UPPER(RIGHT(LEFT(A11,7),1)))-64)+(CODE(UPPER(RIGHT(LEFT(A11,8),1)))-64) )/1000000 -> 5.9e-05 | I11: =G11+H11/10 -> 0.0034059 | J11: =IF($O11="","",I11) | K11: =IF($O11="",I11,"") -> 0.0034059 | L11: =F11-I11 -> 3.9965941 | M11: =IF($O11="","",L11) | N11: =IF($O11="",L11,"") -> 3.9965941 | R11: - Is Mughals - Has enacted the Mughal Diwan government reform - Has assimilated at least *12* culture groups | T11: - One of - - - | U11: =IF($D11="E",K11,"") | V11: =IF($D11="M",K11,"") | W11: =IF($D11="H",K11,"") -> 0.0034059 | X11: =IF($D11="VE",K11,"") | Y11: =VLOOKUP($A11,Runs!$G:$G,1,FALSE) -> Baborg
A12: Australia-Hungary | B12: Starting as an Australian tribe unite Australia and subjugate Hungary. | C12: 0.003 | D12: H | E12: =(30-C12*100)*VLOOKUP($D12,Calc!$A$1:$C$6,3,FALSE) -> 148.5 | F12: =VLOOKUP(D12,Calc!$A$1:$B$6,2,FALSE) -> 4 | G12: =C12+F12/10000 -> 0.0034 | H12: =( (CODE(UPPER(LEFT(A12,1)))-64)+(CODE(UPPER(RIGHT(LEFT(A12,2),1)))-64)+(CODE(UPPER(RIGHT(LEFT(A12,3),1)))-64)+(CODE(UPPER(RIGHT(LEFT(A12,4),1)))-64)+(CODE(UPPER(RIGHT(LEFT(A12,5),1)))-64)+(CODE(UPPER(RIGHT(LEFT(A12,6),1)))-64)+(CODE(UPPER(RIGHT(LEFT(A12,7),1)))-64)+(CODE(UPPER(RIGHT(LEFT(A12,8),1)))-64) )/1000000 -> 0.000101 | I12: =G12+H12/10 -> 0.0034101 | J12: =IF($O12="","",I12) | K12: =IF($O12="",I12,"") -> 0.0034101 | L12: =F12-I12 -> 3.9965899 | M12: =IF($O12="","",L12) | N12: =IF($O12="",L12,"") -> 3.9965899 | Q12: Playing as one of the following countries: - Australia - Tiwi - Larrakia - Yolngu - Yanuwa - Awngthim - Kamilaroi - Mianjin - Eora - Kulin - Kaurna - Palawa - Wurundjeri - Nyoongah - Malgana | R12: - Hungary is a vassal of this country - Owns all provinces in the Australia region. - Is one of the following countries: - Australia - Tiwi - Larrakia - Yolngu - Yanuwa - Awngthim - Kamilaroi - Mianjin - Eora - Kulin - Kaurna - Palawa - Wurundjeri - Nyoongah - Malgana | S12: Forming a federation will make the achievement much harder as your nation tag will change in the process. One possible way to circumvent this is becoming a steppe horde through government reforms, which changes the technology group to nomadic and allows you to form Australia, but becoming a horde in this way is only possible as a migratory tribe. | U12: =IF($D12="E",K12,"") | V12: =IF($D12="M",K12,"") | W12: =IF($D12="H",K12,"") -> 0.0034101 | X12: =IF($D12="VE",K12,"") | Y12: =VLOOKUP($A12,Runs!$G:$G,1,FALSE) -> Australia-Hungary
A13: Mehmet's Ambition | B13: Starting as The Ottomans, own or have Core Eyalets own all the provinces required to form the Roman Empire before 1500. | C13: 0.003 | D13: I | E13: =(30-C13*100)*VLOOKUP($D13,Calc!$A$1:$C$6,3,FALSE) -> 891 | F13: =VLOOKUP(D13,Calc!$A$1:$B$6,2,FALSE) -> 6 | G13: =C13+F13/10000 -> 0.0036 | H13: =( (CODE(UPPER(LEFT(A13,1)))-64)+(CODE(UPPER(RIGHT(LEFT(A13,2),1)))-64)+(CODE(UPPER(RIGHT(LEFT(A13,3),1)))-64)+(CODE(UPPER(RIGHT(LEFT(A13,4),1)))-64)+(CODE(UPPER(RIGHT(LEFT(A13,5),1)))-64)+(CODE(UPPER(RIGHT(LEFT(A13,6),1)))-64)+(CODE(UPPER(RIGHT(LEFT(A13,7),1)))-64)+(CODE(UPPER(RIGHT(LEFT(A13,8),1)))-64) )/1000000 -> 5.8e-05 | I13: =G13+H13/10 -> 0.0036058 | J13: =IF($O13="","",I13) | K13: =IF($O13="",I13,"") -> 0.0036058 | L13: =F13-I13 -> 5.9963942 | M13: =IF($O13="","",L13) | N13: =IF($O13="",L13,"") -> 5.9963942 | Q13: Playing as the Ottomans | R13: - The year is before 1500 - 425 of the following provinces are owned by this country or a subject of type Core Eyalet: Needed provinces to form the Roman Empire | U13: =IF($D13="E",K13,"") | V13: =IF($D13="M",K13,"") | W13: =IF($D13="H",K13,"") | X13: =IF($D13="VE",K13,"") | Y13: =VLOOKUP($A13,Runs!$G:$G,1,FALSE) -> Mehmet's Ambition
A14: The Hungarian Games | B14: Starting as Hungary, win 23 battles with the Black Army against at least 12 different countries. | C14: 0.003 | D14: M | E14: =(30-C14*100)*VLOOKUP($D14,Calc!$A$1:$C$6,3,FALSE) -> 74.25 | F14: =VLOOKUP(D14,Calc!$A$1:$B$6,2,FALSE) -> 3 | G14: =C14+F14/10000 -> 0.0033 | H14: =( (CODE(UPPER(LEFT(A14,1)))-64)+(CODE(UPPER(RIGHT(LEFT(A14,2),1)))-64)+(CODE(UPPER(RIGHT(LEFT(A14,3),1)))-64)+(CODE(UPPER(RIGHT(LEFT(A14,4),1)))-64)+(CODE(UPPER(RIGHT(LEFT(A14,5),1)))-64)+(CODE(UPPER(RIGHT(LEFT(A14,6),1)))-64)+(CODE(UPPER(RIGHT(LEFT(A14,7),1)))-64)+(CODE(UPPER(RIGHT(LEFT(A14,8),1)))-64) )/1000000 -> 5.1e-05 | I14: =G14+H14/10 -> 0.0033051 | J14: =IF($O14="","",I14) -> 0.0033051 | K14: =IF($O14="",I14,"") | L14: =F14-I14 -> 2.9966949 | M14: =IF($O14="","",L14) -> 2.9966949 | N14: =IF($O14="",L14,"") | O14: Y | P14: Hungary | Q14: - Is Hungary | R14: - Any hired mercenary company: - Is *“Black Army”* - Is *“Black Army Reserves”* - Has won at least *23* battles with these mercenary companies. - For each enemy country, only a maximum of *3* battles are counted | S14: If there are multiple countries on the same side in the battle, only the country which is first in the tag order counts. Doesn't count battles fought when rented out as condottieri. The *“Black Army”* can be unlocked in the following ways, some of which also unlock the *“Black Army Reserves”*: | U14: =IF($D14="E",K14,"") | V14: =IF($D14="M",K14,"") | W14: =IF($D14="H",K14,"") | X14: =IF($D14="VE",K14,"") | Y14: =VLOOKUP($A14,Runs!$G:$G,1,FALSE) -> #N/A
A15: It's all coming together | B15: Complete the Incan mission tree (Sunset invasion missions excluded). | C15: 0.003 | D15: M | E15: =(30-C15*100)*VLOOKUP($D15,Calc!$A$1:$C$6,3,FALSE) -> 74.25 | F15: =VLOOKUP(D15,Calc!$A$1:$B$6,2,FALSE) -> 3 | G15: =C15+F15/10000 -> 0.0033 | H15: =( (CODE(UPPER(LEFT(A15,1)))-64)+(CODE(UPPER(RIGHT(LEFT(A15,2),1)))-64)+(CODE(UPPER(RIGHT(LEFT(A15,3),1)))-64)+(CODE(UPPER(RIGHT(LEFT(A15,4),1)))-64)+(CODE(UPPER(RIGHT(LEFT(A15,5),1)))-64)+(CODE(UPPER(RIGHT(LEFT(A15,6),1)))-64)+(CODE(UPPER(RIGHT(LEFT(A15,7),1)))-64)+(CODE(UPPER(RIGHT(LEFT(A15,8),1)))-64) )/1000000 -> 1.6e-05 | I15: =G15+H15/10 -> 0.0033016 | J15: =IF($O15="","",I15) -> 0.0033016 | K15: =IF($O15="",I15,"") | L15: =F15-I15 -> 2.9966984 | M15: =IF($O15="","",L15) -> 2.9966984 | N15: =IF($O15="",L15,"") | O15: Y | P15: Frankfurt | Q15: - Is *not* playing with a Random New World | R15: Has completed the following missions: - *“Rule of the Sun”* - *“Contact the Oracle”* - *“Defeat the Wanka”* - *“Our Chimuan Rivals”* - *“The Ground Shaker”* - *“Conquer Cajamarca”* - *“Take Over Quito”* - *“Defy the Qollans”* - *“Seize Southern Fringes”* - *“Recruit the Chanka”* - *“Seize the Chincha”* - *“Down the Altiplano”* - *“Promote Runasimi”* - *“Development of the Mitma”* - *“Awka Kamayuq”* - *“The Big Ears”* - *“The Zeq'e System”* - *“The Oracle of Pachacamac”* - *“Four Quarters Together”* - *“The Qollqas”* - *“Construct New Kallanka”* - *“The Solar Cult”* - *“Reform Religion”* - *“Temples to Viracocha”* - *“Imperial Infrastructure”* - *“Qhapaq Ñan”* - *“Imperial Frontiers”* - *“Incan Terracing”* - *“Idols of our Subjects”* - *“Among the Mountaintops”* - *“Navel of the Universe”* - *“Haucaypata”* - *“Collect the Mita”* - *“Sweat of the Sun”* - *“Tears of the Moon”* - *“Renovate Cuzco”* - *“Secondary Capital”* - *“Incan Weaving”* - *“Expand into the Jungle”* - *“Recruit Bowmen”* | U15: =IF($D15="E",K15,"") | V15: =IF($D15="M",K15,"") | W15: =IF($D15="H",K15,"") | X15: =IF($D15="VE",K15,"") | Y15: =VLOOKUP($A15,Runs!$G:$G,1,FALSE) -> It's all coming together
A16: Hanukkah Mutapa | B16: Starting as Mutapa, convert to Judaism and celebrate a festival. | C16: 0.003 | D16: M | E16: =(30-C16*100)*VLOOKUP($D16,Calc!$A$1:$C$6,3,FALSE) -> 74.25 | F16: =VLOOKUP(D16,Calc!$A$1:$B$6,2,FALSE) -> 3 | G16: =C16+F16/10000 -> 0.0033 | H16: =( (CODE(UPPER(LEFT(A16,1)))-64)+(CODE(UPPER(RIGHT(LEFT(A16,2),1)))-64)+(CODE(UPPER(RIGHT(LEFT(A16,3),1)))-64)+(CODE(UPPER(RIGHT(LEFT(A16,4),1)))-64)+(CODE(UPPER(RIGHT(LEFT(A16,5),1)))-64)+(CODE(UPPER(RIGHT(LEFT(A16,6),1)))-64)+(CODE(UPPER(RIGHT(LEFT(A16,7),1)))-64)+(CODE(UPPER(RIGHT(LEFT(A16,8),1)))-64) )/1000000 -> 7.5e-05 | I16: =G16+H16/10 -> 0.0033075 | J16: =IF($O16="","",I16) -> 0.0033075 | K16: =IF($O16="",I16,"") | L16: =F16-I16 -> 2.9966925 | M16: =IF($O16="","",L16) -> 2.9966925 | N16: =IF($O16="",L16,"") | O16: Y | P16: Mutapa | Q16: Playing as Mutapa | R16: - Religion is Jewish - Has used the Jewish religion action *“Celebrate Festival”* | S16: This achievement is misspelled as *“Hannukah Mutapa”* in the steam version of the game. At the start of the game the 2 only Jewish provinces are in Ethiopia, due to Ethiopia's missions the AI will always pick the option to temporarily accept Jewish religion, giving you 25 years to take them. Mutapa's gold mines should allow you to go over force limit and quickly declare a war of conquest against Kilwa despite the technology disadvantage. With additional 3 gold mines in Butua after annexing vassal Butua and conquering Sofala and Kilwa even more mercenaries over force limit can be paid. Focus on military mana to not fall further behind Ethiopia and nations lying in the way to the jewish provinces. | U16: =IF($D16="E",K16,"") | V16: =IF($D16="M",K16,"") | W16: =IF($D16="H",K16,"") | X16: =IF($D16="VE",K16,"") | Y16: =VLOOKUP($A16,Runs!$G:$G,1,FALSE) -> Hanukkah Mutapa
A17: The Eagle flies alone | B17: Starting as Hisn Kayfa, reach a forcelimit of 500k. | C17: 0.003 | D17: VH | E17: =(30-C17*100)*VLOOKUP($D17,Calc!$A$1:$C$6,3,FALSE) -> 297 | F17: =VLOOKUP(D17,Calc!$A$1:$B$6,2,FALSE) -> 5 | G17: =C17+F17/10000 -> 0.0035 | H17: =( (CODE(UPPER(LEFT(A17,1)))-64)+(CODE(UPPER(RIGHT(LEFT(A17,2),1)))-64)+(CODE(UPPER(RIGHT(LEFT(A17,3),1)))-64)+(CODE(UPPER(RIGHT(LEFT(A17,4),1)))-64)+(CODE(UPPER(RIGHT(LEFT(A17,5),1)))-64)+(CODE(UPPER(RIGHT(LEFT(A17,6),1)))-64)+(CODE(UPPER(RIGHT(LEFT(A17,7),1)))-64)+(CODE(UPPER(RIGHT(LEFT(A17,8),1)))-64) )/1000000 -> 2.6e-05 | I17: =G17+H17/10 -> 0.0035026 | J17: =IF($O17="","",I17) -> 0.0035026 | K17: =IF($O17="",I17,"") | L17: =F17-I17 -> 4.9964974 | M17: =IF($O17="","",L17) -> 4.9964974 | N17: =IF($O17="",L17,"") | O17: Y | P17: Hisn Kayfa | Q17: - Is Hisn Kayfa | R17: - Land force limit is at least 500 | U17: =IF($D17="E",K17,"") | V17: =IF($D17="M",K17,"") | W17: =IF($D17="H",K17,"") | X17: =IF($D17="VE",K17,"") | Y17: =VLOOKUP($A17,Runs!$G:$G,1,FALSE) -> #N/A
A18: Quizquiz Pro Quo | B18: As Quizquiz, have your capital in the Anjou province. | C18: 0.003 | D18: VH | E18: =(30-C18*100)*VLOOKUP($D18,Calc!$A$1:$C$6,3,FALSE) -> 297 | F18: =VLOOKUP(D18,Calc!$A$1:$B$6,2,FALSE) -> 5 | G18: =C18+F18/10000 -> 0.0035 | H18: =( (CODE(UPPER(LEFT(A18,1)))-64)+(CODE(UPPER(RIGHT(LEFT(A18,2),1)))-64)+(CODE(UPPER(RIGHT(LEFT(A18,3),1)))-64)+(CODE(UPPER(RIGHT(LEFT(A18,4),1)))-64)+(CODE(UPPER(RIGHT(LEFT(A18,5),1)))-64)+(CODE(UPPER(RIGHT(LEFT(A18,6),1)))-64)+(CODE(UPPER(RIGHT(LEFT(A18,7),1)))-64)+(CODE(UPPER(RIGHT(LEFT(A18,8),1)))-64) )/1000000 -> 0.000146 | I18: =G18+H18/10 -> 0.0035146 | J18: =IF($O18="","",I18) -> 0.0035146 | K18: =IF($O18="",I18,"") | L18: =F18-I18 -> 4.9964854 | M18: =IF($O18="","",L18) -> 4.9964854 | N18: =IF($O18="",L18,"") | O18: Y | P18: Quizquiz | Q18: - Playing as Quizquiz - *Not* using a random New World | R18: - Is Quizquiz - Capital is Anjou (178) | S18: This achievement is only visible if the Leviathan DLC is active, but it can be achieved even without the DLC. | U18: =IF($D18="E",K18,"") | V18: =IF($D18="M",K18,"") | W18: =IF($D18="H",K18,"") | X18: =IF($D18="VE",K18,"") | Y18: =VLOOKUP($A18,Runs!$G:$G,1,FALSE) -> Quizquiz Pro Quo
A19: Mets Hayk | B19: Starting as Karabakh, own, core, and convert to Coptic the borders of Great Armenia. | C19: 0.003 | D19: VH | E19: =(30-C19*100)*VLOOKUP($D19,Calc!$A$1:$C$6,3,FALSE) -> 297 | F19: =VLOOKUP(D19,Calc!$A$1:$B$6,2,FALSE) -> 5 | G19: =C19+F19/10000 -> 0.0035 | H19: =( (CODE(UPPER(LEFT(A19,1)))-64)+(CODE(UPPER(RIGHT(LEFT(A19,2),1)))-64)+(CODE(UPPER(RIGHT(LEFT(A19,3),1)))-64)+(CODE(UPPER(RIGHT(LEFT(A19,4),1)))-64)+(CODE(UPPER(RIGHT(LEFT(A19,5),1)))-64)+(CODE(UPPER(RIGHT(LEFT(A19,6),1)))-64)+(CODE(UPPER(RIGHT(LEFT(A19,7),1)))-64)+(CODE(UPPER(RIGHT(LEFT(A19,8),1)))-64) )/1000000 -> 5.9e-05 | I19: =G19+H19/10 -> 0.0035059 | J19: =IF($O19="","",I19) -> 0.0035059 | K19: =IF($O19="",I19,"") | L19: =F19-I19 -> 4.9964941 | M19: =IF($O19="","",L19) -> 4.9964941 | N19: =IF($O19="",L19,"") | O19: Y | P19: Karabakh | Q19: - Playing as Karabakh | R19: - Religion is Coptic - Owns core provinces following the Coptic faith: - - Erzurum (331) - Yerevan (419) - Melikates (2202) - Nakhchivan (2205) - Erzincan (2305) - Van (2307) - Mush (2306) - Bayazid (2306) - Adana (327) 1 province in each of the following areas is owned, cored, and follows the Coptic faith: - - Azerbaijan - Shahrizor - Al Jazira - Dulkadir - Aleppo - Syria - Syrian Desert | S19: If you can get Mamluks to support your independence, the first war is relatively easy. Once you've grown moderately, try to get European allies as soon as possible to help taking provinces from Ottomans and Mamluks. | U19: =IF($D19="E",K19,"") | V19: =IF($D19="M",K19,"") | W19: =IF($D19="H",K19,"") | X19: =IF($D19="VE",K19,"") | Y19: =VLOOKUP($A19,Runs!$G:$G,1,FALSE) -> #N/A
A20: Crossing the Finnish Line | B20: Release and play as Finland in 1444 and have a direct land connection to the Cape while your capital is in Nyland/Uusimaa. | C20: 0.003 | D20: VH | E20: =(30-C20*100)*VLOOKUP($D20,Calc!$A$1:$C$6,3,FALSE) -> 297 | F20: =VLOOKUP(D20,Calc!$A$1:$B$6,2,FALSE) -> 5 | G20: =C20+F20/10000 -> 0.0035 | H20: =( (CODE(UPPER(LEFT(A20,1)))-64)+(CODE(UPPER(RIGHT(LEFT(A20,2),1)))-64)+(CODE(UPPER(RIGHT(LEFT(A20,3),1)))-64)+(CODE(UPPER(RIGHT(LEFT(A20,4),1)))-64)+(CODE(UPPER(RIGHT(LEFT(A20,5),1)))-64)+(CODE(UPPER(RIGHT(LEFT(A20,6),1)))-64)+(CODE(UPPER(RIGHT(LEFT(A20,7),1)))-64)+(CODE(UPPER(RIGHT(LEFT(A20,8),1)))-64) )/1000000 -> 0.000104 | I20: =G20+H20/10 -> 0.0035104 | J20: =IF($O20="","",I20) -> 0.0035104 | K20: =IF($O20="",I20,"") | L20: =F20-I20 -> 4.9964896 | M20: =IF($O20="","",L20) -> 4.9964896 | N20: =IF($O20="",L20,"") | O20: Y | P20: Sweden | Q20: Playing as Sweden | R20: - Finland has been released in 1444 - Is *or* was Finland - Capital is Nyland(28) - Owns Cape(1177) - There exists a land connection of owned provinces between the capital and Cape(1177) | S20: The land connection can go over strait crossings (it is recommended to avoid taking Suez as to not anger the Ottomans). Finland must be released in 1444, but you do not have to play as them in 1444. Consider making them a vassal, feeding them the provinces required, annexing them, the releasing and playing as them after annexing them. This gives you access to the Sweden mission tree and power base to work with. | U20: =IF($D20="E",K20,"") | V20: =IF($D20="M",K20,"") | W20: =IF($D20="H",K20,"") | X20: =IF($D20="VE",K20,"") | Y20: =VLOOKUP($A20,Runs!$G:$G,1,FALSE) -> #N/A
A21: All Blue | B21: As Portugal, all of Europe is owned by you or blue European countries that exist in 1444. | C21: 0.003 | D21: VH | E21: =(30-C21*100)*VLOOKUP($D21,Calc!$A$1:$C$6,3,FALSE) -> 297 | F21: =VLOOKUP(D21,Calc!$A$1:$B$6,2,FALSE) -> 5 | G21: =C21+F21/10000 -> 0.0035 | H21: =( (CODE(UPPER(LEFT(A21,1)))-64)+(CODE(UPPER(RIGHT(LEFT(A21,2),1)))-64)+(CODE(UPPER(RIGHT(LEFT(A21,3),1)))-64)+(CODE(UPPER(RIGHT(LEFT(A21,4),1)))-64)+(CODE(UPPER(RIGHT(LEFT(A21,5),1)))-64)+(CODE(UPPER(RIGHT(LEFT(A21,6),1)))-64)+(CODE(UPPER(RIGHT(LEFT(A21,7),1)))-64)+(CODE(UPPER(RIGHT(LEFT(A21,8),1)))-64) )/1000000 -> 3.3e-05 | I21: =G21+H21/10 -> 0.0035033 | J21: =IF($O21="","",I21) -> 0.0035033 | K21: =IF($O21="",I21,"") | L21: =F21-I21 -> 4.9964967 | M21: =IF($O21="","",L21) -> 4.9964967 | N21: =IF($O21="",L21,"") | O21: Y | P21: Portugal | Q21: Playing as Portugal | R21: - Is Portugal - All provinces in Europe are owned by one of the following countries: - Portugal - Avaria - Bavaria - Bourbonnais - Bremen - Dithmarschen - Dortmund - Flanders - France - Glogow - Herzegovina - Hesse - Imereti - Ingolstadt - Karaman - Landshut - Lorraine - Mecklenburg - Munich - Naxos - Norway - Odoyev - Perugia - Provence - Prussia - Saluzzo - Sardinia-Piedmont - Sweden - The Knights - The Palatinate - Thuringia - Trebizond - Tyrconnell - Urbino - Venice | S21: Note that Bavaria, Prussia and Sardinia-Piedmont count even though they don't exist in 1444. Make sure that none of the blue countries fulfill the conditions to form something which is not allowed. | U21: =IF($D21="E",K21,"") | V21: =IF($D21="M",K21,"") | W21: =IF($D21="H",K21,"") | X21: =IF($D21="VE",K21,"") | Y21: =VLOOKUP($A21,Runs!$G:$G,1,FALSE) -> #N/A
A22: Let It Go! | B22: Starting as Norway, have your capital in the Canada region while not owning any province in Scandinavia and not playing as a released subject. | C22: 0.004 | D22: E | E22: =(30-C22*100)*VLOOKUP($D22,Calc!$A$1:$C$6,3,FALSE) -> 29.6 | F22: =VLOOKUP(D22,Calc!$A$1:$B$6,2,FALSE) -> 2 | G22: =C22+F22/10000 -> 0.0042 | H22: =( (CODE(UPPER(LEFT(A22,1)))-64)+(CODE(UPPER(RIGHT(LEFT(A22,2),1)))-64)+(CODE(UPPER(RIGHT(LEFT(A22,3),1)))-64)+(CODE(UPPER(RIGHT(LEFT(A22,4),1)))-64)+(CODE(UPPER(RIGHT(LEFT(A22,5),1)))-64)+(CODE(UPPER(RIGHT(LEFT(A22,6),1)))-64)+(CODE(UPPER(RIGHT(LEFT(A22,7),1)))-64)+(CODE(UPPER(RIGHT(LEFT(A22,8),1)))-64) )/1000000 -> 9e-06 | I22: =G22+H22/10 -> 0.0042009 | J22: =IF($O22="","",I22) -> 0.0042009 | K22: =IF($O22="",I22,"") | L22: =F22-I22 -> 1.9957991 | M22: =IF($O22="","",L22) -> 1.9957991 | N22: =IF($O22="",L22,"") | O22: Y | P22: Norway | Q22: Playing as Norway | R22: - *Not* playing as a released vassal - Capital is in the Canada region - Owns no province in the Scandinavia region | S22: Forming countries is allowed, but playing as a released colonial nation or switching to a different country is not allowed. The easiest way to be rid of provinces in Europe is to release Sápmi and Iceland as subjects, giving them all other provinces in Europe other than your capital. At that point, moving your capital into America is allowed, and then giving away the last European province should complete the achievement. | U22: =IF($D22="E",K22,"") | V22: =IF($D22="M",K22,"") | W22: =IF($D22="H",K22,"") | X22: =IF($D22="VE",K22,"") | Y22: =VLOOKUP($A22,Runs!$G:$G,1,FALSE) -> #N/A
A23: Breadbasket of the World | B23: As the Mamluks, export grain to every continent at least once. | C23: 0.004 | D23: E | E23: =(30-C23*100)*VLOOKUP($D23,Calc!$A$1:$C$6,3,FALSE) -> 29.6 | F23: =VLOOKUP(D23,Calc!$A$1:$B$6,2,FALSE) -> 2 | G23: =C23+F23/10000 -> 0.0042 | H23: =( (CODE(UPPER(LEFT(A23,1)))-64)+(CODE(UPPER(RIGHT(LEFT(A23,2),1)))-64)+(CODE(UPPER(RIGHT(LEFT(A23,3),1)))-64)+(CODE(UPPER(RIGHT(LEFT(A23,4),1)))-64)+(CODE(UPPER(RIGHT(LEFT(A23,5),1)))-64)+(CODE(UPPER(RIGHT(LEFT(A23,6),1)))-64)+(CODE(UPPER(RIGHT(LEFT(A23,7),1)))-64)+(CODE(UPPER(RIGHT(LEFT(A23,8),1)))-64) )/1000000 -> 5.2e-05 | I23: =G23+H23/10 -> 0.0042052 | J23: =IF($O23="","",I23) -> 0.0042052 | K23: =IF($O23="",I23,"") | L23: =F23-I23 -> 1.9957948 | M23: =IF($O23="","",L23) -> 1.9957948 | N23: =IF($O23="",L23,"") | O23: Y | P23: Mamluks | R23: - Is *or* was the Mamluks - Has used the "Export Grain" diplomatic action on at least one country on each of the following continents: - - Europe - Oceania - North America - South America - Africa - Asia | S23: The country's continent is determined based on the location of its capital. To use "Export grain", the target must be a subject or ally of the Mamluks. This can be an issue in the colonial regions. Its thus recommended to colonize yourself. | U23: =IF($D23="E",K23,"") | V23: =IF($D23="M",K23,"") | W23: =IF($D23="H",K23,"") | X23: =IF($D23="VE",K23,"") | Y23: =VLOOKUP($A23,Runs!$G:$G,1,FALSE) -> Breadbasket of the World
A24: Veritas Vincit | B24: Starting as Bohemia, make Hussite the official faith of the Empire and become the Emperor. | C24: 0.004 | D24: H | E24: =(30-C24*100)*VLOOKUP($D24,Calc!$A$1:$C$6,3,FALSE) -> 148 | F24: =VLOOKUP(D24,Calc!$A$1:$B$6,2,FALSE) -> 4 | G24: =C24+F24/10000 -> 0.0044 | H24: =( (CODE(UPPER(LEFT(A24,1)))-64)+(CODE(UPPER(RIGHT(LEFT(A24,2),1)))-64)+(CODE(UPPER(RIGHT(LEFT(A24,3),1)))-64)+(CODE(UPPER(RIGHT(LEFT(A24,4),1)))-64)+(CODE(UPPER(RIGHT(LEFT(A24,5),1)))-64)+(CODE(UPPER(RIGHT(LEFT(A24,6),1)))-64)+(CODE(UPPER(RIGHT(LEFT(A24,7),1)))-64)+(CODE(UPPER(RIGHT(LEFT(A24,8),1)))-64) )/1000000 -> 6.2e-05 | I24: =G24+H24/10 -> 0.0044062 | J24: =IF($O24="","",I24) -> 0.0044062 | K24: =IF($O24="",I24,"") | L24: =F24-I24 -> 3.9955938 | M24: =IF($O24="","",L24) -> 3.9955938 | N24: =IF($O24="",L24,"") | O24: Y | P24: Bohemia | Q24: - Is Bohemia | R24: - Is the Holy Roman Emperor - The Holy Roman Empire's official religion is Hussite - The religion of the Holy Roman Empire is fixed | S24: Hussite can become the official religion in the imperial incident "*The Hussite Protest*", which gets triggered if hussite countries own at least 80% as many HRE provinces as non-hussite countries when the event *The Evangelical Union is Victorious* happens. | U24: =IF($D24="E",K24,"") | V24: =IF($D24="M",K24,"") | W24: =IF($D24="H",K24,"") | X24: =IF($D24="VE",K24,"") | Y24: =VLOOKUP($A24,Runs!$G:$G,1,FALSE) -> #N/A
A25: Purify the Temple | B25: Starting as Riga, enact the Salvific Plutocracy government reform and raid the heretic church of Rome. | C25: 0.004 | D25: H | E25: =(30-C25*100)*VLOOKUP($D25,Calc!$A$1:$C$6,3,FALSE) -> 148 | F25: =VLOOKUP(D25,Calc!$A$1:$B$6,2,FALSE) -> 4 | G25: =C25+F25/10000 -> 0.0044 | H25: =( (CODE(UPPER(LEFT(A25,1)))-64)+(CODE(UPPER(RIGHT(LEFT(A25,2),1)))-64)+(CODE(UPPER(RIGHT(LEFT(A25,3),1)))-64)+(CODE(UPPER(RIGHT(LEFT(A25,4),1)))-64)+(CODE(UPPER(RIGHT(LEFT(A25,5),1)))-64)+(CODE(UPPER(RIGHT(LEFT(A25,6),1)))-64)+(CODE(UPPER(RIGHT(LEFT(A25,7),1)))-64)+(CODE(UPPER(RIGHT(LEFT(A25,8),1)))-64) )/1000000 -> 8.3e-05 | I25: =G25+H25/10 -> 0.0044083 | J25: =IF($O25="","",I25) -> 0.0044083 | K25: =IF($O25="",I25,"") | L25: =F25-I25 -> 3.9955917 | M25: =IF($O25="","",L25) -> 3.9955917 | N25: =IF($O25="",L25,"") | O25: Y | P25: Riga | Q25: Playing as Riga | R25: - Has enacted the Salvific Plutocracy government reform - Raided the province Roma (118) with the peace term *“Raid Heretic Churches”* | S25: *“Raid Heretic Churches”* always selects Roma (118) as long as it has a Church or Cathedral. You need to convert to another Christian religion to enact Salvific Plutocracy. *“Raid Heretic Churches”* can also be chosen for secondary war participants. | U25: =IF($D25="E",K25,"") | V25: =IF($D25="M",K25,"") | W25: =IF($D25="H",K25,"") | X25: =IF($D25="VE",K25,"") | Y25: =VLOOKUP($A25,Runs!$G:$G,1,FALSE) -> #N/A
A26: One nation to rule them all | B26: As Saruhan, have at least 9 loyal vassals with at least 100 development each. | C26: 0.004 | D26: H | E26: =(30-C26*100)*VLOOKUP($D26,Calc!$A$1:$C$6,3,FALSE) -> 148 | F26: =VLOOKUP(D26,Calc!$A$1:$B$6,2,FALSE) -> 4 | G26: =C26+F26/10000 -> 0.0044 | H26: =( (CODE(UPPER(LEFT(A26,1)))-64)+(CODE(UPPER(RIGHT(LEFT(A26,2),1)))-64)+(CODE(UPPER(RIGHT(LEFT(A26,3),1)))-64)+(CODE(UPPER(RIGHT(LEFT(A26,4),1)))-64)+(CODE(UPPER(RIGHT(LEFT(A26,5),1)))-64)+(CODE(UPPER(RIGHT(LEFT(A26,6),1)))-64)+(CODE(UPPER(RIGHT(LEFT(A26,7),1)))-64)+(CODE(UPPER(RIGHT(LEFT(A26,8),1)))-64) )/1000000 -> 4.6e-05 | I26: =G26+H26/10 -> 0.0044046 | J26: =IF($O26="","",I26) | K26: =IF($O26="",I26,"") -> 0.0044046 | L26: =F26-I26 -> 3.9955954 | M26: =IF($O26="","",L26) | N26: =IF($O26="",L26,"") -> 3.9955954 | R26: - Is Saruhan - 9 countries fulfill the following conditions: - is a vassal of Saruhan - has less than *50%* liberty desire - has at least *100* development | S26: Saruhan's core starts under the control of the Ottomans. Suggested strategy: expand rapidly as you normally would with the Ottomans until you have ~1200 development. Then, plan to release-and-play as Saruhan, taking most of Otto's lands. To do this, you will need to release Saruhan as vassal, wait 10 years, start to annex (to designate cores), feed it land, finalize annexation, and then release-and-play. You can cheese the release-and-play by feeding past the point of loyalty and then applying all available annexation cost reductions (Acquire Subjects mission, Influence idea, Amirs privilege, as well as any possible Policies). Make sure you wait until the last day of the month to do this, or else annexation progress will drop and you will be unable to proceed. As long as your annexation progress is above 100 on the month tick, it won't matter if liberty desire is over 50%. Once you have reannexed, you will be able to release-and-play. Ideally you will then own almost all Ottoman lands, making independence relatively easy to pursue. From there, you need to obtain 9 loyal vassals (NOT marches, NOT client states) with 100+ development. Rather than directly subjugating enemies to meet the vassal count, it is suggested that the player conquer and then release vassals; this avoids the forced vassalization malus. To help reduce liberty desire and thus total development needed, choose the relevant policies, and be sure to get the Splendor abilities in the Age of Revolutions (Anti-Revolutionary Zeal + Loyal Subjects). Upon release, you will no longer have the Ottoman government form, and should choose Iqta. Then on your goverment tab choose Lenient Taxation, which provides another Liberty Desire reduction. Note that during the feeding of Saruhan and following your transition to playing as them, the Ottomans will likely be severely weakened and thus open to attack. Keep this in mind, perhaps securing treaties in advance or locking in allies (though too many allies for Otto will make subsequent independence harder). Ideally you will be able to secure independence support from a rival. | U26: =IF($D26="E",K26,"") | V26: =IF($D26="M",K26,"") | W26: =IF($D26="H",K26,"") -> 0.0044046 | X26: =IF($D26="VE",K26,"") | Y26: =VLOOKUP($A26,Runs!$G:$G,1,FALSE) -> One nation to rule them all
A27: New, New Deli | B27: As Deli, have your capital in the Delhi province. | C27: 0.004 | D27: H | E27: =(30-C27*100)*VLOOKUP($D27,Calc!$A$1:$C$6,3,FALSE) -> 148 | F27: =VLOOKUP(D27,Calc!$A$1:$B$6,2,FALSE) -> 4 | G27: =C27+F27/10000 -> 0.0044 | H27: =( (CODE(UPPER(LEFT(A27,1)))-64)+(CODE(UPPER(RIGHT(LEFT(A27,2),1)))-64)+(CODE(UPPER(RIGHT(LEFT(A27,3),1)))-64)+(CODE(UPPER(RIGHT(LEFT(A27,4),1)))-64)+(CODE(UPPER(RIGHT(LEFT(A27,5),1)))-64)+(CODE(UPPER(RIGHT(LEFT(A27,6),1)))-64)+(CODE(UPPER(RIGHT(LEFT(A27,7),1)))-64)+(CODE(UPPER(RIGHT(LEFT(A27,8),1)))-64) )/1000000 -> 3.2e-05 | I27: =G27+H27/10 -> 0.0044032 | J27: =IF($O27="","",I27) | K27: =IF($O27="",I27,"") -> 0.0044032 | L27: =F27-I27 -> 3.9955968 | M27: =IF($O27="","",L27) | N27: =IF($O27="",L27,"") -> 3.9955968 | Q27: - Playing as Deli - *Not* using a random New World | R27: - Is Deli - Capital is Delhi (522) | S27: This achievement is only visible if the Leviathan DLC is active, but it can be achieved even without the DLC. Can be done in 5–10 years, depending on RNG. Broadly: get as many allies as you can to deter coalition. Vassalize an OPM adjacent to Delhi, preferably Garhwal or Sirmur to even the AE. Then conquer Delhi (and some needed to connect). Give every other territories to vassals, or sell them to other countries. In a war, lose your capital Riau, after that Delhi will be the new capital. | U27: =IF($D27="E",K27,"") | V27: =IF($D27="M",K27,"") | W27: =IF($D27="H",K27,"") -> 0.0044032 | X27: =IF($D27="VE",K27,"") | Y27: =VLOOKUP($A27,Runs!$G:$G,1,FALSE) -> New, New Deli
A28: Knights of the Caribbean | B28: Starting as the Knights, own the Caribbean and every island in the Mediterranean. (Colonies are NOT allowed) | C28: 0.004 | D28: H | E28: =(30-C28*100)*VLOOKUP($D28,Calc!$A$1:$C$6,3,FALSE) -> 148 | F28: =VLOOKUP(D28,Calc!$A$1:$B$6,2,FALSE) -> 4 | G28: =C28+F28/10000 -> 0.0044 | H28: =( (CODE(UPPER(LEFT(A28,1)))-64)+(CODE(UPPER(RIGHT(LEFT(A28,2),1)))-64)+(CODE(UPPER(RIGHT(LEFT(A28,3),1)))-64)+(CODE(UPPER(RIGHT(LEFT(A28,4),1)))-64)+(CODE(UPPER(RIGHT(LEFT(A28,5),1)))-64)+(CODE(UPPER(RIGHT(LEFT(A28,6),1)))-64)+(CODE(UPPER(RIGHT(LEFT(A28,7),1)))-64)+(CODE(UPPER(RIGHT(LEFT(A28,8),1)))-64) )/1000000 -> 5.6e-05 | I28: =G28+H28/10 -> 0.0044056 | J28: =IF($O28="","",I28) -> 0.0044056 | K28: =IF($O28="",I28,"") | L28: =F28-I28 -> 3.9955944 | M28: =IF($O28="","",L28) -> 3.9955944 | N28: =IF($O28="",L28,"") | O28: Y | P28: Knights | Q28: Playing as The Knights | R28: - Owns all provinces in the Caribbean region. Owns the following core provinces: - Rhodes (320) - Cyprus (321) - Crete (163) - Naxos (164) - Chios (2348) - Euboea (3003) - Lesbos (4700) - Cephalonia (4698) - Corfu (142) - Syracuse (2982) - Messina (124) - Palermo (125) - Girgenti (4737) - Trapani (4736) - Djerba (2954) - Malta (126) - Sassari (127) - Corsica (1247) - Menorca (4559) - Ibiza (4560) - Mallorca (333) - Venezia (112) - Arborea (4735) - Cagliari (2986) Map of the Mediterranean provinces: The needed mediterranean provinces | S28: Bermuda is also part of the Caribbean region even though it is not part of the Colonial Caribbean colonial region. | U28: =IF($D28="E",K28,"") | V28: =IF($D28="M",K28,"") | W28: =IF($D28="H",K28,"") | X28: =IF($D28="VE",K28,"") | Y28: =VLOOKUP($A28,Runs!$G:$G,1,FALSE) -> #N/A
A29: Fugger Banking | B29: As Augsburg, subsidize 3 Great Powers 20% of their income while having less than 20 provinces. | C29: 0.004 | D29: H | E29: =(30-C29*100)*VLOOKUP($D29,Calc!$A$1:$C$6,3,FALSE) -> 148 | F29: =VLOOKUP(D29,Calc!$A$1:$B$6,2,FALSE) -> 4 | G29: =C29+F29/10000 -> 0.0044 | H29: =( (CODE(UPPER(LEFT(A29,1)))-64)+(CODE(UPPER(RIGHT(LEFT(A29,2),1)))-64)+(CODE(UPPER(RIGHT(LEFT(A29,3),1)))-64)+(CODE(UPPER(RIGHT(LEFT(A29,4),1)))-64)+(CODE(UPPER(RIGHT(LEFT(A29,5),1)))-64)+(CODE(UPPER(RIGHT(LEFT(A29,6),1)))-64)+(CODE(UPPER(RIGHT(LEFT(A29,7),1)))-64)+(CODE(UPPER(RIGHT(LEFT(A29,8),1)))-64) )/1000000 -> 3.4e-05 | I29: =G29+H29/10 -> 0.0044034 | J29: =IF($O29="","",I29) -> 0.0044034 | K29: =IF($O29="",I29,"") | L29: =F29-I29 -> 3.9955966 | M29: =IF($O29="","",L29) -> 3.9955966 | N29: =IF($O29="",L29,"") | O29: Y | P29: Augsburg | Q29: - Playing as Augsburg | R29: - Is Augsburg - less than 20 provinces - Subsidize 3 Great Powers at least 20% of their income. | S29: The subsidies also count as income, so the subsidies have to be 25% of the income before subsidies. The total income can be seen in the Income Comparison page in the ledger. The Country page doesn't show all income sources. You can subsidize up to 50% of your income to each country, which means you need to reach at least half the income of the 3 poorest great powers. A good way to get it quickly is to get a hold of the Inntal or Eger goldmine and to develop it. | U29: =IF($D29="E",K29,"") | V29: =IF($D29="M",K29,"") | W29: =IF($D29="H",K29,"") | X29: =IF($D29="VE",K29,"") | Y29: =VLOOKUP($A29,Runs!$G:$G,1,FALSE) -> #N/A
A30: Almost Prussian Blue | B30: Starting as the Livonian Order, form Livonia and own the territory of the North German Confederation as core provinces. | C30: 0.004 | D30: H | E30: =(30-C30*100)*VLOOKUP($D30,Calc!$A$1:$C$6,3,FALSE) -> 148 | F30: =VLOOKUP(D30,Calc!$A$1:$B$6,2,FALSE) -> 4 | G30: =C30+F30/10000 -> 0.0044 | H30: =( (CODE(UPPER(LEFT(A30,1)))-64)+(CODE(UPPER(RIGHT(LEFT(A30,2),1)))-64)+(CODE(UPPER(RIGHT(LEFT(A30,3),1)))-64)+(CODE(UPPER(RIGHT(LEFT(A30,4),1)))-64)+(CODE(UPPER(RIGHT(LEFT(A30,5),1)))-64)+(CODE(UPPER(RIGHT(LEFT(A30,6),1)))-64)+(CODE(UPPER(RIGHT(LEFT(A30,7),1)))-64)+(CODE(UPPER(RIGHT(LEFT(A30,8),1)))-64) )/1000000 -> 6.4e-05 | I30: =G30+H30/10 -> 0.0044064 | J30: =IF($O30="","",I30) | K30: =IF($O30="",I30,"") -> 0.0044064 | L30: =F30-I30 -> 3.9955936 | M30: =IF($O30="","",L30) | N30: =IF($O30="",L30,"") -> 3.9955936 | Q30: Playing as Livonian Order | R30: - Is Livonia Own and core all the following provinces: - East Prussia area - West Prussia area - Silesia area - North Germany region except the areas Bohemia, Moravia and Erzgebirge - Chelmno (1859) - Inowroclaw (4523) - Gniezno (4526) - Poznan (254) - Notec (2963) - East Frisia (1931) Map of the provinces: | U30: =IF($D30="E",K30,"") | V30: =IF($D30="M",K30,"") | W30: =IF($D30="H",K30,"") -> 0.0044064 | X30: =IF($D30="VE",K30,"") | Y30: =VLOOKUP($A30,Runs!$G:$G,1,FALSE) -> Almost Prussian Blue
A31: Where are the penguins? | B31: As a Malagasy country, unite Madagascar and hold all the most southern provinces of the world. | C31: 0.004 | D31: M | E31: =(30-C31*100)*VLOOKUP($D31,Calc!$A$1:$C$6,3,FALSE) -> 74 | F31: =VLOOKUP(D31,Calc!$A$1:$B$6,2,FALSE) -> 3 | G31: =C31+F31/10000 -> 0.0043 | H31: =( (CODE(UPPER(LEFT(A31,1)))-64)+(CODE(UPPER(RIGHT(LEFT(A31,2),1)))-64)+(CODE(UPPER(RIGHT(LEFT(A31,3),1)))-64)+(CODE(UPPER(RIGHT(LEFT(A31,4),1)))-64)+(CODE(UPPER(RIGHT(LEFT(A31,5),1)))-64)+(CODE(UPPER(RIGHT(LEFT(A31,6),1)))-64)+(CODE(UPPER(RIGHT(LEFT(A31,7),1)))-64)+(CODE(UPPER(RIGHT(LEFT(A31,8),1)))-64) )/1000000 -> 4.6e-05 | I31: =G31+H31/10 -> 0.0043046 | J31: =IF($O31="","",I31) -> 0.0043046 | K31: =IF($O31="",I31,"") | L31: =F31-I31 -> 2.9956954 | M31: =IF($O31="","",L31) -> 2.9956954 | N31: =IF($O31="",L31,"") | O31: Y | P31: Imerina | Q31: *Not* using a random New World Playing as one of the following countries: - Sakalava - Betsimisaraka - Imerina - Mahafaly - Antemoro | R31: Is one of the following countries: - Sakalava - Betsimisaraka - Imerina - Mahafaly - Antemoro Own and core all provinces in the following areas: - Madagascar Highlands - Betsimasaraka - Sakalava - Southern Madagascar Own or have a non-tributary subject own all the following provinces: - Cape (1177) - Swellendam (1179) - Algoa Bay (833) - Xhosa (1180) - Wadjuk (1084) - Minang (2727) - Nukunu (2736) - Kaurna (1086) - Gunditjmara (2735) - Wurundjeri (1087) - Yuin (2734) - Peerapper (4869) - Pyemmairrener (4868) - Paredarerme (1085) - Tharawal (4858) - Ata Whenua (1246) - Timaru (1109) - Kawesqar (783) - Tierra del Fuego (782) - Florida Blanca (2869) - Falklands (1095) - South Georgia (2025) Map of the provinces: | S31: After taking over Madagascar befriend Kilwa to get Feudalism spreading. Take Exploration, then Expansion and colonize the provinces on the Cape of Good Hope. Afterwards focus your attention mostly on the Atlantic islands and South America to get the required provinces before Portugal does, only spreading east when waiting for colonies to finish for reach. Station troops in Australia after the colonial nation forms, otherwise the natives will attack. This achievement is only visible if the Origins DLC is active, but no DLC is needed to complete it. | U31: =IF($D31="E",K31,"") | V31: =IF($D31="M",K31,"") | W31: =IF($D31="H",K31,"") | X31: =IF($D31="VE",K31,"") | Y31: =VLOOKUP($A31,Runs!$G:$G,1,FALSE) -> Where are the penguins?
A32: There Khan only be one! | B32: Starting as a Steppe Horde, ensure there exists no other horde than you in the world. | C32: 0.004 | D32: M | E32: =(30-C32*100)*VLOOKUP($D32,Calc!$A$1:$C$6,3,FALSE) -> 74 | F32: =VLOOKUP(D32,Calc!$A$1:$B$6,2,FALSE) -> 3 | G32: =C32+F32/10000 -> 0.0043 | H32: =( (CODE(UPPER(LEFT(A32,1)))-64)+(CODE(UPPER(RIGHT(LEFT(A32,2),1)))-64)+(CODE(UPPER(RIGHT(LEFT(A32,3),1)))-64)+(CODE(UPPER(RIGHT(LEFT(A32,4),1)))-64)+(CODE(UPPER(RIGHT(LEFT(A32,5),1)))-64)+(CODE(UPPER(RIGHT(LEFT(A32,6),1)))-64)+(CODE(UPPER(RIGHT(LEFT(A32,7),1)))-64)+(CODE(UPPER(RIGHT(LEFT(A32,8),1)))-64) )/1000000 -> 4.3e-05 | I32: =G32+H32/10 -> 0.0043043 | J32: =IF($O32="","",I32) -> 0.0043043 | K32: =IF($O32="",I32,"") | L32: =F32-I32 -> 2.9956957 | M32: =IF($O32="","",L32) -> 2.9956957 | N32: =IF($O32="",L32,"") | O32: Y | P32: Great Horde | Q32: - Has enacted the Steppe Nomads government reform | R32: - This country has enacted one of the following government reforms: - Steppe Nomads - Great Mongol State - No other country has enacted one of the following government reforms: - Steppe Nomads - Great Mongol State - *countries which switched their government type through government reforms (e.g. by enacting The Great Plains call to us) or enacted Become Horde are not counted* | U32: =IF($D32="E",K32,"") | V32: =IF($D32="M",K32,"") | W32: =IF($D32="H",K32,"") | X32: =IF($D32="VE",K32,"") | Y32: =VLOOKUP($A32,Runs!$G:$G,1,FALSE) -> #N/A
A33: Stardust Crusaders | B33: As Japan have the Land of the Christian Sun reform while Palestine and Cairo are Christian under us. | C33: 0.004 | D33: M | E33: =(30-C33*100)*VLOOKUP($D33,Calc!$A$1:$C$6,3,FALSE) -> 74 | F33: =VLOOKUP(D33,Calc!$A$1:$B$6,2,FALSE) -> 3 | G33: =C33+F33/10000 -> 0.0043 | H33: =( (CODE(UPPER(LEFT(A33,1)))-64)+(CODE(UPPER(RIGHT(LEFT(A33,2),1)))-64)+(CODE(UPPER(RIGHT(LEFT(A33,3),1)))-64)+(CODE(UPPER(RIGHT(LEFT(A33,4),1)))-64)+(CODE(UPPER(RIGHT(LEFT(A33,5),1)))-64)+(CODE(UPPER(RIGHT(LEFT(A33,6),1)))-64)+(CODE(UPPER(RIGHT(LEFT(A33,7),1)))-64)+(CODE(UPPER(RIGHT(LEFT(A33,8),1)))-64) )/1000000 -> 0.000122 | I33: =G33+H33/10 -> 0.0043122 | J33: =IF($O33="","",I33) | K33: =IF($O33="",I33,"") -> 0.0043122 | L33: =F33-I33 -> 2.9956878 | M33: =IF($O33="","",L33) | N33: =IF($O33="",L33,"") -> 2.9956878 | R33: - Is Japan - Has enacted the Land of the Christian Sun government reform - The Palestine area and the province Cairo (361) have a Christian religion and are owned by this country | S33: To get the Land of the Christian Sun government reform, it is mandatory to get the open outcome in the incident Spread of Christianity. | U33: =IF($D33="E",K33,"") | V33: =IF($D33="M",K33,"") -> 0.0043122 | W33: =IF($D33="H",K33,"") | X33: =IF($D33="VE",K33,"") | Y33: =VLOOKUP($A33,Runs!$G:$G,1,FALSE) -> Stardust Crusaders
A34: Golden Wind | B34: As Air, make 50 ducats profit per month and have 50% of your income made through gold provinces. | C34: 0.004 | D34: M | E34: =(30-C34*100)*VLOOKUP($D34,Calc!$A$1:$C$6,3,FALSE) -> 74 | F34: =VLOOKUP(D34,Calc!$A$1:$B$6,2,FALSE) -> 3 | G34: =C34+F34/10000 -> 0.0043 | H34: =( (CODE(UPPER(LEFT(A34,1)))-64)+(CODE(UPPER(RIGHT(LEFT(A34,2),1)))-64)+(CODE(UPPER(RIGHT(LEFT(A34,3),1)))-64)+(CODE(UPPER(RIGHT(LEFT(A34,4),1)))-64)+(CODE(UPPER(RIGHT(LEFT(A34,5),1)))-64)+(CODE(UPPER(RIGHT(LEFT(A34,6),1)))-64)+(CODE(UPPER(RIGHT(LEFT(A34,7),1)))-64)+(CODE(UPPER(RIGHT(LEFT(A34,8),1)))-64) )/1000000 -> 4.8e-05 | I34: =G34+H34/10 -> 0.0043048 | J34: =IF($O34="","",I34) -> 0.0043048 | K34: =IF($O34="",I34,"") | L34: =F34-I34 -> 2.9956952 | M34: =IF($O34="","",L34) -> 2.9956952 | N34: =IF($O34="",L34,"") | O34: Y | P34: Air | Q34: Playing as Air | R34: - Is Air - monthly balance is at least *50* - 50% of the monthly income is from gold | S34: This achievement is only visible if the Origins DLC is active, but no DLC is needed to complete it. As Air consider royal marrying Songhai and Mali and improving relations after to get an alliance. Both should start neutral most of the time and are strong allies. After, look for choice targets and build over force limit by hiring a free company. Air starts with a level 2 fort on their capital so rushing smaller enemy capital forts is a viable strategy, no need to take unnecessary battles. You need 50 positive balance, not income. Consider disbanding armies, firing advisors and deleting forts when your income is over 60 ducats, with at least 50% gold income. Almost all expenses can be reduced to near 0 except for state maintenance. To get enough gold income controlling and developing the three gold mines in West Africa should be enough. In 1444 two are owned by Mali and one by Kong. | U34: =IF($D34="E",K34,"") | V34: =IF($D34="M",K34,"") | W34: =IF($D34="H",K34,"") | X34: =IF($D34="VE",K34,"") | Y34: =VLOOKUP($A34,Runs!$G:$G,1,FALSE) -> Golden Wind
A35: Copium Wars | B35: Starting and playing as Ming, own the Britain region. | C35: 0.004 | D35: M | E35: =(30-C35*100)*VLOOKUP($D35,Calc!$A$1:$C$6,3,FALSE) -> 74 | F35: =VLOOKUP(D35,Calc!$A$1:$B$6,2,FALSE) -> 3 | G35: =C35+F35/10000 -> 0.0043 | H35: =( (CODE(UPPER(LEFT(A35,1)))-64)+(CODE(UPPER(RIGHT(LEFT(A35,2),1)))-64)+(CODE(UPPER(RIGHT(LEFT(A35,3),1)))-64)+(CODE(UPPER(RIGHT(LEFT(A35,4),1)))-64)+(CODE(UPPER(RIGHT(LEFT(A35,5),1)))-64)+(CODE(UPPER(RIGHT(LEFT(A35,6),1)))-64)+(CODE(UPPER(RIGHT(LEFT(A35,7),1)))-64)+(CODE(UPPER(RIGHT(LEFT(A35,8),1)))-64) )/1000000 -> 6.8e-05 | I35: =G35+H35/10 -> 0.0043068 | J35: =IF($O35="","",I35) -> 0.0043068 | K35: =IF($O35="",I35,"") | L35: =F35-I35 -> 2.9956932 | M35: =IF($O35="","",L35) -> 2.9956932 | N35: =IF($O35="",L35,"") | O35: Y | P35: Ming | Q35: - Playing as Ming - AI-controlled custom nations are allowed, but they are not required | R35: - Is Ming - Own all provinces in the Britain region Britain region | S35: This is one of only two achievements which allows a custom nation on the map which can't be earned by playing that custom nation. | U35: =IF($D35="E",K35,"") | V35: =IF($D35="M",K35,"") | W35: =IF($D35="H",K35,"") | X35: =IF($D35="VE",K35,"") | Y35: =VLOOKUP($A35,Runs!$G:$G,1,FALSE) -> Copium Wars
A36: Inner Turmoil | B36: Starting as The Isles, own 20 provinces by 1500, none of which are on Islands. | C36: 0.004 | D36: VH | E36: =(30-C36*100)*VLOOKUP($D36,Calc!$A$1:$C$6,3,FALSE) -> 296 | F36: =VLOOKUP(D36,Calc!$A$1:$B$6,2,FALSE) -> 5 | G36: =C36+F36/10000 -> 0.0045 | H36: =( (CODE(UPPER(LEFT(A36,1)))-64)+(CODE(UPPER(RIGHT(LEFT(A36,2),1)))-64)+(CODE(UPPER(RIGHT(LEFT(A36,3),1)))-64)+(CODE(UPPER(RIGHT(LEFT(A36,4),1)))-64)+(CODE(UPPER(RIGHT(LEFT(A36,5),1)))-64)+(CODE(UPPER(RIGHT(LEFT(A36,6),1)))-64)+(CODE(UPPER(RIGHT(LEFT(A36,7),1)))-64)+(CODE(UPPER(RIGHT(LEFT(A36,8),1)))-64) )/1000000 -> 6.9e-05 | I36: =G36+H36/10 -> 0.0045069 | J36: =IF($O36="","",I36) -> 0.0045069 | K36: =IF($O36="",I36,"") | L36: =F36-I36 -> 4.9954931 | M36: =IF($O36="","",L36) -> 4.9954931 | N36: =IF($O36="",L36,"") | O36: Y | P36: The Isles | Q36: - Playing as The Isles - *Not* using a random New World | R36: - The year is before 1500 - owns at least 20 fully colonized provinces(cities) that are *not*on an island | S36: it is allowed to have provinces on islands, but these don't count towards the 20. Islands in the context of this achievement means any province which does not have a land connection to mainland continents, meaning any province in Britain or Ireland will not count. Unfinished colonies also don't count. An easy way to achieve this is to wait until one of the berber nations is without allies and noCB them. You can core Moroccan and Sus provinces with extended range from exploration ideas and the colonial range advisor. From there, you can keep eating North Africa, or go to West Africa. The provinces do not need to be cored. | U36: =IF($D36="E",K36,"") | V36: =IF($D36="M",K36,"") | W36: =IF($D36="H",K36,"") | X36: =IF($D36="VE",K36,"") | Y36: =VLOOKUP($A36,Runs!$G:$G,1,FALSE) -> Inner Turmoil
A37: I don't like sand | B37: Have the most development while owning no province with terrain other than desert or coastal desert. | C37: 0.004 | D37: VH | E37: =(30-C37*100)*VLOOKUP($D37,Calc!$A$1:$C$6,3,FALSE) -> 296 | F37: =VLOOKUP(D37,Calc!$A$1:$B$6,2,FALSE) -> 5 | G37: =C37+F37/10000 -> 0.0045 | H37: =( (CODE(UPPER(LEFT(A37,1)))-64)+(CODE(UPPER(RIGHT(LEFT(A37,2),1)))-64)+(CODE(UPPER(RIGHT(LEFT(A37,3),1)))-64)+(CODE(UPPER(RIGHT(LEFT(A37,4),1)))-64)+(CODE(UPPER(RIGHT(LEFT(A37,5),1)))-64)+(CODE(UPPER(RIGHT(LEFT(A37,6),1)))-64)+(CODE(UPPER(RIGHT(LEFT(A37,7),1)))-64)+(CODE(UPPER(RIGHT(LEFT(A37,8),1)))-64) )/1000000 -> -2.7e-05 | I37: =G37+H37/10 -> 0.0044973 | J37: =IF($O37="","",I37) | K37: =IF($O37="",I37,"") -> 0.0044973 | L37: =F37-I37 -> 4.9955027 | M37: =IF($O37="","",L37) | N37: =IF($O37="",L37,"") -> 4.9955027 | Q37: *Not* using a random New World | R37: - All provinces are either desert or coastal desert - No other country has a higher development than this country All desert and coastal desert provinces | S37: Easiest as Ajuuraan or the Mamluks, because of their national ideas and the "Hydraulic Rights" estate privilege (which reduces the additional cost from developing deserts and coastal desert by half), that is unlocked through a mission in Origins DLC. Forming Arabia (possibly via Yemen to avoid the tech requirement) will unlock the similar "Oasis Development" privilege, which stacks with "Hydraulic Rights" | U37: =IF($D37="E",K37,"") | V37: =IF($D37="M",K37,"") | W37: =IF($D37="H",K37,"") | X37: =IF($D37="VE",K37,"") | Y37: =VLOOKUP($A37,Runs!$G:$G,1,FALSE) -> I don't like sand
A38: To the Bone | B38: As Bone, use pillage capital at least 7 times. | C38: 0.005 | D38: E | E38: =(30-C38*100)*VLOOKUP($D38,Calc!$A$1:$C$6,3,FALSE) -> 29.5 | F38: =VLOOKUP(D38,Calc!$A$1:$B$6,2,FALSE) -> 2 | G38: =C38+F38/10000 -> 0.0052 | H38: =( (CODE(UPPER(LEFT(A38,1)))-64)+(CODE(UPPER(RIGHT(LEFT(A38,2),1)))-64)+(CODE(UPPER(RIGHT(LEFT(A38,3),1)))-64)+(CODE(UPPER(RIGHT(LEFT(A38,4),1)))-64)+(CODE(UPPER(RIGHT(LEFT(A38,5),1)))-64)+(CODE(UPPER(RIGHT(LEFT(A38,6),1)))-64)+(CODE(UPPER(RIGHT(LEFT(A38,7),1)))-64)+(CODE(UPPER(RIGHT(LEFT(A38,8),1)))-64) )/1000000 -> 6e-06 | I38: =G38+H38/10 -> 0.0052006 | J38: =IF($O38="","",I38) | K38: =IF($O38="",I38,"") -> 0.0052006 | L38: =F38-I38 -> 1.9947994 | M38: =IF($O38="","",L38) | N38: =IF($O38="",L38,"") -> 1.9947994 | Q38: - Playing as Bone - *Not* using a random New World | R38: - Is Bone - Has used the pillage capital peace term at least 7 times | U38: =IF($D38="E",K38,"") -> 0.0052006 | V38: =IF($D38="M",K38,"") | W38: =IF($D38="H",K38,"") | X38: =IF($D38="VE",K38,"") | Y38: =VLOOKUP($A38,Runs!$G:$G,1,FALSE) -> To the Bone
A39: Surfing USA | B39: Form the USA as Hawaii. | C39: 0.005 | D39: E | E39: =(30-C39*100)*VLOOKUP($D39,Calc!$A$1:$C$6,3,FALSE) -> 29.5 | F39: =VLOOKUP(D39,Calc!$A$1:$B$6,2,FALSE) -> 2 | G39: =C39+F39/10000 -> 0.0052 | H39: =( (CODE(UPPER(LEFT(A39,1)))-64)+(CODE(UPPER(RIGHT(LEFT(A39,2),1)))-64)+(CODE(UPPER(RIGHT(LEFT(A39,3),1)))-64)+(CODE(UPPER(RIGHT(LEFT(A39,4),1)))-64)+(CODE(UPPER(RIGHT(LEFT(A39,5),1)))-64)+(CODE(UPPER(RIGHT(LEFT(A39,6),1)))-64)+(CODE(UPPER(RIGHT(LEFT(A39,7),1)))-64)+(CODE(UPPER(RIGHT(LEFT(A39,8),1)))-64) )/1000000 -> 6.2e-05 | I39: =G39+H39/10 -> 0.0052062 | J39: =IF($O39="","",I39) | K39: =IF($O39="",I39,"") -> 0.0052062 | L39: =F39-I39 -> 1.9947938 | M39: =IF($O39="","",L39) | N39: =IF($O39="",L39,"") -> 1.9947938 | Q39: - *Not* using a random New World - Playing as Hawai'i, Maui, O'ahu*or*Kaua'i | R39: Is USA | S39: It is advised to not colonise the nearby islands in your region. To form USA you need to move your capital to the Colonial Eastern America region, and to be able to do that you will need to move your capital. This can be done if it's the only province in a state, i,e, Hawaii. Consider releasing vassals in your home islands to achieve this. | U39: =IF($D39="E",K39,"") -> 0.0052062 | V39: =IF($D39="M",K39,"") | W39: =IF($D39="H",K39,"") | X39: =IF($D39="VE",K39,"") | Y39: =VLOOKUP($A39,Runs!$G:$G,1,FALSE) -> Surfing USA
A40: The Pheasant Strut | B40: As Gorkha form Nepal and defeat Prussia with at least 100,000 Prussian casualties in a war (both have to be primary targets of war). | C40: 0.005 | D40: H | E40: =(30-C40*100)*VLOOKUP($D40,Calc!$A$1:$C$6,3,FALSE) -> 147.5 | F40: =VLOOKUP(D40,Calc!$A$1:$B$6,2,FALSE) -> 4 | G40: =C40+F40/10000 -> 0.0054 | H40: =( (CODE(UPPER(LEFT(A40,1)))-64)+(CODE(UPPER(RIGHT(LEFT(A40,2),1)))-64)+(CODE(UPPER(RIGHT(LEFT(A40,3),1)))-64)+(CODE(UPPER(RIGHT(LEFT(A40,4),1)))-64)+(CODE(UPPER(RIGHT(LEFT(A40,5),1)))-64)+(CODE(UPPER(RIGHT(LEFT(A40,6),1)))-64)+(CODE(UPPER(RIGHT(LEFT(A40,7),1)))-64)+(CODE(UPPER(RIGHT(LEFT(A40,8),1)))-64) )/1000000 -> 3.1e-05 | I40: =G40+H40/10 -> 0.0054031 | J40: =IF($O40="","",I40) | K40: =IF($O40="",I40,"") -> 0.0054031 | L40: =F40-I40 -> 3.9945969 | M40: =IF($O40="","",L40) | N40: =IF($O40="",L40,"") -> 3.9945969 | Q40: Playing as Gorkha | R40: - Is Nepal - Prussia must have lost at least 100,000 men in battles against Nepal in one war with both as primary participants | S40: The game only counts the losses in battles which show Prussia's flag in the battle list at the bottom of the war overview screen. If there are other countries on Prussia's side, battles which show their flag are not counted. But their losses are counted in battles which show Prussia's flag. Brandenburg or Teutonic Order can form Prussia even when subjects, though they'll still need to be Protestant or Reformed. If Prussia doesn't form naturally, you can create them by vassalizing one of the above tags and giving them the required provinces, helping them grow large enough to field a lot of troops and declaring war on them once they form Prussia. | U40: =IF($D40="E",K40,"") | V40: =IF($D40="M",K40,"") | W40: =IF($D40="H",K40,"") -> 0.0054031 | X40: =IF($D40="VE",K40,"") | Y40: =VLOOKUP($A40,Runs!$G:$G,1,FALSE) -> The Pheasant Strut
A41: Eat your Greens | B41: Control all Grasslands in Asia as Kale before the age of Absolutism. | C41: 0.005 | D41: I | E41: =(30-C41*100)*VLOOKUP($D41,Calc!$A$1:$C$6,3,FALSE) -> 885 | F41: =VLOOKUP(D41,Calc!$A$1:$B$6,2,FALSE) -> 6 | G41: =C41+F41/10000 -> 0.0056 | H41: =( (CODE(UPPER(LEFT(A41,1)))-64)+(CODE(UPPER(RIGHT(LEFT(A41,2),1)))-64)+(CODE(UPPER(RIGHT(LEFT(A41,3),1)))-64)+(CODE(UPPER(RIGHT(LEFT(A41,4),1)))-64)+(CODE(UPPER(RIGHT(LEFT(A41,5),1)))-64)+(CODE(UPPER(RIGHT(LEFT(A41,6),1)))-64)+(CODE(UPPER(RIGHT(LEFT(A41,7),1)))-64)+(CODE(UPPER(RIGHT(LEFT(A41,8),1)))-64) )/1000000 -> 7.3e-05 | I41: =G41+H41/10 -> 0.0056073 | J41: =IF($O41="","",I41) | K41: =IF($O41="",I41,"") -> 0.0056073 | L41: =F41-I41 -> 5.9943927 | M41: =IF($O41="","",L41) | N41: =IF($O41="",L41,"") -> 5.9943927 | Q41: Playing as Kale | R41: - It is *not* the Age of Absolutism or the Age of Revolutions - Every province in Asia with Grasslands terrain is owned by the player's country *or* its non-tributary subjects All grassland provinces in Asia | S41: It is not required to keep playing as Kale to earn the achievement, but changing tag will hide it from the achievement tab. Start by subjugating and allying all Shan minors to complete the mission "Unite the Shan" to inherit them all and gain free cores (don't conquer any province from them as these would needlessly have to be cored; best to fully annex Ava and inherit all their tributaries). To limit AE and help with the endless conquests to come it is recommended you switch to horde government first, which is you should form Tibet and do the "Steppe Politics" mission. After choosing to invite one of the two Mongols switch culture back to Shan. Conquer enough of Indochina to form Siam for the ideas. Take Horde Ideas then Expansion then Diplomatic Ideas, don't delay colonizing Siberia. The colonies in the grassland provinces don't have to be finished, but you need to finish 3 colonies to reach the farthest province (2 if you conquer Onan Gol(1058) in Mongolia or Albazin (2102) in Manchuria instead of colonizing from the coast). The can be delayed by 30 years by ensuring that the highest valued trade node in the world contains no centers of trade at level 2 or higher, and no capital provinces. | U41: =IF($D41="E",K41,"") | V41: =IF($D41="M",K41,"") | W41: =IF($D41="H",K41,"") | X41: =IF($D41="VE",K41,"") | Y41: =VLOOKUP($A41,Runs!$G:$G,1,FALSE) -> Eat your Greens
A42: The Reapers | B42: Starting as Aragon, be a Peasant Republic and have Madrid and Paris owned by any Peasant Republic. | C42: 0.005 | D42: M | E42: =(30-C42*100)*VLOOKUP($D42,Calc!$A$1:$C$6,3,FALSE) -> 73.75 | F42: =VLOOKUP(D42,Calc!$A$1:$B$6,2,FALSE) -> 3 | G42: =C42+F42/10000 -> 0.0053 | H42: =( (CODE(UPPER(LEFT(A42,1)))-64)+(CODE(UPPER(RIGHT(LEFT(A42,2),1)))-64)+(CODE(UPPER(RIGHT(LEFT(A42,3),1)))-64)+(CODE(UPPER(RIGHT(LEFT(A42,4),1)))-64)+(CODE(UPPER(RIGHT(LEFT(A42,5),1)))-64)+(CODE(UPPER(RIGHT(LEFT(A42,6),1)))-64)+(CODE(UPPER(RIGHT(LEFT(A42,7),1)))-64)+(CODE(UPPER(RIGHT(LEFT(A42,8),1)))-64) )/1000000 -> 4.1e-05 | I42: =G42+H42/10 -> 0.0053041 | J42: =IF($O42="","",I42) -> 0.0053041 | K42: =IF($O42="",I42,"") | L42: =F42-I42 -> 2.9946959 | M42: =IF($O42="","",L42) -> 2.9946959 | N42: =IF($O42="",L42,"") | O42: Y | P42: Aragon | Q42: Playing as Aragon | R42: - Has enacted the Peasants Republic government reform - The owner of the province Madrid (217) has enacted the Peasants Republic government reform - The owner of the province Paris (183) has enacted the Peasants Republic government reform | S42: The only feasible way to become a peasant republic as Aragon is with the third option in the event Sindicat Remença. As a republic, Aragon will *not* be eligible for the Iberian Wedding. However, swithing to a Peasants Republic after getting the Iberian Wedding will keep the Personal Union. A possible way to delay the event is to use « Return province » on any Catalonian province, since the event requires Aragon to own all of the Catalonia area. | U42: =IF($D42="E",K42,"") | V42: =IF($D42="M",K42,"") | W42: =IF($D42="H",K42,"") | X42: =IF($D42="VE",K42,"") | Y42: =VLOOKUP($A42,Runs!$G:$G,1,FALSE) -> #N/A
A43: Swahili Persuasion | B43: As Kilwa, convert all of the Moluccas and Indonesia. | C43: 0.005 | D43: M | E43: =(30-C43*100)*VLOOKUP($D43,Calc!$A$1:$C$6,3,FALSE) -> 73.75 | F43: =VLOOKUP(D43,Calc!$A$1:$B$6,2,FALSE) -> 3 | G43: =C43+F43/10000 -> 0.0053 | H43: =( (CODE(UPPER(LEFT(A43,1)))-64)+(CODE(UPPER(RIGHT(LEFT(A43,2),1)))-64)+(CODE(UPPER(RIGHT(LEFT(A43,3),1)))-64)+(CODE(UPPER(RIGHT(LEFT(A43,4),1)))-64)+(CODE(UPPER(RIGHT(LEFT(A43,5),1)))-64)+(CODE(UPPER(RIGHT(LEFT(A43,6),1)))-64)+(CODE(UPPER(RIGHT(LEFT(A43,7),1)))-64)+(CODE(UPPER(RIGHT(LEFT(A43,8),1)))-64) )/1000000 -> 4.9e-05 | I43: =G43+H43/10 -> 0.0053049 | J43: =IF($O43="","",I43) -> 0.0053049 | K43: =IF($O43="",I43,"") | L43: =F43-I43 -> 2.9946951 | M43: =IF($O43="","",L43) -> 2.9946951 | N43: =IF($O43="",L43,"") | O43: Y | P43: Kilwa | Q43: Playing as Kilwa | R43: - Is Kilwa - all provinces in the regions Moluccas and Indonesia follow the state religion of Kilwa | S43: Uncolonized provinces must also follow your state religion. Propagate religion is helpful however try to keep the Europeans out of the area as it won't convert Christian provinces. This achievement is only visible if the Origins DLC is active, but it can be achieved even without the DLC | U43: =IF($D43="E",K43,"") | V43: =IF($D43="M",K43,"") | W43: =IF($D43="H",K43,"") | X43: =IF($D43="VE",K43,"") | Y43: =VLOOKUP($A43,Runs!$G:$G,1,FALSE) -> #N/A
A44: No Country for Old Tercios | B44: As Spain, have Reformed Tercios, 33 Tercio Units, and control 3 Great Power capitals at the same time | C44: 0.005 | D44: M | E44: =(30-C44*100)*VLOOKUP($D44,Calc!$A$1:$C$6,3,FALSE) -> 73.75 | F44: =VLOOKUP(D44,Calc!$A$1:$B$6,2,FALSE) -> 3 | G44: =C44+F44/10000 -> 0.0053 | H44: =( (CODE(UPPER(LEFT(A44,1)))-64)+(CODE(UPPER(RIGHT(LEFT(A44,2),1)))-64)+(CODE(UPPER(RIGHT(LEFT(A44,3),1)))-64)+(CODE(UPPER(RIGHT(LEFT(A44,4),1)))-64)+(CODE(UPPER(RIGHT(LEFT(A44,5),1)))-64)+(CODE(UPPER(RIGHT(LEFT(A44,6),1)))-64)+(CODE(UPPER(RIGHT(LEFT(A44,7),1)))-64)+(CODE(UPPER(RIGHT(LEFT(A44,8),1)))-64) )/1000000 -> 7e-05 | I44: =G44+H44/10 -> 0.005307 | J44: =IF($O44="","",I44) -> 0.005307 | K44: =IF($O44="",I44,"") | L44: =F44-I44 -> 2.994693 | M44: =IF($O44="","",L44) -> 2.994693 | N44: =IF($O44="",L44,"") | O44: Y | P44: Castille | R44: - Is Spain - Has the modifier *“Reformed Tercio Regiments”* (from the mission Refine the Tercios) - Has at least 33 tercio regiments - Control the capitals of three great powers | S44: To get the mission, Spain must be formed by a country which *never* was Aragon. | U44: =IF($D44="E",K44,"") | V44: =IF($D44="M",K44,"") | W44: =IF($D44="H",K44,"") | X44: =IF($D44="VE",K44,"") | Y44: =VLOOKUP($A44,Runs!$G:$G,1,FALSE) -> No Country for Old Tercios
A45: Get out of my swamp! | B45: As the Netherlands, own all of the Low Countries and have 50% or more Fort Defense. | C45: 0.005 | D45: M | E45: =(30-C45*100)*VLOOKUP($D45,Calc!$A$1:$C$6,3,FALSE) -> 73.75 | F45: =VLOOKUP(D45,Calc!$A$1:$B$6,2,FALSE) -> 3 | G45: =C45+F45/10000 -> 0.0053 | H45: =( (CODE(UPPER(LEFT(A45,1)))-64)+(CODE(UPPER(RIGHT(LEFT(A45,2),1)))-64)+(CODE(UPPER(RIGHT(LEFT(A45,3),1)))-64)+(CODE(UPPER(RIGHT(LEFT(A45,4),1)))-64)+(CODE(UPPER(RIGHT(LEFT(A45,5),1)))-64)+(CODE(UPPER(RIGHT(LEFT(A45,6),1)))-64)+(CODE(UPPER(RIGHT(LEFT(A45,7),1)))-64)+(CODE(UPPER(RIGHT(LEFT(A45,8),1)))-64) )/1000000 -> 2.4e-05 | I45: =G45+H45/10 -> 0.0053024 | J45: =IF($O45="","",I45) -> 0.0053024 | K45: =IF($O45="",I45,"") | L45: =F45-I45 -> 2.9946976 | M45: =IF($O45="","",L45) -> 2.9946976 | N45: =IF($O45="",L45,"") | O45: Y | P45: Holland | R45: - The country is *or* was Netherlands - Owns all provinces in the Low Countries region - Has at least 50% fort defense | S45: Defensive idea 5 gives *35%* fort defense, having a military engineer advisor gives another *20%*, and having *50* power projection gives the last *5%* | U45: =IF($D45="E",K45,"") | V45: =IF($D45="M",K45,"") | W45: =IF($D45="H",K45,"") | X45: =IF($D45="VE",K45,"") | Y45: =VLOOKUP($A45,Runs!$G:$G,1,FALSE) -> #N/A
A46: Doge Coins | B46: Starting as Venice, become the Economic Hegemon. | C46: 0.005 | D46: M | E46: =(30-C46*100)*VLOOKUP($D46,Calc!$A$1:$C$6,3,FALSE) -> 73.75 | F46: =VLOOKUP(D46,Calc!$A$1:$B$6,2,FALSE) -> 3 | G46: =C46+F46/10000 -> 0.0053 | H46: =( (CODE(UPPER(LEFT(A46,1)))-64)+(CODE(UPPER(RIGHT(LEFT(A46,2),1)))-64)+(CODE(UPPER(RIGHT(LEFT(A46,3),1)))-64)+(CODE(UPPER(RIGHT(LEFT(A46,4),1)))-64)+(CODE(UPPER(RIGHT(LEFT(A46,5),1)))-64)+(CODE(UPPER(RIGHT(LEFT(A46,6),1)))-64)+(CODE(UPPER(RIGHT(LEFT(A46,7),1)))-64)+(CODE(UPPER(RIGHT(LEFT(A46,8),1)))-64) )/1000000 -> 2.6e-05 | I46: =G46+H46/10 -> 0.0053026 | J46: =IF($O46="","",I46) | K46: =IF($O46="",I46,"") -> 0.0053026 | L46: =F46-I46 -> 2.9946974 | M46: =IF($O46="","",L46) | N46: =IF($O46="",L46,"") -> 2.9946974 | Q46: - Is Venice | R46: - Is Economic Hegemon | U46: =IF($D46="E",K46,"") | V46: =IF($D46="M",K46,"") -> 0.0053026 | W46: =IF($D46="H",K46,"") | X46: =IF($D46="VE",K46,"") | Y46: =VLOOKUP($A46,Runs!$G:$G,1,FALSE) -> Doge Coins
A47: Where Am I? | B47: As a New World native with Random New World active, explore the entire New World. | C47: 0.006 | D47: E | E47: =(30-C47*100)*VLOOKUP($D47,Calc!$A$1:$C$6,3,FALSE) -> 29.4 | F47: =VLOOKUP(D47,Calc!$A$1:$B$6,2,FALSE) -> 2 | G47: =C47+F47/10000 -> 0.0062 | H47: =( (CODE(UPPER(LEFT(A47,1)))-64)+(CODE(UPPER(RIGHT(LEFT(A47,2),1)))-64)+(CODE(UPPER(RIGHT(LEFT(A47,3),1)))-64)+(CODE(UPPER(RIGHT(LEFT(A47,4),1)))-64)+(CODE(UPPER(RIGHT(LEFT(A47,5),1)))-64)+(CODE(UPPER(RIGHT(LEFT(A47,6),1)))-64)+(CODE(UPPER(RIGHT(LEFT(A47,7),1)))-64)+(CODE(UPPER(RIGHT(LEFT(A47,8),1)))-64) )/1000000 -> 4.1e-05 | I47: =G47+H47/10 -> 0.0062041 | J47: =IF($O47="","",I47) | K47: =IF($O47="",I47,"") -> 0.0062041 | L47: =F47-I47 -> 1.9937959 | M47: =IF($O47="","",L47) | N47: =IF($O47="",L47,"") -> 1.9937959 | Q47: - Government type is *Native* - Capital is in the New World - Is using a random New World - No more than 1 custom nation exists in the world - Used no more than 201 nation designer points if playing as a custom nation | R47: Has discovered all provinces in the New World. | S47: Eligible countries show “Tribe” as the government in the nation selection screen or are custom nations with one of the government reforms in the “Native” category Sometimes a random world is generated where all of the land is already discovered by most native nations, one only needs to unpause in order to get the achievement | T47: - - | U47: =IF($D47="E",K47,"") -> 0.0062041 | V47: =IF($D47="M",K47,"") | W47: =IF($D47="H",K47,"") | X47: =IF($D47="VE",K47,"") | Y47: =VLOOKUP($A47,Runs!$G:$G,1,FALSE) -> #N/A
A48: Why is the Rûm gone!? | B48: As Asturias, establish an Order in Rum. | C48: 0.006 | D48: H | E48: =(30-C48*100)*VLOOKUP($D48,Calc!$A$1:$C$6,3,FALSE) -> 147 | F48: =VLOOKUP(D48,Calc!$A$1:$B$6,2,FALSE) -> 4 | G48: =C48+F48/10000 -> 0.0064 | H48: =( (CODE(UPPER(LEFT(A48,1)))-64)+(CODE(UPPER(RIGHT(LEFT(A48,2),1)))-64)+(CODE(UPPER(RIGHT(LEFT(A48,3),1)))-64)+(CODE(UPPER(RIGHT(LEFT(A48,4),1)))-64)+(CODE(UPPER(RIGHT(LEFT(A48,5),1)))-64)+(CODE(UPPER(RIGHT(LEFT(A48,6),1)))-64)+(CODE(UPPER(RIGHT(LEFT(A48,7),1)))-64)+(CODE(UPPER(RIGHT(LEFT(A48,8),1)))-64) )/1000000 -> 4e-05 | I48: =G48+H48/10 -> 0.006404 | J48: =IF($O48="","",I48) | K48: =IF($O48="",I48,"") -> 0.006404 | L48: =F48-I48 -> 3.993596 | M48: =IF($O48="","",L48) | N48: =IF($O48="",L48,"") -> 3.993596 | R48: - Is Asturias - Own and have a holy order established in the Rum area | S48: - Easiest to do as Ottomans. First, no-CB Castile and conquer the province of Vizcaya, then release Asturias as a vassal. Next, conquer enough Iberian provinces to connect Vizcaya to the Mediterranean as well as at least one province per sea tile connecting Iberia to all provinces in the Rum area, giving Asturias the line of provinces in each peace deal as well as any of your own provinces needed to complete the snake. Integrate and re-release Asturias, selecting to play as them, and then establish the holy order needed in order to complete the achievement. A similar strategy can be used if starting as Aragon, which owns most of the connecting provinces needed. | U48: =IF($D48="E",K48,"") | V48: =IF($D48="M",K48,"") | W48: =IF($D48="H",K48,"") -> 0.006404 | X48: =IF($D48="VE",K48,"") | Y48: =VLOOKUP($A48,Runs!$G:$G,1,FALSE) -> Why is the Rûm gone!?
A49: The Fezzan Corridors | B49: As Fezzan, control at least 90% of the trade power in Tunis, Katsina, Safi and Timbuktu. | C49: 0.006 | D49: H | E49: =(30-C49*100)*VLOOKUP($D49,Calc!$A$1:$C$6,3,FALSE) -> 147 | F49: =VLOOKUP(D49,Calc!$A$1:$B$6,2,FALSE) -> 4 | G49: =C49+F49/10000 -> 0.0064 | H49: =( (CODE(UPPER(LEFT(A49,1)))-64)+(CODE(UPPER(RIGHT(LEFT(A49,2),1)))-64)+(CODE(UPPER(RIGHT(LEFT(A49,3),1)))-64)+(CODE(UPPER(RIGHT(LEFT(A49,4),1)))-64)+(CODE(UPPER(RIGHT(LEFT(A49,5),1)))-64)+(CODE(UPPER(RIGHT(LEFT(A49,6),1)))-64)+(CODE(UPPER(RIGHT(LEFT(A49,7),1)))-64)+(CODE(UPPER(RIGHT(LEFT(A49,8),1)))-64) )/1000000 -> 6.4e-05 | I49: =G49+H49/10 -> 0.0064064 | J49: =IF($O49="","",I49) -> 0.0064064 | K49: =IF($O49="",I49,"") | L49: =F49-I49 -> 3.9935936 | M49: =IF($O49="","",L49) -> 3.9935936 | N49: =IF($O49="",L49,"") | O49: Y | P49: Fezzan | Q49: Playing as Fezzan | R49: Have at least 90% trade power in Katsina, Safi, Timbuktu and Tunis trade nodes | S49: Will likely require conquering (or at least occupying) much of Spain to prevent upstream trade power transfers to Tunis and Safi from Seville and Valencia. | U49: =IF($D49="E",K49,"") | V49: =IF($D49="M",K49,"") | W49: =IF($D49="H",K49,"") | X49: =IF($D49="VE",K49,"") | Y49: =VLOOKUP($A49,Runs!$G:$G,1,FALSE) -> The Fezzan Corridors
A50: Stiff Upper Lippe | B50: As Lippe, own all of the British Isles. | C50: 0.006 | D50: H | E50: =(30-C50*100)*VLOOKUP($D50,Calc!$A$1:$C$6,3,FALSE) -> 147 | F50: =VLOOKUP(D50,Calc!$A$1:$B$6,2,FALSE) -> 4 | G50: =C50+F50/10000 -> 0.0064 | H50: =( (CODE(UPPER(LEFT(A50,1)))-64)+(CODE(UPPER(RIGHT(LEFT(A50,2),1)))-64)+(CODE(UPPER(RIGHT(LEFT(A50,3),1)))-64)+(CODE(UPPER(RIGHT(LEFT(A50,4),1)))-64)+(CODE(UPPER(RIGHT(LEFT(A50,5),1)))-64)+(CODE(UPPER(RIGHT(LEFT(A50,6),1)))-64)+(CODE(UPPER(RIGHT(LEFT(A50,7),1)))-64)+(CODE(UPPER(RIGHT(LEFT(A50,8),1)))-64) )/1000000 -> 6.5e-05 | I50: =G50+H50/10 -> 0.0064065 | J50: =IF($O50="","",I50) -> 0.0064065 | K50: =IF($O50="",I50,"") | L50: =F50-I50 -> 3.9935935 | M50: =IF($O50="","",L50) -> 3.9935935 | N50: =IF($O50="",L50,"") | O50: Y | P50: Hesse | Q50: *Not* using a random New World | R50: - Is Lippe - Own all provinces in Britain Britain region | S50: Lippe doesn't exist in 1444, but it can be released from its core province Ravensberg (4775) which is owned by Berg. By first releasing Lippe as a regular vassal, giving them provinces to core and annexing them gives more land when releasing them again. Can be done as part of a HRE campaign. Ensure Lippe exists before you pass "Revoke the Privilegia". Feed all of Britain's cores to your Lippe vassal and then either annex Lippe or pass the final reform "Renovatio Imperii", then release and play as Lippe, earning you the achievement. | U50: =IF($D50="E",K50,"") | V50: =IF($D50="M",K50,"") | W50: =IF($D50="H",K50,"") | X50: =IF($D50="VE",K50,"") | Y50: =VLOOKUP($A50,Runs!$G:$G,1,FALSE) -> Stiff Upper Lippe
A51: Stern des Südens | B51: Form Bavaria starting as München and have your Subject Bremen own Werder. | C51: 0.006 | D51: H | E51: =(30-C51*100)*VLOOKUP($D51,Calc!$A$1:$C$6,3,FALSE) -> 147 | F51: =VLOOKUP(D51,Calc!$A$1:$B$6,2,FALSE) -> 4 | G51: =C51+F51/10000 -> 0.0064 | H51: =( (CODE(UPPER(LEFT(A51,1)))-64)+(CODE(UPPER(RIGHT(LEFT(A51,2),1)))-64)+(CODE(UPPER(RIGHT(LEFT(A51,3),1)))-64)+(CODE(UPPER(RIGHT(LEFT(A51,4),1)))-64)+(CODE(UPPER(RIGHT(LEFT(A51,5),1)))-64)+(CODE(UPPER(RIGHT(LEFT(A51,6),1)))-64)+(CODE(UPPER(RIGHT(LEFT(A51,7),1)))-64)+(CODE(UPPER(RIGHT(LEFT(A51,8),1)))-64) )/1000000 -> 5.3e-05 | I51: =G51+H51/10 -> 0.0064053 | J51: =IF($O51="","",I51) | K51: =IF($O51="",I51,"") -> 0.0064053 | L51: =F51-I51 -> 3.9935947 | M51: =IF($O51="","",L51) | N51: =IF($O51="",L51,"") -> 3.9935947 | Q51: - Playing as Munich - *Not* using a random New World | R51: - Is Bavaria - Bremen is a subject of Bavaria - Bremen owns Werder (2778) | S51: Werder (2778) is in the Horn of Africa region and owned by Marehan at the start of the game. As Munich, take your time consolidating into Bavaria. If you can, befriend the emperor and/or electors to make your life within the HRE easier. Once you have a border with Bremen, or coastal provinces in coring range of Bremen, look for war opportunities which Bremen will be called ito as an ally. As they are a free city, it will be much harder if you declare directly on them (as the Emperor will defend free cities). Annex Bremen in a separate peace and release them as your vassal (you can't vassalize a free city in a peace deal). Afterwards, expand in power so that you can combat your most powerful neighbours - Ottomans, Spain, France, etc. Make sure to give Bremen land, either in the direction of the Ottomans or in the direction of Spain. You will have to fight your way through at least one, feeding Bremen provinces to "snake" their land down to Werder (this is because vassals need adjacent land or sea tiles to be given provinces and do not care about coring distance/colonial range). The least time-consuming method would be to give them a province per sea tile starting from the Mediterranean, down through the Mamluks to the Red Sea coast, and finally down to Werder. | U51: =IF($D51="E",K51,"") | V51: =IF($D51="M",K51,"") | W51: =IF($D51="H",K51,"") -> 0.0064053 | X51: =IF($D51="VE",K51,"") | Y51: =VLOOKUP($A51,Runs!$G:$G,1,FALSE) -> Stern des Südens
A52: Pick Your Poison | B52: As Kaffa, develop in Cafa while a subject of yours owns it. | C52: 0.006 | D52: H | E52: =(30-C52*100)*VLOOKUP($D52,Calc!$A$1:$C$6,3,FALSE) -> 147 | F52: =VLOOKUP(D52,Calc!$A$1:$B$6,2,FALSE) -> 4 | G52: =C52+F52/10000 -> 0.0064 | H52: =( (CODE(UPPER(LEFT(A52,1)))-64)+(CODE(UPPER(RIGHT(LEFT(A52,2),1)))-64)+(CODE(UPPER(RIGHT(LEFT(A52,3),1)))-64)+(CODE(UPPER(RIGHT(LEFT(A52,4),1)))-64)+(CODE(UPPER(RIGHT(LEFT(A52,5),1)))-64)+(CODE(UPPER(RIGHT(LEFT(A52,6),1)))-64)+(CODE(UPPER(RIGHT(LEFT(A52,7),1)))-64)+(CODE(UPPER(RIGHT(LEFT(A52,8),1)))-64) )/1000000 -> 6.8e-05 | I52: =G52+H52/10 -> 0.0064068 | J52: =IF($O52="","",I52) | K52: =IF($O52="",I52,"") -> 0.0064068 | L52: =F52-I52 -> 3.9935932 | M52: =IF($O52="","",L52) | N52: =IF($O52="",L52,"") -> 3.9935932 | Q52: Playing as Kaffa | R52: - Developed in Caffa (285). - Any subject nation owns Caffa. | S52: Caffa is in the Pontic Steppe region, initially owned by Genoa. | U52: =IF($D52="E",K52,"") | V52: =IF($D52="M",K52,"") | W52: =IF($D52="H",K52,"") -> 0.0064068 | X52: =IF($D52="VE",K52,"") | Y52: =VLOOKUP($A52,Runs!$G:$G,1,FALSE) -> Pick Your Poison
A53: Pandya Empire | B53: Starting as Madurai, conquer the Pandya Territories. | C53: 0.006 | D53: H | E53: =(30-C53*100)*VLOOKUP($D53,Calc!$A$1:$C$6,3,FALSE) -> 147 | F53: =VLOOKUP(D53,Calc!$A$1:$B$6,2,FALSE) -> 4 | G53: =C53+F53/10000 -> 0.0064 | H53: =( (CODE(UPPER(LEFT(A53,1)))-64)+(CODE(UPPER(RIGHT(LEFT(A53,2),1)))-64)+(CODE(UPPER(RIGHT(LEFT(A53,3),1)))-64)+(CODE(UPPER(RIGHT(LEFT(A53,4),1)))-64)+(CODE(UPPER(RIGHT(LEFT(A53,5),1)))-64)+(CODE(UPPER(RIGHT(LEFT(A53,6),1)))-64)+(CODE(UPPER(RIGHT(LEFT(A53,7),1)))-64)+(CODE(UPPER(RIGHT(LEFT(A53,8),1)))-64) )/1000000 -> 3.4e-05 | I53: =G53+H53/10 -> 0.0064034 | J53: =IF($O53="","",I53) | K53: =IF($O53="",I53,"") -> 0.0064034 | L53: =F53-I53 -> 3.9935966 | M53: =IF($O53="","",L53) | N53: =IF($O53="",L53,"") -> 3.9935966 | Q53: Playing as Madurai | R53: Own all provinces in the region of Coromandel and the areas of Malabar, Mysore, and Rayalaseema | U53: =IF($D53="E",K53,"") | V53: =IF($D53="M",K53,"") | W53: =IF($D53="H",K53,"") -> 0.0064034 | X53: =IF($D53="VE",K53,"") | Y53: =VLOOKUP($A53,Runs!$G:$G,1,FALSE) -> Pandya Empire
A54: Mass Production | B54: Starting as Odoyev, own one of every manufactory. | C54: 0.006 | D54: H | E54: =(30-C54*100)*VLOOKUP($D54,Calc!$A$1:$C$6,3,FALSE) -> 147 | F54: =VLOOKUP(D54,Calc!$A$1:$B$6,2,FALSE) -> 4 | G54: =C54+F54/10000 -> 0.0064 | H54: =( (CODE(UPPER(LEFT(A54,1)))-64)+(CODE(UPPER(RIGHT(LEFT(A54,2),1)))-64)+(CODE(UPPER(RIGHT(LEFT(A54,3),1)))-64)+(CODE(UPPER(RIGHT(LEFT(A54,4),1)))-64)+(CODE(UPPER(RIGHT(LEFT(A54,5),1)))-64)+(CODE(UPPER(RIGHT(LEFT(A54,6),1)))-64)+(CODE(UPPER(RIGHT(LEFT(A54,7),1)))-64)+(CODE(UPPER(RIGHT(LEFT(A54,8),1)))-64) )/1000000 -> 6.9e-05 | I54: =G54+H54/10 -> 0.0064069 | J54: =IF($O54="","",I54) -> 0.0064069 | K54: =IF($O54="",I54,"") | L54: =F54-I54 -> 3.9935931 | M54: =IF($O54="","",L54) -> 3.9935931 | N54: =IF($O54="",L54,"") | O54: Y | P54: Odoyev | Q54: Playing as Odoyev | R54: Own at least one manufactory of each type | S54: - The new manufactories (Ramparts, Soldier's Households, Impressment Offices, State House) are also necessary - With the Rule Britannia DLC a furnace is also necessary. - Building the manufactories isn't very hard. The hard part is surviving long enough to get to the required technology (admin tech 16 without Rule Britannia and till the Enlightenment with the DLC) as well as getting provinces with the correct trade goods. | U54: =IF($D54="E",K54,"") | V54: =IF($D54="M",K54,"") | W54: =IF($D54="H",K54,"") | X54: =IF($D54="VE",K54,"") | Y54: =VLOOKUP($A54,Runs!$G:$G,1,FALSE) -> Mass Production
A55: Everything's Coming Up Mulhouse | B55: Starting as Mulhouse, become Emperor of the HRE and completely decentralize the Empire. | C55: 0.006 | D55: H | E55: =(30-C55*100)*VLOOKUP($D55,Calc!$A$1:$C$6,3,FALSE) -> 147 | F55: =VLOOKUP(D55,Calc!$A$1:$B$6,2,FALSE) -> 4 | G55: =C55+F55/10000 -> 0.0064 | H55: =( (CODE(UPPER(LEFT(A55,1)))-64)+(CODE(UPPER(RIGHT(LEFT(A55,2),1)))-64)+(CODE(UPPER(RIGHT(LEFT(A55,3),1)))-64)+(CODE(UPPER(RIGHT(LEFT(A55,4),1)))-64)+(CODE(UPPER(RIGHT(LEFT(A55,5),1)))-64)+(CODE(UPPER(RIGHT(LEFT(A55,6),1)))-64)+(CODE(UPPER(RIGHT(LEFT(A55,7),1)))-64)+(CODE(UPPER(RIGHT(LEFT(A55,8),1)))-64) )/1000000 -> 0.000112 | I55: =G55+H55/10 -> 0.0064112 | J55: =IF($O55="","",I55) -> 0.0064112 | K55: =IF($O55="",I55,"") | L55: =F55-I55 -> 3.9935888 | M55: =IF($O55="","",L55) -> 3.9935888 | N55: =IF($O55="",L55,"") | O55: Y | P55: Mulhouse | Q55: - Playing as Mulhouse - *Not* using a random New World | R55: - Is the emperor of the Holy Roman Empire - Has enacted the reform Reichskrieg | S55: Mulhouse starts as a republic, and needs to become a monarchy to be able to become the Holy Roman Emperor. | U55: =IF($D55="E",K55,"") | V55: =IF($D55="M",K55,"") | W55: =IF($D55="H",K55,"") | X55: =IF($D55="VE",K55,"") | Y55: =VLOOKUP($A55,Runs!$G:$G,1,FALSE) -> #N/A
A56: Dovmont's Own | B56: Starting as Pskov, have 100 standing Streltsy units. | C56: 0.006 | D56: H | E56: =(30-C56*100)*VLOOKUP($D56,Calc!$A$1:$C$6,3,FALSE) -> 147 | F56: =VLOOKUP(D56,Calc!$A$1:$B$6,2,FALSE) -> 4 | G56: =C56+F56/10000 -> 0.0064 | H56: =( (CODE(UPPER(LEFT(A56,1)))-64)+(CODE(UPPER(RIGHT(LEFT(A56,2),1)))-64)+(CODE(UPPER(RIGHT(LEFT(A56,3),1)))-64)+(CODE(UPPER(RIGHT(LEFT(A56,4),1)))-64)+(CODE(UPPER(RIGHT(LEFT(A56,5),1)))-64)+(CODE(UPPER(RIGHT(LEFT(A56,6),1)))-64)+(CODE(UPPER(RIGHT(LEFT(A56,7),1)))-64)+(CODE(UPPER(RIGHT(LEFT(A56,8),1)))-64) )/1000000 -> 7.8e-05 | I56: =G56+H56/10 -> 0.0064078 | J56: =IF($O56="","",I56) | K56: =IF($O56="",I56,"") -> 0.0064078 | L56: =F56-I56 -> 3.9935922 | M56: =IF($O56="","",L56) | N56: =IF($O56="",L56,"") -> 3.9935922 | Q56: Playing as Pskov | R56: Has at least 100 Streltsy units | U56: =IF($D56="E",K56,"") | V56: =IF($D56="M",K56,"") | W56: =IF($D56="H",K56,"") -> 0.0064078 | X56: =IF($D56="VE",K56,"") | Y56: =VLOOKUP($A56,Runs!$G:$G,1,FALSE) -> Dovmont's Own
A57: That's No Mon | B57: As Pegu, own at least 50 provinces that are not of the Mon culture. | C57: 0.006 | D57: M | E57: =(30-C57*100)*VLOOKUP($D57,Calc!$A$1:$C$6,3,FALSE) -> 73.5 | F57: =VLOOKUP(D57,Calc!$A$1:$B$6,2,FALSE) -> 3 | G57: =C57+F57/10000 -> 0.0063 | H57: =( (CODE(UPPER(LEFT(A57,1)))-64)+(CODE(UPPER(RIGHT(LEFT(A57,2),1)))-64)+(CODE(UPPER(RIGHT(LEFT(A57,3),1)))-64)+(CODE(UPPER(RIGHT(LEFT(A57,4),1)))-64)+(CODE(UPPER(RIGHT(LEFT(A57,5),1)))-64)+(CODE(UPPER(RIGHT(LEFT(A57,6),1)))-64)+(CODE(UPPER(RIGHT(LEFT(A57,7),1)))-64)+(CODE(UPPER(RIGHT(LEFT(A57,8),1)))-64) )/1000000 -> 2.5e-05 | I57: =G57+H57/10 -> 0.0063025 | J57: =IF($O57="","",I57) -> 0.0063025 | K57: =IF($O57="",I57,"") | L57: =F57-I57 -> 2.9936975 | M57: =IF($O57="","",L57) -> 2.9936975 | N57: =IF($O57="",L57,"") | O57: Y | P57: Pegu | Q57: - Playing as Pegu - *Not* using a random New World | R57: - Is Pegu - At least 50 owned provinces do not have Mon culture | S57: This achievement is only visible if the Leviathan DLC is active, but it can be achieved even without the DLC. This can be done at the same time as the Sailor Mon achievement, and will often occur without any additional effort. With Leviathan, the Pegu mission tree grants a subjugation cb on Ayutthaya, which can lead to quite a large acquisition of provinces. The player can also flip cultures to Burmese to ensure colonies are not of Mon culture and can culture convert their original provinces to a new culture. | U57: =IF($D57="E",K57,"") | V57: =IF($D57="M",K57,"") | W57: =IF($D57="H",K57,"") | X57: =IF($D57="VE",K57,"") | Y57: =VLOOKUP($A57,Runs!$G:$G,1,FALSE) -> That's No Mon
A58: Sun Invasion | B58: As the Madyas, own and have cores on Tepeacac, Mexico, Tullucan and Huastec. | C58: 0.006 | D58: M | E58: =(30-C58*100)*VLOOKUP($D58,Calc!$A$1:$C$6,3,FALSE) -> 73.5 | F58: =VLOOKUP(D58,Calc!$A$1:$B$6,2,FALSE) -> 3 | G58: =C58+F58/10000 -> 0.0063 | H58: =( (CODE(UPPER(LEFT(A58,1)))-64)+(CODE(UPPER(RIGHT(LEFT(A58,2),1)))-64)+(CODE(UPPER(RIGHT(LEFT(A58,3),1)))-64)+(CODE(UPPER(RIGHT(LEFT(A58,4),1)))-64)+(CODE(UPPER(RIGHT(LEFT(A58,5),1)))-64)+(CODE(UPPER(RIGHT(LEFT(A58,6),1)))-64)+(CODE(UPPER(RIGHT(LEFT(A58,7),1)))-64)+(CODE(UPPER(RIGHT(LEFT(A58,8),1)))-64) )/1000000 -> 6.8e-05 | I58: =G58+H58/10 -> 0.0063068 | J58: =IF($O58="","",I58) -> 0.0063068 | K58: =IF($O58="",I58,"") | L58: =F58-I58 -> 2.9936932 | M58: =IF($O58="","",L58) -> 2.9936932 | N58: =IF($O58="",L58,"") | O58: Y | P58: Madyas | R58: - Is Madyas - Own and core the provinces of Tepeacac (2628), Mexico (852), Tullucan (2626) and Tlapacoyan(853, formerly called Huastec). | S58: You need to directly own and core the target provinces, and not through your colonial nation. There are several ways to achieve this: Move your capital city to North America before a colonial nation forms. Get a colonial nation in one of the colonial regions adjacent to Mexico and grant them a chain of colonized or conquered provinces in Mexico up to the achievement provinces with the help of the grant province subject interaction(or by transferring occupations in a war if they are on the same continent as the capital of the CN). The achievement provinces can be cored as soon as the colonial nation has cored a province next to them. Vassalize a native, take land from some other native including the needed ones and a chain of provinces leading to the coast. Core one coastal province to be able to start coring the 4 achievement provinces. To avoid forming a colonial nation, the cored coastal province then has to be given to the vassal. Use the Unrestricted Conquest age ability from the Age of Revolutions. Simply annexing a vassal in the region won't fire the achievement. | U58: =IF($D58="E",K58,"") | V58: =IF($D58="M",K58,"") | W58: =IF($D58="H",K58,"") | X58: =IF($D58="VE",K58,"") | Y58: =VLOOKUP($A58,Runs!$G:$G,1,FALSE) -> Sun Invasion
A59: Shemot is Not | B59: As a Jewish nation, convert all of Egypt to Jewish while having the Jewish Community Aspect active. | C59: 0.006 | D59: M | E59: =(30-C59*100)*VLOOKUP($D59,Calc!$A$1:$C$6,3,FALSE) -> 73.5 | F59: =VLOOKUP(D59,Calc!$A$1:$B$6,2,FALSE) -> 3 | G59: =C59+F59/10000 -> 0.0063 | H59: =( (CODE(UPPER(LEFT(A59,1)))-64)+(CODE(UPPER(RIGHT(LEFT(A59,2),1)))-64)+(CODE(UPPER(RIGHT(LEFT(A59,3),1)))-64)+(CODE(UPPER(RIGHT(LEFT(A59,4),1)))-64)+(CODE(UPPER(RIGHT(LEFT(A59,5),1)))-64)+(CODE(UPPER(RIGHT(LEFT(A59,6),1)))-64)+(CODE(UPPER(RIGHT(LEFT(A59,7),1)))-64)+(CODE(UPPER(RIGHT(LEFT(A59,8),1)))-64) )/1000000 -> 5.7e-05 | I59: =G59+H59/10 -> 0.0063057 | J59: =IF($O59="","",I59) -> 0.0063057 | K59: =IF($O59="",I59,"") | L59: =F59-I59 -> 2.9936943 | M59: =IF($O59="","",L59) -> 2.9936943 | N59: =IF($O59="",L59,"") | O59: Y | P59: Mamluks | R59: - Religion is Jewish - The church aspect “*Jewish Community*” is active - All provinces in the Egypt region are Jewish | S59: Easiest to do as Mamluks. Conquer Semien (and Dembiya) in Ethiopia and immediately send a missionary with 0 maintenance to switch the rebels to Jewish Zealots (before the previous rebel type in the province has reached 30% progress). Let the rebels spawn and let them convert the country. Once Jewish has become the dominant religion, the rebel demands will also include to change the state religion. Then the demands can be accepted, but it might be beneficial to let them convert more provinces. After becoming Jewish, finish converting Egypt and choose Jewish Community as your first aspect. | U59: =IF($D59="E",K59,"") | V59: =IF($D59="M",K59,"") | W59: =IF($D59="H",K59,"") | X59: =IF($D59="VE",K59,"") | Y59: =VLOOKUP($A59,Runs!$G:$G,1,FALSE) -> Shemot is Not
A60: Mansa Musa | B60: As Mali, give 10k ducats away to another great power without having a single loan or being bankrupt. | C60: 0.006 | D60: M | E60: =(30-C60*100)*VLOOKUP($D60,Calc!$A$1:$C$6,3,FALSE) -> 73.5 | F60: =VLOOKUP(D60,Calc!$A$1:$B$6,2,FALSE) -> 3 | G60: =C60+F60/10000 -> 0.0063 | H60: =( (CODE(UPPER(LEFT(A60,1)))-64)+(CODE(UPPER(RIGHT(LEFT(A60,2),1)))-64)+(CODE(UPPER(RIGHT(LEFT(A60,3),1)))-64)+(CODE(UPPER(RIGHT(LEFT(A60,4),1)))-64)+(CODE(UPPER(RIGHT(LEFT(A60,5),1)))-64)+(CODE(UPPER(RIGHT(LEFT(A60,6),1)))-64)+(CODE(UPPER(RIGHT(LEFT(A60,7),1)))-64)+(CODE(UPPER(RIGHT(LEFT(A60,8),1)))-64) )/1000000 -> 5e-05 | I60: =G60+H60/10 -> 0.006305 | J60: =IF($O60="","",I60) -> 0.006305 | K60: =IF($O60="",I60,"") | L60: =F60-I60 -> 2.993695 | M60: =IF($O60="","",L60) -> 2.993695 | N60: =IF($O60="",L60,"") | O60: Y | P60: Mali | Q60: Playing as Mali | R60: - Is Mali - Has given at least 10k ducats to a great power with a single use of the diplomatic action Send gift - Has no loans - Is not bankrupt | S60: This achievement is only visible if the Origins DLC is active, but it is possible to get the achievement without that DLC. | U60: =IF($D60="E",K60,"") | V60: =IF($D60="M",K60,"") | W60: =IF($D60="H",K60,"") | X60: =IF($D60="VE",K60,"") | Y60: =VLOOKUP($A60,Runs!$G:$G,1,FALSE) -> Mansa Musa
A61: King of Kings | B61: Complete the Persian mission tree. | C61: 0.006 | D61: M | E61: =(30-C61*100)*VLOOKUP($D61,Calc!$A$1:$C$6,3,FALSE) -> 73.5 | F61: =VLOOKUP(D61,Calc!$A$1:$B$6,2,FALSE) -> 3 | G61: =C61+F61/10000 -> 0.0063 | H61: =( (CODE(UPPER(LEFT(A61,1)))-64)+(CODE(UPPER(RIGHT(LEFT(A61,2),1)))-64)+(CODE(UPPER(RIGHT(LEFT(A61,3),1)))-64)+(CODE(UPPER(RIGHT(LEFT(A61,4),1)))-64)+(CODE(UPPER(RIGHT(LEFT(A61,5),1)))-64)+(CODE(UPPER(RIGHT(LEFT(A61,6),1)))-64)+(CODE(UPPER(RIGHT(LEFT(A61,7),1)))-64)+(CODE(UPPER(RIGHT(LEFT(A61,8),1)))-64) )/1000000 -> -2e-06 | I61: =G61+H61/10 -> 0.0062998 | J61: =IF($O61="","",I61) -> 0.0062998 | K61: =IF($O61="",I61,"") | L61: =F61-I61 -> 2.9937002 | M61: =IF($O61="","",L61) -> 2.9937002 | N61: =IF($O61="",L61,"") | O61: Y | P61: Ardabil | R61: - Complete the Sunni or Shia or Zoroastrian version of the Persian missions | U61: =IF($D61="E",K61,"") | V61: =IF($D61="M",K61,"") | W61: =IF($D61="H",K61,"") | X61: =IF($D61="VE",K61,"") | Y61: =VLOOKUP($A61,Runs!$G:$G,1,FALSE) -> King of Kings
A62: Atwix Legacy | B62: Have 10 personal unions at the same time. | C62: 0.006 | D62: M | E62: =(30-C62*100)*VLOOKUP($D62,Calc!$A$1:$C$6,3,FALSE) -> 73.5 | F62: =VLOOKUP(D62,Calc!$A$1:$B$6,2,FALSE) -> 3 | G62: =C62+F62/10000 -> 0.0063 | H62: =( (CODE(UPPER(LEFT(A62,1)))-64)+(CODE(UPPER(RIGHT(LEFT(A62,2),1)))-64)+(CODE(UPPER(RIGHT(LEFT(A62,3),1)))-64)+(CODE(UPPER(RIGHT(LEFT(A62,4),1)))-64)+(CODE(UPPER(RIGHT(LEFT(A62,5),1)))-64)+(CODE(UPPER(RIGHT(LEFT(A62,6),1)))-64)+(CODE(UPPER(RIGHT(LEFT(A62,7),1)))-64)+(CODE(UPPER(RIGHT(LEFT(A62,8),1)))-64) )/1000000 -> 6.2e-05 | I62: =G62+H62/10 -> 0.0063062 | J62: =IF($O62="","",I62) -> 0.0063062 | K62: =IF($O62="",I62,"") | L62: =F62-I62 -> 2.9936938 | M62: =IF($O62="","",L62) -> 2.9936938 | N62: =IF($O62="",L62,"") | O62: Y | P62: Castille | R62: Have 10 or more personal unions | S62: A good way is to choose a country with many PUs in its mission tree such as Hungary, Bohemia or Austria. Follow Atwix guide and make use of the new favor feature to spread your dynasty. Ensure that your PU subjects are fairly large to avoid inheriting their throne. | U62: =IF($D62="E",K62,"") | V62: =IF($D62="M",K62,"") | W62: =IF($D62="H",K62,"") | X62: =IF($D62="VE",K62,"") | Y62: =VLOOKUP($A62,Runs!$G:$G,1,FALSE) -> #N/A
A63: Imposter Syndrome | B63: As Sus, have three countries hostile to you (less than 0 opinion) after they discovered your spy. | C63: 0.006 | D63: VE | E63: =(30-C63*100)*VLOOKUP($D63,Calc!$A$1:$C$6,3,FALSE) -> 14.7 | F63: =VLOOKUP(D63,Calc!$A$1:$B$6,2,FALSE) -> 1 | G63: =C63+F63/10000 -> 0.0061 | H63: =( (CODE(UPPER(LEFT(A63,1)))-64)+(CODE(UPPER(RIGHT(LEFT(A63,2),1)))-64)+(CODE(UPPER(RIGHT(LEFT(A63,3),1)))-64)+(CODE(UPPER(RIGHT(LEFT(A63,4),1)))-64)+(CODE(UPPER(RIGHT(LEFT(A63,5),1)))-64)+(CODE(UPPER(RIGHT(LEFT(A63,6),1)))-64)+(CODE(UPPER(RIGHT(LEFT(A63,7),1)))-64)+(CODE(UPPER(RIGHT(LEFT(A63,8),1)))-64) )/1000000 -> 0.000115 | I63: =G63+H63/10 -> 0.0061115 | J63: =IF($O63="","",I63) | K63: =IF($O63="",I63,"") -> 0.0061115 | L63: =F63-I63 -> 0.9938885 | M63: =IF($O63="","",L63) | N63: =IF($O63="",L63,"") -> 0.9938885 | Q63: Playing as Sus | R63: - Is Sus - Three countries fulfill the following conditions: - have a negative opinion of this country - have the opinion modifier “*Did Covert Actions*” towards this country | S63: Being a subject of Morocco does not prevent you from spying on other countries and independence is therefore not required. You simply need to use your two diplomats to build spy network in any country. There is about an 85% chance three nations will discover your spies within the first ten years. If your relations with them are still positive, insult them. Before unpausing the game, search for the countries with starting rulers with Secretive personality which gives *+20%* foreign spy detection. | U63: =IF($D63="E",K63,"") | V63: =IF($D63="M",K63,"") | W63: =IF($D63="H",K63,"") | X63: =IF($D63="VE",K63,"") -> 0.0061115 | Y63: =VLOOKUP($A63,Runs!$G:$G,1,FALSE) -> Imposter Syndrome
A64: Empire of Mann | B64: As Mann, conquer all Islands in the world. | C64: 0.006 | D64: VH | E64: =(30-C64*100)*VLOOKUP($D64,Calc!$A$1:$C$6,3,FALSE) -> 294 | F64: =VLOOKUP(D64,Calc!$A$1:$B$6,2,FALSE) -> 5 | G64: =C64+F64/10000 -> 0.0065 | H64: =( (CODE(UPPER(LEFT(A64,1)))-64)+(CODE(UPPER(RIGHT(LEFT(A64,2),1)))-64)+(CODE(UPPER(RIGHT(LEFT(A64,3),1)))-64)+(CODE(UPPER(RIGHT(LEFT(A64,4),1)))-64)+(CODE(UPPER(RIGHT(LEFT(A64,5),1)))-64)+(CODE(UPPER(RIGHT(LEFT(A64,6),1)))-64)+(CODE(UPPER(RIGHT(LEFT(A64,7),1)))-64)+(CODE(UPPER(RIGHT(LEFT(A64,8),1)))-64) )/1000000 -> 4.9e-05 | I64: =G64+H64/10 -> 0.0065049 | J64: =IF($O64="","",I64) | K64: =IF($O64="",I64,"") -> 0.0065049 | L64: =F64-I64 -> 4.9934951 | M64: =IF($O64="","",L64) | N64: =IF($O64="",L64,"") -> 4.9934951 | R64: - Is Mann - Own *or* have non-tributary subjects own all provinces which are on an island. | S64: Mann can't be selected as a country in 1444, you must release it as a vassal and choose the option to play as a released vassal. As England release Mann at the very start of the game. After 10 years you can annex them again. As the annexation progresses grant them your provinces bit by bit before the process hits 100%. You can even move your capital to continental Europe and give London to Mann. Be careful about France as they will likely attack you once you are weakened. After annexation is finished spend all your monarch points to boost provinces that Mann considers as a core. Now release Mann again and chose to play as a released vassal. Alternatively, sabotage England as much as possible, such as releasing all releasable nations, leaving Mann for last. Release and play as them, then ally all other released nations, plus a major like Castile. Take London, Sussex, and Kent in your first war and you should be off to a great start. | U64: =IF($D64="E",K64,"") | V64: =IF($D64="M",K64,"") | W64: =IF($D64="H",K64,"") | X64: =IF($D64="VE",K64,"") | Y64: =VLOOKUP($A64,Runs!$G:$G,1,FALSE) -> Empire of Mann
A65: Around the World in 80 Years | B65: Starting as a Custom Nation of up to 400 points in the British Region, own New York, San Francisco, Suez, Bombay, Calcutta, Hong Kong and Yokohama by 1524.11.11. | C65: 0.006 | D65: VH | E65: =(30-C65*100)*VLOOKUP($D65,Calc!$A$1:$C$6,3,FALSE) -> 294 | F65: =VLOOKUP(D65,Calc!$A$1:$B$6,2,FALSE) -> 5 | G65: =C65+F65/10000 -> 0.0065 | H65: =( (CODE(UPPER(LEFT(A65,1)))-64)+(CODE(UPPER(RIGHT(LEFT(A65,2),1)))-64)+(CODE(UPPER(RIGHT(LEFT(A65,3),1)))-64)+(CODE(UPPER(RIGHT(LEFT(A65,4),1)))-64)+(CODE(UPPER(RIGHT(LEFT(A65,5),1)))-64)+(CODE(UPPER(RIGHT(LEFT(A65,6),1)))-64)+(CODE(UPPER(RIGHT(LEFT(A65,7),1)))-64)+(CODE(UPPER(RIGHT(LEFT(A65,8),1)))-64) )/1000000 -> 6.1e-05 | I65: =G65+H65/10 -> 0.0065061 | J65: =IF($O65="","",I65) -> 0.0065061 | K65: =IF($O65="",I65,"") | L65: =F65-I65 -> 4.9934939 | M65: =IF($O65="","",L65) -> 4.9934939 | N65: =IF($O65="",L65,"") | O65: Y | P65: Custom | Q65: - Playing as a custom nation - Only 1 custom nation exists in the world - Used no more than 401 nation designer points - *Not* using a random New World - Own no provinces outside the Britain region | R65: - The date is before 12 November 1524 - Own Manahahttan (965), Ohlone (4637), Suez (2315), Thana (529), Bengal Delta (561), Canton (667), and Musashi (1028) | S65: Requires Ohlone (4637) instead of Miwok/San Francisco (2021). Provinces cannot be owned by subject, so it is important not to establish colonial nations in North America. Considerably easier with the charter company mechanism from Dharma. | T65: - | U65: =IF($D65="E",K65,"") | V65: =IF($D65="M",K65,"") | W65: =IF($D65="H",K65,"") | X65: =IF($D65="VE",K65,"") | Y65: =VLOOKUP($A65,Runs!$G:$G,1,FALSE) -> #N/A
A66: With a little help.. | B66: As Ragusa, lead a Trade League of at least 5 nations and guarantee the Ottomans’ independence. | C66: 0.007 | D66: H | E66: =(30-C66*100)*VLOOKUP($D66,Calc!$A$1:$C$6,3,FALSE) -> 146.5 | F66: =VLOOKUP(D66,Calc!$A$1:$B$6,2,FALSE) -> 4 | G66: =C66+F66/10000 -> 0.0074 | H66: =( (CODE(UPPER(LEFT(A66,1)))-64)+(CODE(UPPER(RIGHT(LEFT(A66,2),1)))-64)+(CODE(UPPER(RIGHT(LEFT(A66,3),1)))-64)+(CODE(UPPER(RIGHT(LEFT(A66,4),1)))-64)+(CODE(UPPER(RIGHT(LEFT(A66,5),1)))-64)+(CODE(UPPER(RIGHT(LEFT(A66,6),1)))-64)+(CODE(UPPER(RIGHT(LEFT(A66,7),1)))-64)+(CODE(UPPER(RIGHT(LEFT(A66,8),1)))-64) )/1000000 -> 9e-06 | I66: =G66+H66/10 -> 0.0074009 | J66: =IF($O66="","",I66) | K66: =IF($O66="",I66,"") -> 0.0074009 | L66: =F66-I66 -> 3.9925991 | M66: =IF($O66="","",L66) | N66: =IF($O66="",L66,"") -> 3.9925991 | Q66: Playing as Ragusa | R66: - Lead a Trade League of at least 5 nations - Guarantee the independence of Ottomans | S66: You can only guarantee a country if you are larger than it. Ironically, taking land from the Ottomans for a vassal is probably the best way to do this. | U66: =IF($D66="E",K66,"") | V66: =IF($D66="M",K66,"") | W66: =IF($D66="H",K66,"") -> 0.0074009 | X66: =IF($D66="VE",K66,"") | Y66: =VLOOKUP($A66,Runs!$G:$G,1,FALSE) -> With a little help..
A67: Turkish Delight | B67: Start as Candar and own 20 Sugar provinces between you and your subjects. | C67: 0.007 | D67: H | E67: =(30-C67*100)*VLOOKUP($D67,Calc!$A$1:$C$6,3,FALSE) -> 146.5 | F67: =VLOOKUP(D67,Calc!$A$1:$B$6,2,FALSE) -> 4 | G67: =C67+F67/10000 -> 0.0074 | H67: =( (CODE(UPPER(LEFT(A67,1)))-64)+(CODE(UPPER(RIGHT(LEFT(A67,2),1)))-64)+(CODE(UPPER(RIGHT(LEFT(A67,3),1)))-64)+(CODE(UPPER(RIGHT(LEFT(A67,4),1)))-64)+(CODE(UPPER(RIGHT(LEFT(A67,5),1)))-64)+(CODE(UPPER(RIGHT(LEFT(A67,6),1)))-64)+(CODE(UPPER(RIGHT(LEFT(A67,7),1)))-64)+(CODE(UPPER(RIGHT(LEFT(A67,8),1)))-64) )/1000000 -> 7.4e-05 | I67: =G67+H67/10 -> 0.0074074 | J67: =IF($O67="","",I67) | K67: =IF($O67="",I67,"") -> 0.0074074 | L67: =F67-I67 -> 3.9925926 | M67: =IF($O67="","",L67) | N67: =IF($O67="",L67,"") -> 3.9925926 | Q67: Playing as Candar | R67: Have 20 provinces of sugar owned by this country and its non-tributary subjects | S67: Fleeing to the new world is recommended, if not required for this achievement. | U67: =IF($D67="E",K67,"") | V67: =IF($D67="M",K67,"") | W67: =IF($D67="H",K67,"") -> 0.0074074 | X67: =IF($D67="VE",K67,"") | Y67: =VLOOKUP($A67,Runs!$G:$G,1,FALSE) -> Turkish Delight
A68: Tiger of Mysore | B68: Starting as Mysore, Conquer the Deccan and Coromandel Regions. | C68: 0.007 | D68: H | E68: =(30-C68*100)*VLOOKUP($D68,Calc!$A$1:$C$6,3,FALSE) -> 146.5 | F68: =VLOOKUP(D68,Calc!$A$1:$B$6,2,FALSE) -> 4 | G68: =C68+F68/10000 -> 0.0074 | H68: =( (CODE(UPPER(LEFT(A68,1)))-64)+(CODE(UPPER(RIGHT(LEFT(A68,2),1)))-64)+(CODE(UPPER(RIGHT(LEFT(A68,3),1)))-64)+(CODE(UPPER(RIGHT(LEFT(A68,4),1)))-64)+(CODE(UPPER(RIGHT(LEFT(A68,5),1)))-64)+(CODE(UPPER(RIGHT(LEFT(A68,6),1)))-64)+(CODE(UPPER(RIGHT(LEFT(A68,7),1)))-64)+(CODE(UPPER(RIGHT(LEFT(A68,8),1)))-64) )/1000000 -> 4.8e-05 | I68: =G68+H68/10 -> 0.0074048 | J68: =IF($O68="","",I68) | K68: =IF($O68="",I68,"") -> 0.0074048 | L68: =F68-I68 -> 3.9925952 | M68: =IF($O68="","",L68) | N68: =IF($O68="",L68,"") -> 3.9925952 | Q68: Playing as Mysore | R68: - All provinces in Deccan and Coromandel regions are owned by the country or a non-tributary subject | S68: You need to ally Bahmanis to make it possible to defeat Vijayanagar If you can't, then you might have to restart a few times or no-cb a country in southeast Asia | U68: =IF($D68="E",K68,"") | V68: =IF($D68="M",K68,"") | W68: =IF($D68="H",K68,"") -> 0.0074048 | X68: =IF($D68="VE",K68,"") | Y68: =VLOOKUP($A68,Runs!$G:$G,1,FALSE) -> Tiger of Mysore
A69: The 52 Garhs | B69: As Garhwal own and maintain 52 forts without going into debt. | C69: 0.007 | D69: H | E69: =(30-C69*100)*VLOOKUP($D69,Calc!$A$1:$C$6,3,FALSE) -> 146.5 | F69: =VLOOKUP(D69,Calc!$A$1:$B$6,2,FALSE) -> 4 | G69: =C69+F69/10000 -> 0.0074 | H69: =( (CODE(UPPER(LEFT(A69,1)))-64)+(CODE(UPPER(RIGHT(LEFT(A69,2),1)))-64)+(CODE(UPPER(RIGHT(LEFT(A69,3),1)))-64)+(CODE(UPPER(RIGHT(LEFT(A69,4),1)))-64)+(CODE(UPPER(RIGHT(LEFT(A69,5),1)))-64)+(CODE(UPPER(RIGHT(LEFT(A69,6),1)))-64)+(CODE(UPPER(RIGHT(LEFT(A69,7),1)))-64)+(CODE(UPPER(RIGHT(LEFT(A69,8),1)))-64) )/1000000 -> -4.9e-05 | I69: =G69+H69/10 -> 0.0073951 | J69: =IF($O69="","",I69) | K69: =IF($O69="",I69,"") -> 0.0073951 | L69: =F69-I69 -> 3.9926049 | M69: =IF($O69="","",L69) | N69: =IF($O69="",L69,"") -> 3.9926049 | Q69: Playing as Garhwal | R69: - Has no loans - Own at least 52 forts (level 2) | U69: =IF($D69="E",K69,"") | V69: =IF($D69="M",K69,"") | W69: =IF($D69="H",K69,"") -> 0.0073951 | X69: =IF($D69="VE",K69,"") | Y69: =VLOOKUP($A69,Runs!$G:$G,1,FALSE) -> The 52 Garhs
A70: Sworn Fealty | B70: Starting as an Arabian Tribal Federation, unite Arabia and have Maximum tribal Allegiance. | C70: 0.007 | D70: H | E70: =(30-C70*100)*VLOOKUP($D70,Calc!$A$1:$C$6,3,FALSE) -> 146.5 | F70: =VLOOKUP(D70,Calc!$A$1:$B$6,2,FALSE) -> 4 | G70: =C70+F70/10000 -> 0.0074 | H70: =( (CODE(UPPER(LEFT(A70,1)))-64)+(CODE(UPPER(RIGHT(LEFT(A70,2),1)))-64)+(CODE(UPPER(RIGHT(LEFT(A70,3),1)))-64)+(CODE(UPPER(RIGHT(LEFT(A70,4),1)))-64)+(CODE(UPPER(RIGHT(LEFT(A70,5),1)))-64)+(CODE(UPPER(RIGHT(LEFT(A70,6),1)))-64)+(CODE(UPPER(RIGHT(LEFT(A70,7),1)))-64)+(CODE(UPPER(RIGHT(LEFT(A70,8),1)))-64) )/1000000 -> 6.8e-05 | I70: =G70+H70/10 -> 0.0074068 | J70: =IF($O70="","",I70) -> 0.0074068 | K70: =IF($O70="",I70,"") | L70: =F70-I70 -> 3.9925932 | M70: =IF($O70="","",L70) -> 3.9925932 | N70: =IF($O70="",L70,"") | O70: Y | P70: Najd | Q70: - Culture group is *Levantine* - Culture is not *Turkish* - Has the Tribal Federation government reform | R70: - Is Arabia - Have *100*Tribal Allegiance | S70: Possible starts are Anizah, Dawasir, Fadl, Najd, Najran, Shammar and Yas. The only way to get Tribal Allegiance within the constraints of this achievement is by keeping the Tribal Federation government reform. This reform *cannot* be selected again after losing it, so it is mandatory to *never* switch government types (e.g. with one of the tier 6 government reforms or via the first option of the Arabian mission event A New Caliphate) or do something else which gives a different tier 1 reform. To get Tribal Allegiance quickly as a large nation, humiliate rivals and allow enemies to rebuild armies so you can wipe them for prestige (since battle prestige gives Tribal Allegiance). The Offensive idea group is useful as it doubles prestige gain from battle victories. The Tier 6 reform Tribal Unity, as well as both monuments in Cairo at magnificent tier, give *+1* yearly Tribal allegiance each, which will help to offset the loss of Tribal Allegiance due to development (capped at *-0.25* monthly at 1000 development). | U70: =IF($D70="E",K70,"") | V70: =IF($D70="M",K70,"") | W70: =IF($D70="H",K70,"") | X70: =IF($D70="VE",K70,"") | Y70: =VLOOKUP($A70,Runs!$G:$G,1,FALSE) -> #N/A
A71: Protect the Secret | B71: As Yemen, prevent any European Nation from owning a Coffee-producing province in the Old World until 1700. | C71: 0.007 | D71: H | E71: =(30-C71*100)*VLOOKUP($D71,Calc!$A$1:$C$6,3,FALSE) -> 146.5 | F71: =VLOOKUP(D71,Calc!$A$1:$B$6,2,FALSE) -> 4 | G71: =C71+F71/10000 -> 0.0074 | H71: =( (CODE(UPPER(LEFT(A71,1)))-64)+(CODE(UPPER(RIGHT(LEFT(A71,2),1)))-64)+(CODE(UPPER(RIGHT(LEFT(A71,3),1)))-64)+(CODE(UPPER(RIGHT(LEFT(A71,4),1)))-64)+(CODE(UPPER(RIGHT(LEFT(A71,5),1)))-64)+(CODE(UPPER(RIGHT(LEFT(A71,6),1)))-64)+(CODE(UPPER(RIGHT(LEFT(A71,7),1)))-64)+(CODE(UPPER(RIGHT(LEFT(A71,8),1)))-64) )/1000000 -> 6.5e-05 | I71: =G71+H71/10 -> 0.0074065 | J71: =IF($O71="","",I71) | K71: =IF($O71="",I71,"") -> 0.0074065 | L71: =F71-I71 -> 3.9925935 | M71: =IF($O71="","",L71) | N71: =IF($O71="",L71,"") -> 3.9925935 | Q71: *Not* using a random New World | R71: - Culture is *Yemeni* - Is year 1700 or later - Is Yemen - No coffee-producing provinces in the continents of Asia, Africa, or Oceania are held by a country with its capital in Europe. | S71: Conditions may be fulfilled any time after 1699, and do not need to be fulfilled before that time. Yemen is reformable via culture shift, so this is very attainable playing as any country. Can be combined with the Arabian Coffee achievement. Do not form Arabia | U71: =IF($D71="E",K71,"") | V71: =IF($D71="M",K71,"") | W71: =IF($D71="H",K71,"") -> 0.0074065 | X71: =IF($D71="VE",K71,"") | Y71: =VLOOKUP($A71,Runs!$G:$G,1,FALSE) -> Protect the Secret
A72: Foremost Servitor of Jagannath | B72: Start as Orissa and own or have a subject own all tropical wood provinces. | C72: 0.007 | D72: H | E72: =(30-C72*100)*VLOOKUP($D72,Calc!$A$1:$C$6,3,FALSE) -> 146.5 | F72: =VLOOKUP(D72,Calc!$A$1:$B$6,2,FALSE) -> 4 | G72: =C72+F72/10000 -> 0.0074 | H72: =( (CODE(UPPER(LEFT(A72,1)))-64)+(CODE(UPPER(RIGHT(LEFT(A72,2),1)))-64)+(CODE(UPPER(RIGHT(LEFT(A72,3),1)))-64)+(CODE(UPPER(RIGHT(LEFT(A72,4),1)))-64)+(CODE(UPPER(RIGHT(LEFT(A72,5),1)))-64)+(CODE(UPPER(RIGHT(LEFT(A72,6),1)))-64)+(CODE(UPPER(RIGHT(LEFT(A72,7),1)))-64)+(CODE(UPPER(RIGHT(LEFT(A72,8),1)))-64) )/1000000 -> 0.000111 | I72: =G72+H72/10 -> 0.0074111 | J72: =IF($O72="","",I72) | K72: =IF($O72="",I72,"") -> 0.0074111 | L72: =F72-I72 -> 3.9925889 | M72: =IF($O72="","",L72) | N72: =IF($O72="",L72,"") -> 3.9925889 | Q72: Playing as Orissa | R72: All provinces with tropical wood are owned by the player's country or its non-tributary subjects. Provinces producing tropical wood at game start (orange) and uncolonized provinces capable of producing tropical wood (yellow) | U72: =IF($D72="E",K72,"") | V72: =IF($D72="M",K72,"") | W72: =IF($D72="H",K72,"") -> 0.0074111 | X72: =IF($D72="VE",K72,"") | Y72: =VLOOKUP($A72,Runs!$G:$G,1,FALSE) -> Foremost Servitor of Jagannath
A73: Core-fu | B73: Force a nation to revoke 5 cores in one peace deal as Corfu. | C73: 0.007 | D73: H | E73: =(30-C73*100)*VLOOKUP($D73,Calc!$A$1:$C$6,3,FALSE) -> 146.5 | F73: =VLOOKUP(D73,Calc!$A$1:$B$6,2,FALSE) -> 4 | G73: =C73+F73/10000 -> 0.0074 | H73: =( (CODE(UPPER(LEFT(A73,1)))-64)+(CODE(UPPER(RIGHT(LEFT(A73,2),1)))-64)+(CODE(UPPER(RIGHT(LEFT(A73,3),1)))-64)+(CODE(UPPER(RIGHT(LEFT(A73,4),1)))-64)+(CODE(UPPER(RIGHT(LEFT(A73,5),1)))-64)+(CODE(UPPER(RIGHT(LEFT(A73,6),1)))-64)+(CODE(UPPER(RIGHT(LEFT(A73,7),1)))-64)+(CODE(UPPER(RIGHT(LEFT(A73,8),1)))-64) )/1000000 -> 7e-05 | I73: =G73+H73/10 -> 0.007407 | J73: =IF($O73="","",I73) | K73: =IF($O73="",I73,"") -> 0.007407 | L73: =F73-I73 -> 3.992593 | M73: =IF($O73="","",L73) | N73: =IF($O73="",L73,"") -> 3.992593 | R73: - Is Corfu - Forced a country to revoke 5 cores in one peace deal | S73: Although this achievement can theoretically be started as any nation due to Corfu being a releasable nation, the cores need to be revoked while you are Corfu. Forcing a nation to revoke cores as another nation, then releasing Corfu will not count. | U73: =IF($D73="E",K73,"") | V73: =IF($D73="M",K73,"") | W73: =IF($D73="H",K73,"") -> 0.007407 | X73: =IF($D73="VE",K73,"") | Y73: =VLOOKUP($A73,Runs!$G:$G,1,FALSE) -> Core-fu
A74: Bunte Kuh | B74: As Hamburg, trade in both Gems and Livestock. | C74: 0.007 | D74: H | E74: =(30-C74*100)*VLOOKUP($D74,Calc!$A$1:$C$6,3,FALSE) -> 146.5 | F74: =VLOOKUP(D74,Calc!$A$1:$B$6,2,FALSE) -> 4 | G74: =C74+F74/10000 -> 0.0074 | H74: =( (CODE(UPPER(LEFT(A74,1)))-64)+(CODE(UPPER(RIGHT(LEFT(A74,2),1)))-64)+(CODE(UPPER(RIGHT(LEFT(A74,3),1)))-64)+(CODE(UPPER(RIGHT(LEFT(A74,4),1)))-64)+(CODE(UPPER(RIGHT(LEFT(A74,5),1)))-64)+(CODE(UPPER(RIGHT(LEFT(A74,6),1)))-64)+(CODE(UPPER(RIGHT(LEFT(A74,7),1)))-64)+(CODE(UPPER(RIGHT(LEFT(A74,8),1)))-64) )/1000000 -> 6.2e-05 | I74: =G74+H74/10 -> 0.0074062 | J74: =IF($O74="","",I74) | K74: =IF($O74="",I74,"") -> 0.0074062 | L74: =F74-I74 -> 3.9925938 | M74: =IF($O74="","",L74) | N74: =IF($O74="",L74,"") -> 3.9925938 | Q74: Playing as Hamburg | R74: - Has country modifier *Trading in Livestock* - Has country modifier *Trading in Gems* | S74: The "trading in" bonus is gained by controlling 20% of the trade value of a given commodity, calculated as the sum of the value of a good produced in a node times the percentage of trade you control in that node, added up for every node in the world. It is not necessary to expand further than Northern Europe in order to achieve the necessary economy. There are two gems provinces (Königsberg and Danzig) just upstream of Hamburg that can be highly developed in order to add up to the 20% necessary. The goods produced in these provinces can be maximized by adding the rest of Baltic trade node to a trade company (which gives a goods produced bonus to all other provinces in the node) and stating the two gems provinces. There are many livestock provinces in Denmark and around the Baltic that can be used to gain the trading in livestock bonus. Keep in mind that manufactories will contribute to the bonus, but workshops will not. You may wish to form Lübeck to gain better trade ideas. Plutocratic, Trade, and Infrastructure ideas are all helpful. | U74: =IF($D74="E",K74,"") | V74: =IF($D74="M",K74,"") | W74: =IF($D74="H",K74,"") -> 0.0074062 | X74: =IF($D74="VE",K74,"") | Y74: =VLOOKUP($A74,Runs!$G:$G,1,FALSE) -> Bunte Kuh
A75: Avar Khaganate | B75: Achieve Empire rank and conquer Hungary as Avaria. | C75: 0.007 | D75: H | E75: =(30-C75*100)*VLOOKUP($D75,Calc!$A$1:$C$6,3,FALSE) -> 146.5 | F75: =VLOOKUP(D75,Calc!$A$1:$B$6,2,FALSE) -> 4 | G75: =C75+F75/10000 -> 0.0074 | H75: =( (CODE(UPPER(LEFT(A75,1)))-64)+(CODE(UPPER(RIGHT(LEFT(A75,2),1)))-64)+(CODE(UPPER(RIGHT(LEFT(A75,3),1)))-64)+(CODE(UPPER(RIGHT(LEFT(A75,4),1)))-64)+(CODE(UPPER(RIGHT(LEFT(A75,5),1)))-64)+(CODE(UPPER(RIGHT(LEFT(A75,6),1)))-64)+(CODE(UPPER(RIGHT(LEFT(A75,7),1)))-64)+(CODE(UPPER(RIGHT(LEFT(A75,8),1)))-64) )/1000000 -> 3e-05 | I75: =G75+H75/10 -> 0.007403 | J75: =IF($O75="","",I75) | K75: =IF($O75="",I75,"") -> 0.007403 | L75: =F75-I75 -> 3.992597 | M75: =IF($O75="","",L75) | N75: =IF($O75="",L75,"") -> 3.992597 | Q75: Playing as Avaria | R75: - Is empire - Avaria owns all provinces in the areas Alföld, Transdanubia, Slovakia, Northern Transylvania, and Southern Transylvania. | U75: =IF($D75="E",K75,"") | V75: =IF($D75="M",K75,"") | W75: =IF($D75="H",K75,"") -> 0.007403 | X75: =IF($D75="VE",K75,"") | Y75: =VLOOKUP($A75,Runs!$G:$G,1,FALSE) -> Avar Khaganate
A76: The League of Mayapan | B76: Starting as Huastec, form Maya. | C76: 0.007 | D76: M | E76: =(30-C76*100)*VLOOKUP($D76,Calc!$A$1:$C$6,3,FALSE) -> 73.25 | F76: =VLOOKUP(D76,Calc!$A$1:$B$6,2,FALSE) -> 3 | G76: =C76+F76/10000 -> 0.0073 | H76: =( (CODE(UPPER(LEFT(A76,1)))-64)+(CODE(UPPER(RIGHT(LEFT(A76,2),1)))-64)+(CODE(UPPER(RIGHT(LEFT(A76,3),1)))-64)+(CODE(UPPER(RIGHT(LEFT(A76,4),1)))-64)+(CODE(UPPER(RIGHT(LEFT(A76,5),1)))-64)+(CODE(UPPER(RIGHT(LEFT(A76,6),1)))-64)+(CODE(UPPER(RIGHT(LEFT(A76,7),1)))-64)+(CODE(UPPER(RIGHT(LEFT(A76,8),1)))-64) )/1000000 -> 2.6e-05 | I76: =G76+H76/10 -> 0.0073026 | J76: =IF($O76="","",I76) -> 0.0073026 | K76: =IF($O76="",I76,"") | L76: =F76-I76 -> 2.9926974 | M76: =IF($O76="","",L76) -> 2.9926974 | N76: =IF($O76="",L76,"") | O76: Y | P76: Huastec | Q76: Playing as Huastec | R76: Is Maya | S76: Playing without El Dorado makes this achievement considerably faster and easier since you will not need to reform your religion, which can include decades of waiting for Europeans to show up. | U76: =IF($D76="E",K76,"") | V76: =IF($D76="M",K76,"") | W76: =IF($D76="H",K76,"") | X76: =IF($D76="VE",K76,"") | Y76: =VLOOKUP($A76,Runs!$G:$G,1,FALSE) -> #N/A
A77: Kuban Cigars | B77: As Kuba, own or have a subject own Havana and be the world’s leading producer of Tobacco. | C77: 0.007 | D77: M | E77: =(30-C77*100)*VLOOKUP($D77,Calc!$A$1:$C$6,3,FALSE) -> 73.25 | F77: =VLOOKUP(D77,Calc!$A$1:$B$6,2,FALSE) -> 3 | G77: =C77+F77/10000 -> 0.0073 | H77: =( (CODE(UPPER(LEFT(A77,1)))-64)+(CODE(UPPER(RIGHT(LEFT(A77,2),1)))-64)+(CODE(UPPER(RIGHT(LEFT(A77,3),1)))-64)+(CODE(UPPER(RIGHT(LEFT(A77,4),1)))-64)+(CODE(UPPER(RIGHT(LEFT(A77,5),1)))-64)+(CODE(UPPER(RIGHT(LEFT(A77,6),1)))-64)+(CODE(UPPER(RIGHT(LEFT(A77,7),1)))-64)+(CODE(UPPER(RIGHT(LEFT(A77,8),1)))-64) )/1000000 -> 2.9e-05 | I77: =G77+H77/10 -> 0.0073029 | J77: =IF($O77="","",I77) | K77: =IF($O77="",I77,"") -> 0.0073029 | L77: =F77-I77 -> 2.9926971 | M77: =IF($O77="","",L77) | N77: =IF($O77="",L77,"") -> 2.9926971 | Q77: Playing as Kuba | R77: - Own or have a non-tributary subject own the province Havana (484) - The leading producer of Tobacco is *either* this country or a subject of this country | S77: - Not possible with Random New World. - Making the leading tobacco producer a tributary would count. | U77: =IF($D77="E",K77,"") | V77: =IF($D77="M",K77,"") -> 0.0073029 | W77: =IF($D77="H",K77,"") | X77: =IF($D77="VE",K77,"") | Y77: =VLOOKUP($A77,Runs!$G:$G,1,FALSE) -> Kuban Cigars
A78: Ganges Khan | B78: Start as Tribal nation in India and become a Steppe Horde. | C78: 0.007 | D78: M | E78: =(30-C78*100)*VLOOKUP($D78,Calc!$A$1:$C$6,3,FALSE) -> 73.25 | F78: =VLOOKUP(D78,Calc!$A$1:$B$6,2,FALSE) -> 3 | G78: =C78+F78/10000 -> 0.0073 | H78: =( (CODE(UPPER(LEFT(A78,1)))-64)+(CODE(UPPER(RIGHT(LEFT(A78,2),1)))-64)+(CODE(UPPER(RIGHT(LEFT(A78,3),1)))-64)+(CODE(UPPER(RIGHT(LEFT(A78,4),1)))-64)+(CODE(UPPER(RIGHT(LEFT(A78,5),1)))-64)+(CODE(UPPER(RIGHT(LEFT(A78,6),1)))-64)+(CODE(UPPER(RIGHT(LEFT(A78,7),1)))-64)+(CODE(UPPER(RIGHT(LEFT(A78,8),1)))-64) )/1000000 -> 3.2e-05 | I78: =G78+H78/10 -> 0.0073032 | J78: =IF($O78="","",I78) | K78: =IF($O78="",I78,"") -> 0.0073032 | L78: =F78-I78 -> 2.9926968 | M78: =IF($O78="","",L78) | N78: =IF($O78="",L78,"") -> 2.9926968 | Q78: - Government type is Tribal - Capital is in India superregion | R78: - Has the Steppe Nomads government reform | S78: - This achievement is only visible if the Dharma *or* Emperor DLC is enabled, but it can be completed without them. Eligible countries are: - Bastar - Bishnupur - Chanda - Garha - Garjat - Jangladesh - Jeypore - Jhalavad - Jharkhand - Junagarh - Kachar - Kalahandi - Keonhjar - Kutch - Ladakh - Manipur - Patna - Parlakhimidi - Porbandar - Ratanpur - Sadiya - Tripura | U78: =IF($D78="E",K78,"") | V78: =IF($D78="M",K78,"") -> 0.0073032 | W78: =IF($D78="H",K78,"") | X78: =IF($D78="VE",K78,"") | Y78: =VLOOKUP($A78,Runs!$G:$G,1,FALSE) -> Ganges Khan
A79: Brentry! | B79: Starting as England, form the Angevin Kingdom and enact all the 'Acts of Crown' parliamentary issues. | C79: 0.007 | D79: M | E79: =(30-C79*100)*VLOOKUP($D79,Calc!$A$1:$C$6,3,FALSE) -> 73.25 | F79: =VLOOKUP(D79,Calc!$A$1:$B$6,2,FALSE) -> 3 | G79: =C79+F79/10000 -> 0.0073 | H79: =( (CODE(UPPER(LEFT(A79,1)))-64)+(CODE(UPPER(RIGHT(LEFT(A79,2),1)))-64)+(CODE(UPPER(RIGHT(LEFT(A79,3),1)))-64)+(CODE(UPPER(RIGHT(LEFT(A79,4),1)))-64)+(CODE(UPPER(RIGHT(LEFT(A79,5),1)))-64)+(CODE(UPPER(RIGHT(LEFT(A79,6),1)))-64)+(CODE(UPPER(RIGHT(LEFT(A79,7),1)))-64)+(CODE(UPPER(RIGHT(LEFT(A79,8),1)))-64) )/1000000 -> 7.1e-05 | I79: =G79+H79/10 -> 0.0073071 | J79: =IF($O79="","",I79) -> 0.0073071 | K79: =IF($O79="",I79,"") | L79: =F79-I79 -> 2.9926929 | M79: =IF($O79="","",L79) -> 2.9926929 | N79: =IF($O79="",L79,"") | O79: Y | P79: England | R79: - Is Angevin Kingdom - Has enacted all of the following parliament issues: - Crown of Ireland Act - Act of the Spanish Crown - Act of the Italian Crown - Crown of the Empire | S79: Do *not* dismantle the HRE, because that prevents the issue *“Crown of the Empire”*. It's recommended to stay Catholic as becoming HRE emperor as Anglican requires either religious peace or Protestant victory with around a quarter of HRE provinces under Anglican control. | U79: =IF($D79="E",K79,"") | V79: =IF($D79="M",K79,"") | W79: =IF($D79="H",K79,"") | X79: =IF($D79="VE",K79,"") | Y79: =VLOOKUP($A79,Runs!$G:$G,1,FALSE) -> Brentry!
A80: Assembly Instructions Needed | B80: Form Scandinavia and revoke the privilegia of the Holy Roman Empire while being the Emperor. | C80: 0.007 | D80: M | E80: =(30-C80*100)*VLOOKUP($D80,Calc!$A$1:$C$6,3,FALSE) -> 73.25 | F80: =VLOOKUP(D80,Calc!$A$1:$B$6,2,FALSE) -> 3 | G80: =C80+F80/10000 -> 0.0073 | H80: =( (CODE(UPPER(LEFT(A80,1)))-64)+(CODE(UPPER(RIGHT(LEFT(A80,2),1)))-64)+(CODE(UPPER(RIGHT(LEFT(A80,3),1)))-64)+(CODE(UPPER(RIGHT(LEFT(A80,4),1)))-64)+(CODE(UPPER(RIGHT(LEFT(A80,5),1)))-64)+(CODE(UPPER(RIGHT(LEFT(A80,6),1)))-64)+(CODE(UPPER(RIGHT(LEFT(A80,7),1)))-64)+(CODE(UPPER(RIGHT(LEFT(A80,8),1)))-64) )/1000000 -> 9.6e-05 | I80: =G80+H80/10 -> 0.0073096 | J80: =IF($O80="","",I80) -> 0.0073096 | K80: =IF($O80="",I80,"") | L80: =F80-I80 -> 2.9926904 | M80: =IF($O80="","",L80) -> 2.9926904 | N80: =IF($O80="",L80,"") | O80: Y | P80: Sweden | R80: One of the following: - Is Scandinavia and the emperor of the HRE and has passed the imperial reform *“Revoke The Privilegia”* - Is the Holy Roman Empire and was Scandinavia before | S80: Easy to do as Denmark. Restart until Burgundy is friendly, hire diplomatic reputation advisor, take religious diplomats estate privilege, and insult their rival. This should guarantee alliance and marriage for potential BI. Then ally and max relations with 3-4 electors, and you should become the emperor. Then the standard HRE approach of killing the Reformation. Join the HRE for a one-time IA boost. Ideas: Diplomatic, Religious, Influence. Diplomatic reputation for passing reforms and inheriting thrones and Religious to convert centers of reformation. Emperor Denmark also has an easy time killing Swedish pretender rebels. | U80: =IF($D80="E",K80,"") | V80: =IF($D80="M",K80,"") | W80: =IF($D80="H",K80,"") | X80: =IF($D80="VE",K80,"") | Y80: =VLOOKUP($A80,Runs!$G:$G,1,FALSE) -> #N/A
A81: Truly Good Maaaaa-tch | B81: Starting as either Aq Qoyunlu or Qara Qoyunlu, have a royal marriage and an alliance with Ramazan. | C81: 0.007 | D81: VE | E81: =(30-C81*100)*VLOOKUP($D81,Calc!$A$1:$C$6,3,FALSE) -> 14.65 | F81: =VLOOKUP(D81,Calc!$A$1:$B$6,2,FALSE) -> 1 | G81: =C81+F81/10000 -> 0.0071 | H81: =( (CODE(UPPER(LEFT(A81,1)))-64)+(CODE(UPPER(RIGHT(LEFT(A81,2),1)))-64)+(CODE(UPPER(RIGHT(LEFT(A81,3),1)))-64)+(CODE(UPPER(RIGHT(LEFT(A81,4),1)))-64)+(CODE(UPPER(RIGHT(LEFT(A81,5),1)))-64)+(CODE(UPPER(RIGHT(LEFT(A81,6),1)))-64)+(CODE(UPPER(RIGHT(LEFT(A81,7),1)))-64)+(CODE(UPPER(RIGHT(LEFT(A81,8),1)))-64) )/1000000 -> 8.6e-05 | I81: =G81+H81/10 -> 0.0071086 | J81: =IF($O81="","",I81) | K81: =IF($O81="",I81,"") -> 0.0071086 | L81: =F81-I81 -> 0.9928914 | M81: =IF($O81="","",L81) | N81: =IF($O81="",L81,"") -> 0.9928914 | Q81: Is Aq Qoyunlu or Qara Qoyunlu | R81: - Is Aq Qoyunlu or Qara Qoyunlu - Has an alliance with Ramazan - Has a royal marriage with Ramazan | S81: Can be achieved in a little over a month. Take out a loan, send 50 ducats to Ramazan, send a scornful insult to one of their rivals, then send an alliance offer after a month. Ramazan should send you a marriage offer within a few days. | U81: =IF($D81="E",K81,"") | V81: =IF($D81="M",K81,"") | W81: =IF($D81="H",K81,"") | X81: =IF($D81="VE",K81,"") -> 0.0071086 | Y81: =VLOOKUP($A81,Runs!$G:$G,1,FALSE) -> Truly Good Maaaaa-tch
A82: Where the heart is | B82: As Dahomey, force all non-Fetishist nations out of Niger and Sahel by 1500. | C82: 0.007 | D82: VH | E82: =(30-C82*100)*VLOOKUP($D82,Calc!$A$1:$C$6,3,FALSE) -> 293 | F82: =VLOOKUP(D82,Calc!$A$1:$B$6,2,FALSE) -> 5 | G82: =C82+F82/10000 -> 0.0075 | H82: =( (CODE(UPPER(LEFT(A82,1)))-64)+(CODE(UPPER(RIGHT(LEFT(A82,2),1)))-64)+(CODE(UPPER(RIGHT(LEFT(A82,3),1)))-64)+(CODE(UPPER(RIGHT(LEFT(A82,4),1)))-64)+(CODE(UPPER(RIGHT(LEFT(A82,5),1)))-64)+(CODE(UPPER(RIGHT(LEFT(A82,6),1)))-64)+(CODE(UPPER(RIGHT(LEFT(A82,7),1)))-64)+(CODE(UPPER(RIGHT(LEFT(A82,8),1)))-64) )/1000000 -> 5.5e-05 | I82: =G82+H82/10 -> 0.0075055 | J82: =IF($O82="","",I82) -> 0.0075055 | K82: =IF($O82="",I82,"") | L82: =F82-I82 -> 4.9924945 | M82: =IF($O82="","",L82) -> 4.9924945 | N82: =IF($O82="",L82,"") | O82: Y | P82: Dahomey | Q82: Playing as Dahomey | R82: - The year is before 1500 - All colonised provinces in the Niger and Sahel regions are owned by a Fetishist nation. | S82: - The owner must be Fetishist, not the province. Possible to do by feeding lots of land to a Sunni vassal and then enforcing religion. | U82: =IF($D82="E",K82,"") | V82: =IF($D82="M",K82,"") | W82: =IF($D82="H",K82,"") | X82: =IF($D82="VE",K82,"") | Y82: =VLOOKUP($A82,Runs!$G:$G,1,FALSE) -> #N/A
A83: Spanish Fly | B83: Starting as Offaly, secure a Personal Union over an Iberian nation. | C83: 0.007 | D83: VH | E83: =(30-C83*100)*VLOOKUP($D83,Calc!$A$1:$C$6,3,FALSE) -> 293 | F83: =VLOOKUP(D83,Calc!$A$1:$B$6,2,FALSE) -> 5 | G83: =C83+F83/10000 -> 0.0075 | H83: =( (CODE(UPPER(LEFT(A83,1)))-64)+(CODE(UPPER(RIGHT(LEFT(A83,2),1)))-64)+(CODE(UPPER(RIGHT(LEFT(A83,3),1)))-64)+(CODE(UPPER(RIGHT(LEFT(A83,4),1)))-64)+(CODE(UPPER(RIGHT(LEFT(A83,5),1)))-64)+(CODE(UPPER(RIGHT(LEFT(A83,6),1)))-64)+(CODE(UPPER(RIGHT(LEFT(A83,7),1)))-64)+(CODE(UPPER(RIGHT(LEFT(A83,8),1)))-64) )/1000000 -> 5.4e-05 | I83: =G83+H83/10 -> 0.0075054 | J83: =IF($O83="","",I83) | K83: =IF($O83="",I83,"") -> 0.0075054 | L83: =F83-I83 -> 4.9924946 | M83: =IF($O83="","",L83) | N83: =IF($O83="",L83,"") -> 4.9924946 | Q83: Playing as Offaly | R83: - Lead a personal union over a country whose capital fulfills both of the following conditions: - is in the Iberia region - has a province culture in the Iberian culture group | S83: Forming Ireland or another country *will not* prevent the achievement but instead only hiding its conditions. Take a single Spanish province with a core of another tag and release that tag as a vassal. Place dynasty member on the throne and annex the vassal. Return their core via the province screen to release them as an independent nation with your dynasty ruling. Claim their throne, immediately declare with restoration of union CB and enforce union for the achievement. It is also possible to obtain a "Restoration of Union" casus belli on Spain/ Castile by forming France and completing the mission French Claim to Naples (requires having the Emperor DLC activated and the Domination not active). | U83: =IF($D83="E",K83,"") | V83: =IF($D83="M",K83,"") | W83: =IF($D83="H",K83,"") | X83: =IF($D83="VE",K83,"") | Y83: =VLOOKUP($A83,Runs!$G:$G,1,FALSE) -> Spanish Fly
A84: Great Perm | B84: As Perm, own or have a subject own the Russian, Siberian, Scandinavian, Canadian, Hudson Bay and Cascadian Regions. | C84: 0.007 | D84: VH | E84: =(30-C84*100)*VLOOKUP($D84,Calc!$A$1:$C$6,3,FALSE) -> 293 | F84: =VLOOKUP(D84,Calc!$A$1:$B$6,2,FALSE) -> 5 | G84: =C84+F84/10000 -> 0.0075 | H84: =( (CODE(UPPER(LEFT(A84,1)))-64)+(CODE(UPPER(RIGHT(LEFT(A84,2),1)))-64)+(CODE(UPPER(RIGHT(LEFT(A84,3),1)))-64)+(CODE(UPPER(RIGHT(LEFT(A84,4),1)))-64)+(CODE(UPPER(RIGHT(LEFT(A84,5),1)))-64)+(CODE(UPPER(RIGHT(LEFT(A84,6),1)))-64)+(CODE(UPPER(RIGHT(LEFT(A84,7),1)))-64)+(CODE(UPPER(RIGHT(LEFT(A84,8),1)))-64) )/1000000 -> 4e-05 | I84: =G84+H84/10 -> 0.007504 | J84: =IF($O84="","",I84) | K84: =IF($O84="",I84,"") -> 0.007504 | L84: =F84-I84 -> 4.992496 | M84: =IF($O84="","",L84) | N84: =IF($O84="",L84,"") -> 4.992496 | Q84: Playing as Perm | R84: - *Not* playing as a released vassal - Is Perm - All provinces in the Canada, Cascadia, Hudson Bay, East Siberia, West Siberia, Scandinavia, Russia and Ural regions are owned by Perm*or* its non-tributary subjects. | U84: =IF($D84="E",K84,"") | V84: =IF($D84="M",K84,"") | W84: =IF($D84="H",K84,"") | X84: =IF($D84="VE",K84,"") | Y84: =VLOOKUP($A84,Runs!$G:$G,1,FALSE) -> Great Perm
A85: Basque in Glory | B85: Starting as Navarra, ensure that most of Iberia is Basque culture before the Age of Absolutism. | C85: 0.007 | D85: VH | E85: =(30-C85*100)*VLOOKUP($D85,Calc!$A$1:$C$6,3,FALSE) -> 293 | F85: =VLOOKUP(D85,Calc!$A$1:$B$6,2,FALSE) -> 5 | G85: =C85+F85/10000 -> 0.0075 | H85: =( (CODE(UPPER(LEFT(A85,1)))-64)+(CODE(UPPER(RIGHT(LEFT(A85,2),1)))-64)+(CODE(UPPER(RIGHT(LEFT(A85,3),1)))-64)+(CODE(UPPER(RIGHT(LEFT(A85,4),1)))-64)+(CODE(UPPER(RIGHT(LEFT(A85,5),1)))-64)+(CODE(UPPER(RIGHT(LEFT(A85,6),1)))-64)+(CODE(UPPER(RIGHT(LEFT(A85,7),1)))-64)+(CODE(UPPER(RIGHT(LEFT(A85,8),1)))-64) )/1000000 -> 4.2e-05 | I85: =G85+H85/10 -> 0.0075042 | J85: =IF($O85="","",I85) -> 0.0075042 | K85: =IF($O85="",I85,"") | L85: =F85-I85 -> 4.9924958 | M85: =IF($O85="","",L85) -> 4.9924958 | N85: =IF($O85="",L85,"") | O85: Y | P85: Navarra | Q85: Playing as Navarra | R85: - It is *not* the Age of Absolutism or the Age of Revolutions - At least 32 provinces in Iberia have Basque culture | U85: =IF($D85="E",K85,"") | V85: =IF($D85="M",K85,"") | W85: =IF($D85="H",K85,"") | X85: =IF($D85="VE",K85,"") | Y85: =VLOOKUP($A85,Runs!$G:$G,1,FALSE) -> #N/A
A86: Forgive me, for I have Sindh | B86: Become Christian as Sindh. | C86: 0.008 | D86: E | E86: =(30-C86*100)*VLOOKUP($D86,Calc!$A$1:$C$6,3,FALSE) -> 29.2 | F86: =VLOOKUP(D86,Calc!$A$1:$B$6,2,FALSE) -> 2 | G86: =C86+F86/10000 -> 0.0082 | H86: =( (CODE(UPPER(LEFT(A86,1)))-64)+(CODE(UPPER(RIGHT(LEFT(A86,2),1)))-64)+(CODE(UPPER(RIGHT(LEFT(A86,3),1)))-64)+(CODE(UPPER(RIGHT(LEFT(A86,4),1)))-64)+(CODE(UPPER(RIGHT(LEFT(A86,5),1)))-64)+(CODE(UPPER(RIGHT(LEFT(A86,6),1)))-64)+(CODE(UPPER(RIGHT(LEFT(A86,7),1)))-64)+(CODE(UPPER(RIGHT(LEFT(A86,8),1)))-64) )/1000000 -> 5e-05 | I86: =G86+H86/10 -> 0.008205 | J86: =IF($O86="","",I86) | K86: =IF($O86="",I86,"") -> 0.008205 | L86: =F86-I86 -> 1.991795 | M86: =IF($O86="","",L86) | N86: =IF($O86="",L86,"") -> 1.991795 | Q86: Playing as Sindh | R86: - Is Sindh - Religion is in Christian group | S86: The island Suqutra is the nearest Christian province and can be easily conquered from its owner Mahra, who will normally ally your neighbor Baluchistan. Sell your province Umarkot to a neighboring country (since Baluchistan does not want it) and declare war on them with your reconquest casus belli. Then, head to Mahra to eliminate their armies and siege their provinces until they will accept giving you Suqutra in a separate peace deal (you do not need to land any troops on the island for it to be selectable). Next, give Baluchistan all of your mainland provinces in a peace deal and declare bankruptcy. Since you are an OPM on a Coptic province, this will convert you to Coptic and grant the achievement. | U86: =IF($D86="E",K86,"") -> 0.008205 | V86: =IF($D86="M",K86,"") | W86: =IF($D86="H",K86,"") | X86: =IF($D86="VE",K86,"") | Y86: =VLOOKUP($A86,Runs!$G:$G,1,FALSE) -> Forgive me, for I have Sindh
A87: Spaghetti Western | B87: Starting as Bologna, become Mexico or Texas. | C87: 0.008 | D87: H | E87: =(30-C87*100)*VLOOKUP($D87,Calc!$A$1:$C$6,3,FALSE) -> 146 | F87: =VLOOKUP(D87,Calc!$A$1:$B$6,2,FALSE) -> 4 | G87: =C87+F87/10000 -> 0.0084 | H87: =( (CODE(UPPER(LEFT(A87,1)))-64)+(CODE(UPPER(RIGHT(LEFT(A87,2),1)))-64)+(CODE(UPPER(RIGHT(LEFT(A87,3),1)))-64)+(CODE(UPPER(RIGHT(LEFT(A87,4),1)))-64)+(CODE(UPPER(RIGHT(LEFT(A87,5),1)))-64)+(CODE(UPPER(RIGHT(LEFT(A87,6),1)))-64)+(CODE(UPPER(RIGHT(LEFT(A87,7),1)))-64)+(CODE(UPPER(RIGHT(LEFT(A87,8),1)))-64) )/1000000 -> 9.6e-05 | I87: =G87+H87/10 -> 0.0084096 | J87: =IF($O87="","",I87) -> 0.0084096 | K87: =IF($O87="",I87,"") | L87: =F87-I87 -> 3.9915904 | M87: =IF($O87="","",L87) -> 3.9915904 | N87: =IF($O87="",L87,"") | O87: Y | P87: Bologna | Q87: - Playing as Bologna - *Not* using a random New World | R87: Is Mexico*or*Texas*or*Sonora | S87: Easiest to do by forming a colonial nation in the Mexico colonial region (to form Mexico) or the Rio Grande region (to form Texas) and then release and play as them which requires Conquest of Paradise. But it is also possible to form Mexico or Texas by moving your capital to the previously mentioned (colonial) region before a colonial nation forms. Then no DLC is necessary. | U87: =IF($D87="E",K87,"") | V87: =IF($D87="M",K87,"") | W87: =IF($D87="H",K87,"") | X87: =IF($D87="VE",K87,"") | Y87: =VLOOKUP($A87,Runs!$G:$G,1,FALSE) -> Spaghetti Western
A88: Philippine Tiger | B88: As Cebu, recreate the Chola Empire. | C88: 0.008 | D88: H | E88: =(30-C88*100)*VLOOKUP($D88,Calc!$A$1:$C$6,3,FALSE) -> 146 | F88: =VLOOKUP(D88,Calc!$A$1:$B$6,2,FALSE) -> 4 | G88: =C88+F88/10000 -> 0.0084 | H88: =( (CODE(UPPER(LEFT(A88,1)))-64)+(CODE(UPPER(RIGHT(LEFT(A88,2),1)))-64)+(CODE(UPPER(RIGHT(LEFT(A88,3),1)))-64)+(CODE(UPPER(RIGHT(LEFT(A88,4),1)))-64)+(CODE(UPPER(RIGHT(LEFT(A88,5),1)))-64)+(CODE(UPPER(RIGHT(LEFT(A88,6),1)))-64)+(CODE(UPPER(RIGHT(LEFT(A88,7),1)))-64)+(CODE(UPPER(RIGHT(LEFT(A88,8),1)))-64) )/1000000 -> 9.5e-05 | I88: =G88+H88/10 -> 0.0084095 | J88: =IF($O88="","",I88) | K88: =IF($O88="",I88,"") -> 0.0084095 | L88: =F88-I88 -> 3.9915905 | M88: =IF($O88="","",L88) | N88: =IF($O88="",L88,"") -> 3.9915905 | R88: - Is Cebu - Own the following provinces: | U88: =IF($D88="E",K88,"") | V88: =IF($D88="M",K88,"") | W88: =IF($D88="H",K88,"") -> 0.0084095 | X88: =IF($D88="VE",K88,"") | Y88: =VLOOKUP($A88,Runs!$G:$G,1,FALSE) -> Philippine Tiger
A89: Never say Nevers | B89: As Nevers, own the entire France region as core provinces. | C89: 0.008 | D89: H | E89: =(30-C89*100)*VLOOKUP($D89,Calc!$A$1:$C$6,3,FALSE) -> 146 | F89: =VLOOKUP(D89,Calc!$A$1:$B$6,2,FALSE) -> 4 | G89: =C89+F89/10000 -> 0.0084 | H89: =( (CODE(UPPER(LEFT(A89,1)))-64)+(CODE(UPPER(RIGHT(LEFT(A89,2),1)))-64)+(CODE(UPPER(RIGHT(LEFT(A89,3),1)))-64)+(CODE(UPPER(RIGHT(LEFT(A89,4),1)))-64)+(CODE(UPPER(RIGHT(LEFT(A89,5),1)))-64)+(CODE(UPPER(RIGHT(LEFT(A89,6),1)))-64)+(CODE(UPPER(RIGHT(LEFT(A89,7),1)))-64)+(CODE(UPPER(RIGHT(LEFT(A89,8),1)))-64) )/1000000 -> 5.2e-05 | I89: =G89+H89/10 -> 0.0084052 | J89: =IF($O89="","",I89) -> 0.0084052 | K89: =IF($O89="",I89,"") | L89: =F89-I89 -> 3.9915948 | M89: =IF($O89="","",L89) -> 3.9915948 | N89: =IF($O89="",L89,"") | O89: Y | P89: Nevers | Q89: Playing as Nevers | R89: - Is Nevers - Own and have cores on every province in the France region. | U89: =IF($D89="E",K89,"") | V89: =IF($D89="M",K89,"") | W89: =IF($D89="H",K89,"") | X89: =IF($D89="VE",K89,"") | Y89: =VLOOKUP($A89,Runs!$G:$G,1,FALSE) -> #N/A
A90: Meissner Porcelain | B90: As Saxony, own or have a subject own all Chinaware provinces in the world. | C90: 0.008 | D90: H | E90: =(30-C90*100)*VLOOKUP($D90,Calc!$A$1:$C$6,3,FALSE) -> 146 | F90: =VLOOKUP(D90,Calc!$A$1:$B$6,2,FALSE) -> 4 | G90: =C90+F90/10000 -> 0.0084 | H90: =( (CODE(UPPER(LEFT(A90,1)))-64)+(CODE(UPPER(RIGHT(LEFT(A90,2),1)))-64)+(CODE(UPPER(RIGHT(LEFT(A90,3),1)))-64)+(CODE(UPPER(RIGHT(LEFT(A90,4),1)))-64)+(CODE(UPPER(RIGHT(LEFT(A90,5),1)))-64)+(CODE(UPPER(RIGHT(LEFT(A90,6),1)))-64)+(CODE(UPPER(RIGHT(LEFT(A90,7),1)))-64)+(CODE(UPPER(RIGHT(LEFT(A90,8),1)))-64) )/1000000 -> 0.000102 | I90: =G90+H90/10 -> 0.0084102 | J90: =IF($O90="","",I90) | K90: =IF($O90="",I90,"") -> 0.0084102 | L90: =F90-I90 -> 3.9915898 | M90: =IF($O90="","",L90) | N90: =IF($O90="",L90,"") -> 3.9915898 | Q90: Playing as Saxony | R90: - *Not* playing as a released vassal - Is Saxony - All provinces with chinaware are owned by Saxony or its non-tributary subjects. | S90: Chinaware appears in China, Japan, Korea and the East Indies. | U90: =IF($D90="E",K90,"") | V90: =IF($D90="M",K90,"") | W90: =IF($D90="H",K90,"") -> 0.0084102 | X90: =IF($D90="VE",K90,"") | Y90: =VLOOKUP($A90,Runs!$G:$G,1,FALSE) -> Meissner Porcelain
A91: Kushite Restoration | B91: As a Nubian culture nation, own or have a non-Tributary subject own the entire Egyptian region. | C91: 0.008 | D91: H | E91: =(30-C91*100)*VLOOKUP($D91,Calc!$A$1:$C$6,3,FALSE) -> 146 | F91: =VLOOKUP(D91,Calc!$A$1:$B$6,2,FALSE) -> 4 | G91: =C91+F91/10000 -> 0.0084 | H91: =( (CODE(UPPER(LEFT(A91,1)))-64)+(CODE(UPPER(RIGHT(LEFT(A91,2),1)))-64)+(CODE(UPPER(RIGHT(LEFT(A91,3),1)))-64)+(CODE(UPPER(RIGHT(LEFT(A91,4),1)))-64)+(CODE(UPPER(RIGHT(LEFT(A91,5),1)))-64)+(CODE(UPPER(RIGHT(LEFT(A91,6),1)))-64)+(CODE(UPPER(RIGHT(LEFT(A91,7),1)))-64)+(CODE(UPPER(RIGHT(LEFT(A91,8),1)))-64) )/1000000 -> 6.1e-05 | I91: =G91+H91/10 -> 0.0084061 | J91: =IF($O91="","",I91) | K91: =IF($O91="",I91,"") -> 0.0084061 | L91: =F91-I91 -> 3.9915939 | M91: =IF($O91="","",L91) | N91: =IF($O91="",L91,"") -> 3.9915939 | Q91: Primary culture is *Nubian* | R91: All provinces in the Egypt region are owned by the player's country *or* its non-tributary subjects. | S91: Possible starts are Dongola, Alodia, and Makuria. | U91: =IF($D91="E",K91,"") | V91: =IF($D91="M",K91,"") | W91: =IF($D91="H",K91,"") -> 0.0084061 | X91: =IF($D91="VE",K91,"") | Y91: =VLOOKUP($A91,Runs!$G:$G,1,FALSE) -> Kushite Restoration
A92: It's All Greek To Me | B92: Form Greece and own and have cores on Zeta, Thatta, Lamba, and Roh. | C92: 0.008 | D92: H | E92: =(30-C92*100)*VLOOKUP($D92,Calc!$A$1:$C$6,3,FALSE) -> 146 | F92: =VLOOKUP(D92,Calc!$A$1:$B$6,2,FALSE) -> 4 | G92: =C92+F92/10000 -> 0.0084 | H92: =( (CODE(UPPER(LEFT(A92,1)))-64)+(CODE(UPPER(RIGHT(LEFT(A92,2),1)))-64)+(CODE(UPPER(RIGHT(LEFT(A92,3),1)))-64)+(CODE(UPPER(RIGHT(LEFT(A92,4),1)))-64)+(CODE(UPPER(RIGHT(LEFT(A92,5),1)))-64)+(CODE(UPPER(RIGHT(LEFT(A92,6),1)))-64)+(CODE(UPPER(RIGHT(LEFT(A92,7),1)))-64)+(CODE(UPPER(RIGHT(LEFT(A92,8),1)))-64) )/1000000 -> 1.6e-05 | I92: =G92+H92/10 -> 0.0084016 | J92: =IF($O92="","",I92) -> 0.0084016 | K92: =IF($O92="",I92,"") | L92: =F92-I92 -> 3.9915984 | M92: =IF($O92="","",L92) -> 3.9915984 | N92: =IF($O92="",L92,"") | O92: Y | P92: Knights | R92: - Is Greece - Own the core provinces of Zeta (138), Thatta (504), Roh (578), and Lamba (4104) | S92: - Forming Greece requires Greek primary culture. Zeta begins held by Serbia, Thatta held by Sindh, Roh held by Afghanistan, and Lamba uncolonized in Central Africa. - Alternatively, you can conquer Byzantium and wait for Greek cores to form after the Greek Separatism event fires (requires Admin Tech 20). Release Greece as a vassal and feed him the required provinces. Once they are cored, diplomatically annex Greece and release them again, but chose to play as Greece this time. Note that since Thatta is in a Trade Company region you must own the province yourself to state and fully core it before giving it to Greece, otherwise they will lose their territorial core upon annexing. | U92: =IF($D92="E",K92,"") | V92: =IF($D92="M",K92,"") | W92: =IF($D92="H",K92,"") | X92: =IF($D92="VE",K92,"") | Y92: =VLOOKUP($A92,Runs!$G:$G,1,FALSE) -> #N/A
A93: Holy Horder | B93: Starting as the Teutonic Order, form the Mongol Empire while have the Holy Horde government reform enacted. | C93: 0.008 | D93: H | E93: =(30-C93*100)*VLOOKUP($D93,Calc!$A$1:$C$6,3,FALSE) -> 146 | F93: =VLOOKUP(D93,Calc!$A$1:$B$6,2,FALSE) -> 4 | G93: =C93+F93/10000 -> 0.0084 | H93: =( (CODE(UPPER(LEFT(A93,1)))-64)+(CODE(UPPER(RIGHT(LEFT(A93,2),1)))-64)+(CODE(UPPER(RIGHT(LEFT(A93,3),1)))-64)+(CODE(UPPER(RIGHT(LEFT(A93,4),1)))-64)+(CODE(UPPER(RIGHT(LEFT(A93,5),1)))-64)+(CODE(UPPER(RIGHT(LEFT(A93,6),1)))-64)+(CODE(UPPER(RIGHT(LEFT(A93,7),1)))-64)+(CODE(UPPER(RIGHT(LEFT(A93,8),1)))-64) )/1000000 -> 6.9e-05 | I93: =G93+H93/10 -> 0.0084069 | J93: =IF($O93="","",I93) | K93: =IF($O93="",I93,"") -> 0.0084069 | L93: =F93-I93 -> 3.9915931 | M93: =IF($O93="","",L93) | N93: =IF($O93="",L93,"") -> 3.9915931 | Q93: Playing as Teutonic Order | R93: - *Not* playing as a released vassal - Is the Mongol Empire - Has enacted the Holy Horde government reform | S93: To form the Mongol Empire as the Teutonic Order you need to choose the crusader path of missions after completing Defeat Poland, this will unlock the mission Crusaders of the Steppes which allows forming the Mongol Empire due to the unique government reform. | U93: =IF($D93="E",K93,"") | V93: =IF($D93="M",K93,"") | W93: =IF($D93="H",K93,"") -> 0.0084069 | X93: =IF($D93="VE",K93,"") | Y93: =VLOOKUP($A93,Runs!$G:$G,1,FALSE) -> Holy Horder
A94: Cotton Kandy | B94: As Kandy be production leader in Cotton. | C94: 0.008 | D94: H | E94: =(30-C94*100)*VLOOKUP($D94,Calc!$A$1:$C$6,3,FALSE) -> 146 | F94: =VLOOKUP(D94,Calc!$A$1:$B$6,2,FALSE) -> 4 | G94: =C94+F94/10000 -> 0.0084 | H94: =( (CODE(UPPER(LEFT(A94,1)))-64)+(CODE(UPPER(RIGHT(LEFT(A94,2),1)))-64)+(CODE(UPPER(RIGHT(LEFT(A94,3),1)))-64)+(CODE(UPPER(RIGHT(LEFT(A94,4),1)))-64)+(CODE(UPPER(RIGHT(LEFT(A94,5),1)))-64)+(CODE(UPPER(RIGHT(LEFT(A94,6),1)))-64)+(CODE(UPPER(RIGHT(LEFT(A94,7),1)))-64)+(CODE(UPPER(RIGHT(LEFT(A94,8),1)))-64) )/1000000 -> 6.6e-05 | I94: =G94+H94/10 -> 0.0084066 | J94: =IF($O94="","",I94) -> 0.0084066 | K94: =IF($O94="",I94,"") | L94: =F94-I94 -> 3.9915934 | M94: =IF($O94="","",L94) -> 3.9915934 | N94: =IF($O94="",L94,"") | O94: Y | P94: Kandy | Q94: Playing as Kandy | R94: - Is Kandy - Be production leader of cotton | S94: The Indian sub-continent already has the highest concentration of cotton-producing provinces in the game, so this achievement is best partnered with The Buddhists Strike Back. | U94: =IF($D94="E",K94,"") | V94: =IF($D94="M",K94,"") | W94: =IF($D94="H",K94,"") | X94: =IF($D94="VE",K94,"") | Y94: =VLOOKUP($A94,Runs!$G:$G,1,FALSE) -> Cotton Kandy
A95: Breaking the Yoke | B95: As Ryazan, own Saratov, Crimea and Kazan while being independent. | C95: 0.008 | D95: H | E95: =(30-C95*100)*VLOOKUP($D95,Calc!$A$1:$C$6,3,FALSE) -> 146 | F95: =VLOOKUP(D95,Calc!$A$1:$B$6,2,FALSE) -> 4 | G95: =C95+F95/10000 -> 0.0084 | H95: =( (CODE(UPPER(LEFT(A95,1)))-64)+(CODE(UPPER(RIGHT(LEFT(A95,2),1)))-64)+(CODE(UPPER(RIGHT(LEFT(A95,3),1)))-64)+(CODE(UPPER(RIGHT(LEFT(A95,4),1)))-64)+(CODE(UPPER(RIGHT(LEFT(A95,5),1)))-64)+(CODE(UPPER(RIGHT(LEFT(A95,6),1)))-64)+(CODE(UPPER(RIGHT(LEFT(A95,7),1)))-64)+(CODE(UPPER(RIGHT(LEFT(A95,8),1)))-64) )/1000000 -> 6.7e-05 | I95: =G95+H95/10 -> 0.0084067 | J95: =IF($O95="","",I95) -> 0.0084067 | K95: =IF($O95="",I95,"") | L95: =F95-I95 -> 3.9915933 | M95: =IF($O95="","",L95) -> 3.9915933 | N95: =IF($O95="",L95,"") | O95: Y | P95: Ryazan | Q95: Playing as Ryazan | R95: - Is *not* a subject nation - Own the provinces of Crimea (284), Kazan (1082) and Saratov (303) | U95: =IF($D95="E",K95,"") | V95: =IF($D95="M",K95,"") | W95: =IF($D95="H",K95,"") | X95: =IF($D95="VE",K95,"") | Y95: =VLOOKUP($A95,Runs!$G:$G,1,FALSE) -> Breaking the Yoke
A96: Victorian Three | B96: As Busoga, Buganda or Karagwe, reach administrative, diplomatic and military technology level 32. | C96: 0.008 | D96: M | E96: =(30-C96*100)*VLOOKUP($D96,Calc!$A$1:$C$6,3,FALSE) -> 73 | F96: =VLOOKUP(D96,Calc!$A$1:$B$6,2,FALSE) -> 3 | G96: =C96+F96/10000 -> 0.0083 | H96: =( (CODE(UPPER(LEFT(A96,1)))-64)+(CODE(UPPER(RIGHT(LEFT(A96,2),1)))-64)+(CODE(UPPER(RIGHT(LEFT(A96,3),1)))-64)+(CODE(UPPER(RIGHT(LEFT(A96,4),1)))-64)+(CODE(UPPER(RIGHT(LEFT(A96,5),1)))-64)+(CODE(UPPER(RIGHT(LEFT(A96,6),1)))-64)+(CODE(UPPER(RIGHT(LEFT(A96,7),1)))-64)+(CODE(UPPER(RIGHT(LEFT(A96,8),1)))-64) )/1000000 -> 9.7e-05 | I96: =G96+H96/10 -> 0.0083097 | J96: =IF($O96="","",I96) | K96: =IF($O96="",I96,"") -> 0.0083097 | L96: =F96-I96 -> 2.9916903 | M96: =IF($O96="","",L96) | N96: =IF($O96="",L96,"") -> 2.9916903 | Q96: Playing as *either*: - Buganda - Busoga - Karagwe | R96: - Administration technology is *32* - Diplomatic technology is *32* - Military technology is *32* | S96: Most easily accomplished by manually spawning Renaissance, Colonialism and Printing Press, and not expanding too much. To get the other institutions, build manufactories and universities. Researching level 32 loses the ahead-of-time penalty in 1820. | U96: =IF($D96="E",K96,"") | V96: =IF($D96="M",K96,"") -> 0.0083097 | W96: =IF($D96="H",K96,"") | X96: =IF($D96="VE",K96,"") | Y96: =VLOOKUP($A96,Runs!$G:$G,1,FALSE) -> Victorian Three
A97: Super Trooper | B97: Starting as Sweden, enact the Allotment System government reform, have 80 regiments of Carolean raised at the same time with at least +40% infantry combat ability. | C97: 0.008 | D97: M | E97: =(30-C97*100)*VLOOKUP($D97,Calc!$A$1:$C$6,3,FALSE) -> 73 | F97: =VLOOKUP(D97,Calc!$A$1:$B$6,2,FALSE) -> 3 | G97: =C97+F97/10000 -> 0.0083 | H97: =( (CODE(UPPER(LEFT(A97,1)))-64)+(CODE(UPPER(RIGHT(LEFT(A97,2),1)))-64)+(CODE(UPPER(RIGHT(LEFT(A97,3),1)))-64)+(CODE(UPPER(RIGHT(LEFT(A97,4),1)))-64)+(CODE(UPPER(RIGHT(LEFT(A97,5),1)))-64)+(CODE(UPPER(RIGHT(LEFT(A97,6),1)))-64)+(CODE(UPPER(RIGHT(LEFT(A97,7),1)))-64)+(CODE(UPPER(RIGHT(LEFT(A97,8),1)))-64) )/1000000 -> 8.5e-05 | I97: =G97+H97/10 -> 0.0083085 | J97: =IF($O97="","",I97) -> 0.0083085 | K97: =IF($O97="",I97,"") | L97: =F97-I97 -> 2.9916915 | M97: =IF($O97="","",L97) -> 2.9916915 | N97: =IF($O97="",L97,"") | O97: Y | P97: Sweden | Q97: Playing as Sweden | R97: - / Has enacted the Allotment System government reform - Has at least 80 carolean regiments - Infantry combat ability is at least *40%* | S97: Take quality and innovative ideas for *45%* infantry combat ability with swedish ideas. Since only development from swedish and finnish cultured provinces counts towards increasing how many carolean regiments are available you need to culture convert other provinces to reach 800 development. | U97: =IF($D97="E",K97,"") | V97: =IF($D97="M",K97,"") | W97: =IF($D97="H",K97,"") | X97: =IF($D97="VE",K97,"") | Y97: =VLOOKUP($A97,Runs!$G:$G,1,FALSE) -> #N/A
A98: Napoleon’s Ambition | B98: As Revolutionary France, spread the Revolution to 10 countries. | C98: 0.008 | D98: M | E98: =(30-C98*100)*VLOOKUP($D98,Calc!$A$1:$C$6,3,FALSE) -> 73 | F98: =VLOOKUP(D98,Calc!$A$1:$B$6,2,FALSE) -> 3 | G98: =C98+F98/10000 -> 0.0083 | H98: =( (CODE(UPPER(LEFT(A98,1)))-64)+(CODE(UPPER(RIGHT(LEFT(A98,2),1)))-64)+(CODE(UPPER(RIGHT(LEFT(A98,3),1)))-64)+(CODE(UPPER(RIGHT(LEFT(A98,4),1)))-64)+(CODE(UPPER(RIGHT(LEFT(A98,5),1)))-64)+(CODE(UPPER(RIGHT(LEFT(A98,6),1)))-64)+(CODE(UPPER(RIGHT(LEFT(A98,7),1)))-64)+(CODE(UPPER(RIGHT(LEFT(A98,8),1)))-64) )/1000000 -> 9.2e-05 | I98: =G98+H98/10 -> 0.0083092 | J98: =IF($O98="","",I98) -> 0.0083092 | K98: =IF($O98="",I98,"") | L98: =F98-I98 -> 2.9916908 | M98: =IF($O98="","",L98) -> 2.9916908 | N98: =IF($O98="",L98,"") | O98: Y | P98: France | Q98: *Not* using a random New World | R98: - Is France - has used the *“Spread the Revolution”* peace term 10 times | S98: "Spread the Revolution" peace term can only be used by the revolution target against nations that have at least one province the Center of Revolution hasn't spread to. They can also only be used against the country directly attacked with the CB (not any allies). Best done quickly as revolutionary ideas can spread across the entire world, preventing the achievement. Small nations in the Americas, Africa and Asia can be targeted to get to 10 if necessary. | U98: =IF($D98="E",K98,"") | V98: =IF($D98="M",K98,"") | W98: =IF($D98="H",K98,"") | X98: =IF($D98="VE",K98,"") | Y98: =VLOOKUP($A98,Runs!$G:$G,1,FALSE) -> #N/A
A99: Home and Away | B99: As Wales, hold Cardiff, Dublin, Edinburgh, Rome, Paris and London. | C99: 0.008 | D99: M | E99: =(30-C99*100)*VLOOKUP($D99,Calc!$A$1:$C$6,3,FALSE) -> 73 | F99: =VLOOKUP(D99,Calc!$A$1:$B$6,2,FALSE) -> 3 | G99: =C99+F99/10000 -> 0.0083 | H99: =( (CODE(UPPER(LEFT(A99,1)))-64)+(CODE(UPPER(RIGHT(LEFT(A99,2),1)))-64)+(CODE(UPPER(RIGHT(LEFT(A99,3),1)))-64)+(CODE(UPPER(RIGHT(LEFT(A99,4),1)))-64)+(CODE(UPPER(RIGHT(LEFT(A99,5),1)))-64)+(CODE(UPPER(RIGHT(LEFT(A99,6),1)))-64)+(CODE(UPPER(RIGHT(LEFT(A99,7),1)))-64)+(CODE(UPPER(RIGHT(LEFT(A99,8),1)))-64) )/1000000 -> 2.8e-05 | I99: =G99+H99/10 -> 0.0083028 | J99: =IF($O99="","",I99) | K99: =IF($O99="",I99,"") -> 0.0083028 | L99: =F99-I99 -> 2.9916972 | M99: =IF($O99="","",L99) | N99: =IF($O99="",L99,"") -> 2.9916972 | R99: - Is Wales - Own Glamorgan (241), Pale (373), Lothian (248), Roma (118), Paris (183) and London (236) | S99: - It is not needed to core the required provinces. - The welsh names of the provinces in eu4 are Morgannwg(241), Dulyn(373), Lleuddiniawn(248), Rhufain(118), Paris(183) and Llundain(236) | U99: =IF($D99="E",K99,"") | V99: =IF($D99="M",K99,"") -> 0.0083028 | W99: =IF($D99="H",K99,"") | X99: =IF($D99="VE",K99,"") | Y99: =VLOOKUP($A99,Runs!$G:$G,1,FALSE) -> Home and Away
A100: Don’t be Cilli | B100: Starting as Cilli, form another nation. | C100: 0.008 | D100: M | E100: =(30-C100*100)*VLOOKUP($D100,Calc!$A$1:$C$6,3,FALSE) -> 73 | F100: =VLOOKUP(D100,Calc!$A$1:$B$6,2,FALSE) -> 3 | G100: =C100+F100/10000 -> 0.0083 | H100: =( (CODE(UPPER(LEFT(A100,1)))-64)+(CODE(UPPER(RIGHT(LEFT(A100,2),1)))-64)+(CODE(UPPER(RIGHT(LEFT(A100,3),1)))-64)+(CODE(UPPER(RIGHT(LEFT(A100,4),1)))-64)+(CODE(UPPER(RIGHT(LEFT(A100,5),1)))-64)+(CODE(UPPER(RIGHT(LEFT(A100,6),1)))-64)+(CODE(UPPER(RIGHT(LEFT(A100,7),1)))-64)+(CODE(UPPER(RIGHT(LEFT(A100,8),1)))-64) )/1000000 -> 0.00011 | I100: =G100+H100/10 -> 0.008311 | J100: =IF($O100="","",I100) -> 0.008311 | K100: =IF($O100="",I100,"") | L100: =F100-I100 -> 2.991689 | M100: =IF($O100="","",L100) -> 2.991689 | N100: =IF($O100="",L100,"") | O100: Y | P100: Cilli | Q100: - Playing as Cilli - *Not* using a random New World | R100: - is *not*Cilli - *Not* playing as a released vassal | S100: Can be done by annexing Croatia, then culture shifting and re-forming it. Use the fact that you are eligible to form a royal marriage with both Austria and Hungary in the early game and later grab alliances with Poland and/or Bohemia to defeat Hungary for the important provinces. | U100: =IF($D100="E",K100,"") | V100: =IF($D100="M",K100,"") | W100: =IF($D100="H",K100,"") | X100: =IF($D100="VE",K100,"") | Y100: =VLOOKUP($A100,Runs!$G:$G,1,FALSE) -> Don’t be Cilli
...

Sheet Formable Countries
A1: Non-colonial Formable | B1: End Game Tag? | C1: non "starting as" Achievement | D1: description | E1: "starting as" Achievement | F1: description
A2: Aksum | B2: Yes
A3: Andalusia | B3: Yes | E3: The Re-Reconquista | F3: As Granada, form Andalusia and reconquer all of Iberia.
A4: Angevin Kingdom | B4: Yes
A5: Aotearoa | B5: No
A6: Arabia | B6: Yes
A7: Armenia | B7: No
A8: Australia | B8: Yes | E8: Australia-Hungary | F8: Starting as an Australian tribe unite Australia and subjugate Hungary.
A9: Austria | B9: No | E9: The Zoro-Austrians | F9: Starting as Austria, convert to Zoroastrianism, and complete the Persian Zoroastrian missions.
A10: Bavaria | B10: No | E10: Stern des Südens | F10: Form Bavaria starting as München and have your Subject Bremen own Werder.
A11: Bharat | B11: Yes
A12: Brazil | B12: Yes
A13: Bukhara | B13: No
A14: Bulgaria | B14: No
A15: Byzantium | B15: Yes
A16: Canada | B16: Yes
A17: Commonwealth | B17: Yes | E17: The Uncommonwealth | F17: As Lithuania, become The Commonwealth.
A18: Croatia | B18: No | C18: Krabater | D18: Form the nation of Croatia and station a unit of cavalry in Stockholm.
A19: Dai Viet | B19: No | E19: Disciples of Enlightenment | F19: Starting as Dai Viet, have 10 nations follow the Mahayana Faith by 1500.
A20: Dalmatia | B20: No
A21: Deccan | B21: No
A22: Delhi | B22: No | E22: Emperor of Hindustan | F22: Starting as Delhi, Restore their Empire's borders.
A23: Denmark | B23: No | E23: Brick by Brick The Iron Price Østindisk Kompagni Te | F23: Starting as Denmark, enact the Unified Kalmar Monarchy government reform and own the entire Scandinavian region as your cores. Restore the Danelaw region to Danish rule, and make it Danish culture. As Denmark establish Trade company and have at least 10% Tea market share.
A24: Egypt | B24: No
A25: England | B25: No | E25: Brentry! | F25: Starting as England, form the Angevin Kingdom and enact all the 'Acts of Crown' parliamentary issues.
A26: Eranshahr | B26: Yes | E26: Shahanshah | F26: Start as Ardabil and form Persia or Eranshahr.
A27: Ethiopia | B27: Yes | E27: Prester John | F27: Starting as Ethiopia, own and have cores on Alexandria, Antioch and Constantinople as a Coptic country.
A28: France | B28: Yes
A29: Franconia | B29: No
A30: Georgia | B30: No | C30: Legacy of Saint George | D30: As Georgia, have as vassals Genoa, Aragon, England and Trier or their successors, and control Wales.
A31: Germany | B31: Yes | C31: For the Emperor! | D31: Form Prussia or Germany, have the Empire government rank and 40.000 Marines raised at the same time.
A32: Golden Horde | B32: No
A33: Great Britain | B33: Yes
A34: Great Moravia | B34: No | E34: Great Moravia | F34: Restore the Great Moravian borders as Nitra or Moravia.
A35: Greece | B35: No
A36: Hanover | B36: No
A37: Hausa | B37: No
A38: Hawai'i | B38: No
A39: Hindustan | B39: Yes
A40: Holy Roman Empire | B40: Yes
A41: Hungary | B41: No
A42: Iceland | B42: No
A43: Ilkhanate | B43: No
A44: Inca | B44: No | C44: It's all coming together A Sun God | D44: Complete the Incan mission tree (Sunset invasion missions excluded). Form Inca, embrace all Institutions and own all of South America as core provinces. | E44: From Frankfurt to the Andes | F44: Starting as Frankfurt, form Jerusalem, and then form the Inca while owning Mallorca.
A45: Ireland | B45: No
A46: Israel | B46: No
A47: Italy | B47: Yes
A48: Japan | B48: Yes | C48: Stardust Crusaders | D48: As Japan have the Land of the Christian Sun reform while Palestine and Cairo are Christian under us.
A49: Jerusalem | B49: No
A50: Kitara | B50: No
A51: Kongo | B51: No
A52: Kurland | B52: No
A53: Lan Xang | B53: No
A54: Lanfang | B54: No
A55: Latin Empire | B55: No
A56: Livonia | B56: No | E56: Almost Prussian Blue | F56: Starting as the Livonian Order, form Livonia and own the territory of the North German Confederation as core provinces.
A57: Lotharingia | B57: Yes
A58: Lubeck | B58: No
A59: Macina | B59: No
A60: Malaya | B60: No | C60: The Spice Must Flow | D60: Form the nation of Malaya.
A61: Mali | B61: No | E61: Mansa Musa Abu Bakr II’s Ambition | F61: As Mali, give 10k ducats away to another great power without having a single loan or being bankrupt. Start as Mali and have 4 Colonial Subjects in South America.
A62: Mamluks | B62: No | C62: Breadbasket of the World | D62: As the Mamluks, export grain to every continent at least once. | E62: The Levant Turnabout | F62: As the Mamluks, have 100 Army Professionalism and annex the Ottomans.
A63: Manchu | B63: No
A64: Marathas | B64: No
A65: Maya | B65: No
A66: Mexico | B66: Yes | E66: Spaghetti Western | F66: Starting as Bologna, become Mexico or Texas.
A67: Ming | B67: Yes
A68: Mongol Empire | B68: Yes | E68: Holy Horder | F68: Starting as the Teutonic Order, form the Mongol Empire while have the Holy Horde government reform enacted.
A69: Morocco | B69: No | E69: The Sudanese Expedition | F69: Starting as Morocco, conquer the Niger and Sahel Regions.
A70: Mossi | B70: No
A71: Mughals | B71: Yes | C71: Baborg Sweet Home Qaraqorum | D71: As the Mughals, assimilate at least 12 culture groups. As the Mughals assimilate Mongolian culture. | E71: True Heir of Timur | F71: Starting as a Timurid subject, form the Mughals and conquer India by 1550.
A72: Nagpur | B72: No
A73: Nepal | B73: No | E73: The Pheasant Strut | F73: As Gorkha form Nepal and defeat Prussia with at least 100,000 Prussian casualties in a war (both have to be primary targets of war).
A74: Netherlands | B74: No
A75: Nubia | B75: No
A76: Orissa | B76: No
A77: Ottomans | B77: Yes | C77: Parisian Pasha Definitely the Sultan of Rum | D77: Assign Pasha to Paris. Own and have cores on Rome, Moscow and Istanbul as Ottomans or Rum. | E77: Mehmet's Ambition | F77: Starting as The Ottomans, own or have Core Eyalets own all the provinces required to form the Roman Empire before 1500.
A78: Persia | B78: Yes | C78: King of Kings | D78: Complete the Persian mission tree. | E78: Shahanshah | F78: Start as Ardabil and form Persia or Eranshahr.
A79: Poland | B79: No | E79: Back to the Piast Poland can into space One King to Rule! | F79: As Mazovia, Glogow or Opole, form the nation of Poland. As Poland, reach the maximum level in all technologies (32). As Poland, become an absolutist monarchy, abolishing the Sejm.
A80: Pomerania | B80: No
A81: Prussia | B81: No | C81: For the Emperor! A Fine Goosestep | D81: Form Prussia or Germany, have the Empire government rank and 40.000 Marines raised at the same time. Form Prussia and have at least 125% Discipline.
A82: Punjab | B82: No | C82: Sikh Pun | D82: Convert to Sikhism and form the nation of Punjab.
A83: Qing | B83: Yes
A84: Rajputana | B84: No
A85: Roman Empire | B85: Yes
A86: Romania | B86: No
A87: Rozwi Empire | B87: Yes
A88: Rum | B88: Yes | C88: Parisian Pasha Definitely the Sultan of Rum | D88: Assign Pasha to Paris. Own and have cores on Rome, Moscow and Istanbul as Ottomans or Rum. | E88: A Hero’s Welcome | F88: Starting as Karaman, form the Sultanate of Rum.
A89: Russia | B89: Yes | C89: Triple the Rome | D89: As Russia, be the Emperor of China and the HRE. | E89: All belongs to Mother Russia | F89: Start as a country of Russian culture and form Russia.
A90: Ruthenia | B90: No
A91: Sardinia-Piemont | B91: No
A92: Saxony | B92: No
A93: Scandinavia | B93: Yes
A94: Scotland | B94: No | E94: Auld Alliance Reversed | F94: As Scotland, have France as a vassal (do not form Great Britain).
A95: Shan | B95: No
A96: Siam | B96: No
A97: Silesia | B97: No
A98: Sokoto | B98: No
A99: Somalia | B99: No
A100: Spain | B100: Yes | C100: No Country for Old Tercios Forever Golden Imperio español | D100: As Spain, have Reformed Tercios, 33 Tercio Units, and control 3 Great Power capitals at the same time Complete the Spanish Mission Tree. As Spain have Mexico, Panama, Havana, Cuzco in colonial Nations under you.
...

Sheet Runs
A1: Run ID | B1: Starting country | C1: Run difficulty | D1: Run value | E1: Run value2 | F1: Progress | G1: Name | H1: Done? | I1: Description | J1: Percentage | K1: Difficulty | L1: Points | M1: Starting conditions | N1: Cheesable with custom nation? | O1: Completion requirements | P1: Notes1
A2: 000 | B2: Base | D2: =SUMIFS($L:$L,$A:$A,$A2) -> 15083.95 | E2: =D2/'Top 10 Hard'!$J$2 -> 0.40804818 | F2: =IF(NOT(ISNUMBER(F1)),0,F1)+Table1[[#This Row],[Points]]/'Top 10 Hard'!$J$2 -> 0.40804818 | H2: =IF(VLOOKUP($G2,List!$A:$O,15,FALSE)=0,"",VLOOKUP($G2,List!$A:$O,15,FALSE)) -> #N/A | I2: =VLOOKUP($G2,List!$A:$U,2,FALSE) -> #N/A | J2: =VLOOKUP($G2,List!$A:$U,3,FALSE) -> #N/A | K2: =VLOOKUP($G2,List!$A:$U,4,FALSE) -> #N/A | L2: 15083.95 | M2: =VLOOKUP($G2,List!$A:$U,17,FALSE) -> #N/A | O2: =VLOOKUP($G2,List!$A:$U,18,FALSE) -> #N/A | P2: =VLOOKUP($G2,List!$A:$U,19,FALSE) -> #N/A
A3: 001 | B3: Denmark | C3: M | D3: =SUMIFS($L:$L,$A:$A,$A3) -> 128.2 | E3: =D3/'Top 10 Hard'!$J$2 -> 0.0034680423 | F3: =IF(NOT(ISNUMBER(F2)),0,F2)+Table1[[#This Row],[Points]]/'Top 10 Hard'!$J$2 -> 0.40882728 | G3: Brick by Brick | H3: =IF(VLOOKUP($G3,List!$A:$O,15,FALSE)=0,"",VLOOKUP($G3,List!$A:$O,15,FALSE)) -> Y | I3: =VLOOKUP($G3,List!$A:$U,2,FALSE) -> Starting as Denmark, enact the Unified Kalmar Monarchy government reform and own the entire Scandinavian region as your cores. | J3: =VLOOKUP($G3,List!$A:$U,3,FALSE) -> 0.012 | K3: =VLOOKUP($G3,List!$A:$U,4,FALSE) -> E | L3: =VLOOKUP($G3,List!$A:$U,5,FALSE) -> 28.8 | M3: =VLOOKUP($G3,List!$A:$U,17,FALSE) -> Playing as Denmark | N3: No | O3: =VLOOKUP($G3,List!$A:$U,18,FALSE) -> - Has enacted the Unified Kalmar Monarchy government reform - Own and core all provinces in the Scandinavia region | P3: =VLOOKUP($G3,List!$A:$U,19,FALSE) -> Make sure that you always have at least one junior partner in Scandinavia, because otherwise you will lose the starting reform Kalmar Union, because you can only get the reform Unified Kalmar Monarchy by completing the mission Ratify the Kalmar Union while having the reform Kalmar Union.
A4: 001 | B4: Denmark | C4: M | D4: =SUMIFS($L:$L,$A:$A,$A4) -> 128.2 | E4: =D4/'Top 10 Hard'!$J$2 -> 0.0034680423 | F4: =IF(NOT(ISNUMBER(F3)),0,F3)+Table1[[#This Row],[Points]]/'Top 10 Hard'!$J$2 -> 0.41073443 | G4: The Iron Price | H4: =IF(VLOOKUP($G4,List!$A:$O,15,FALSE)=0,"",VLOOKUP($G4,List!$A:$O,15,FALSE)) -> Y | I4: =VLOOKUP($G4,List!$A:$U,2,FALSE) -> Restore the Danelaw region to Danish rule, and make it Danish culture. | J4: =VLOOKUP($G4,List!$A:$U,3,FALSE) -> 0.018 | K4: =VLOOKUP($G4,List!$A:$U,4,FALSE) -> M | L4: =VLOOKUP($G4,List!$A:$U,5,FALSE) -> 70.5 | M4: =VLOOKUP($G4,List!$A:$U,17,FALSE) -> Playing as Denmark | N4: No | O4: =VLOOKUP($G4,List!$A:$U,18,FALSE) -> - Own and core Northumberland and the Yorkshire, East Midlands, and East Anglia areas. - All these provinces have *Danish*culture. | P4: =VLOOKUP($G4,List!$A:$U,19,FALSE) -> 0
A5: 001 | B5: Denmark | C5: M | D5: =SUMIFS($L:$L,$A:$A,$A5) -> 128.2 | E5: =D5/'Top 10 Hard'!$J$2 -> 0.0034680423 | F5: =IF(NOT(ISNUMBER(F4)),0,F4)+Table1[[#This Row],[Points]]/'Top 10 Hard'!$J$2 -> 0.41151623 | G5: Østindisk Kompagni Te | H5: =IF(VLOOKUP($G5,List!$A:$O,15,FALSE)=0,"",VLOOKUP($G5,List!$A:$O,15,FALSE)) -> Y | I5: =VLOOKUP($G5,List!$A:$U,2,FALSE) -> As Denmark establish Trade company and have at least 10% Tea market share. | J5: =VLOOKUP($G5,List!$A:$U,3,FALSE) -> 0.011 | K5: =VLOOKUP($G5,List!$A:$U,4,FALSE) -> E | L5: =VLOOKUP($G5,List!$A:$U,5,FALSE) -> 28.9 | M5: =VLOOKUP($G5,List!$A:$U,17,FALSE) -> - Playing as Denmark | N5: No | O5: =VLOOKUP($G5,List!$A:$U,18,FALSE) -> - Is Denmark*or*Scandinavia - Has at least one province in Asia assigned to a trade company - Has 10% market share in Tea | P5: =VLOOKUP($G5,List!$A:$U,19,FALSE) -> Easiest when Denmark chooses exploration ideas early to reach Southeast Asia. Then form a claim in Ayutthaya or wait for Mingsplosion.
A6: 002 | B6: Frankfurt | C6: VH | D6: =SUMIFS($L:$L,$A:$A,$A6) -> 443.25 | E6: =D6/'Top 10 Hard'!$J$2 -> 0.011990716 | F6: =IF(NOT(ISNUMBER(F5)),0,F5)+Table1[[#This Row],[Points]]/'Top 10 Hard'!$J$2 -> 0.41957767 | G6: From Frankfurt to the Andes | H6: =IF(VLOOKUP($G6,List!$A:$O,15,FALSE)=0,"",VLOOKUP($G6,List!$A:$O,15,FALSE)) -> Y | I6: =VLOOKUP($G6,List!$A:$U,2,FALSE) -> Starting as Frankfurt, form Jerusalem, and then form the Inca while owning Mallorca. | J6: =VLOOKUP($G6,List!$A:$U,3,FALSE) -> 0.002 | K6: =VLOOKUP($G6,List!$A:$U,4,FALSE) -> VH | L6: =VLOOKUP($G6,List!$A:$U,5,FALSE) -> 298 | M6: =VLOOKUP($G6,List!$A:$U,17,FALSE) -> Playing as Frankfurt | N6: No | O6: =VLOOKUP($G6,List!$A:$U,18,FALSE) -> - Was Frankfurt - Was Jerusalem - Is Inca - Own Mallorca (333) | P6: =VLOOKUP($G6,List!$A:$U,19,FALSE) -> - Hardest part of this achievement is finding and fulfilling conditions for different tag formation. - To form Jerusalem, you need to get into coring range of Jerusalem area (vassalize an Italian minor and conquer a province next to it), own and state Jerusalem area, move capital to Arabia, Egypt or Mashriq and switch from Republic to Monarchy. And this has to be done before the Age of Reformation ends, because Frankfurt can't form Jerusalem later. - To form Inca you need to move your capital to the New World, own cores on required provinces, culture shift to Andean culture and change your religion to a pagan faith via rebels. - Switching to play as a released vassal will invalidate the achievement.
A7: 002 | B7: Frankfurt | C7: VH | D7: =SUMIFS($L:$L,$A:$A,$A7) -> 443.25 | E7: =D7/'Top 10 Hard'!$J$2 -> 0.011990716 | F7: =IF(NOT(ISNUMBER(F6)),0,F6)+Table1[[#This Row],[Points]]/'Top 10 Hard'!$J$2 -> 0.42158626 | G7: It's all coming together | H7: =IF(VLOOKUP($G7,List!$A:$O,15,FALSE)=0,"",VLOOKUP($G7,List!$A:$O,15,FALSE)) -> Y | I7: =VLOOKUP($G7,List!$A:$U,2,FALSE) -> Complete the Incan mission tree (Sunset invasion missions excluded). | J7: =VLOOKUP($G7,List!$A:$U,3,FALSE) -> 0.003 | K7: =VLOOKUP($G7,List!$A:$U,4,FALSE) -> M | L7: =VLOOKUP($G7,List!$A:$U,5,FALSE) -> 74.25 | M7: =VLOOKUP($G7,List!$A:$U,17,FALSE) -> - Is *not* playing with a Random New World | N7: No | O7: =VLOOKUP($G7,List!$A:$U,18,FALSE) -> Has completed the following missions: - *“Rule of the Sun”* - *“Contact the Oracle”* - *“Defeat the Wanka”* - *“Our Chimuan Rivals”* - *“The Ground Shaker”* - *“Conquer Cajamarca”* - *“Take Over Quito”* - *“Defy the Qollans”* - *“Seize Southern Fringes”* - *“Recruit the Chanka”* - *“Seize the Chincha”* - *“Down the Altiplano”* - *“Promote Runasimi”* - *“Development of the Mitma”* - *“Awka Kamayuq”* - *“The Big Ears”* - *“The Zeq'e System”* - *“The Oracle of Pachacamac”* - *“Four Quarters Together”* - *“The Qollqas”* - *“Construct New Kallanka”* - *“The Solar Cult”* - *“Reform Religion”* - *“Temples to Viracocha”* - *“Imperial Infrastructure”* - *“Qhapaq Ñan”* - *“Imperial Frontiers”* - *“Incan Terracing”* - *“Idols of our Subjects”* - *“Among the Mountaintops”* - *“Navel of the Universe”* - *“Haucaypata”* - *“Collect the Mita”* - *“Sweat of the Sun”* - *“Tears of the Moon”* - *“Renovate Cuzco”* - *“Secondary Capital”* - *“Incan Weaving”* - *“Expand into the Jungle”* - *“Recruit Bowmen”* | P7: =VLOOKUP($G7,List!$A:$U,19,FALSE) -> 0
A8: 002 | B8: Frankfurt | C8: VH | D8: =SUMIFS($L:$L,$A:$A,$A8) -> 443.25 | E8: =D8/'Top 10 Hard'!$J$2 -> 0.011990716 | F8: =IF(NOT(ISNUMBER(F7)),0,F7)+Table1[[#This Row],[Points]]/'Top 10 Hard'!$J$2 -> 0.42350694 | G8: A Sun God | H8: =IF(VLOOKUP($G8,List!$A:$O,15,FALSE)=0,"",VLOOKUP($G8,List!$A:$O,15,FALSE)) -> Y | I8: =VLOOKUP($G8,List!$A:$U,2,FALSE) -> Form Inca, embrace all Institutions and own all of South America as core provinces. | J8: =VLOOKUP($G8,List!$A:$U,3,FALSE) -> 0.016 | K8: =VLOOKUP($G8,List!$A:$U,4,FALSE) -> M | L8: =VLOOKUP($G8,List!$A:$U,5,FALSE) -> 71 | M8: =VLOOKUP($G8,List!$A:$U,17,FALSE) -> *Not* using a random New World. | N8: No | O8: =VLOOKUP($G8,List!$A:$U,18,FALSE) -> - Is Inca - *Not* playing as a released vassal - Have embraced all institutions - All provinces in South America are either empty, wasteland, a colony or owned and cored Inca. | P8: =VLOOKUP($G8,List!$A:$U,19,FALSE) -> The Falklands (1095), South Georgia (2025) and Galapagos (2002) are also part of South America. It is useful to colonize them before a strong colonizer can do it, because these provinces won't become part of a colonial nation. This achievement is very hard without El Dorado, but pretty easy without it.
A9: 003 | B9: Novgorod | C9: VH | D9: =SUMIFS($L:$L,$A:$A,$A9) -> 379.4 | E9: =D9/'Top 10 Hard'!$J$2 -> 0.010263458 | F9: =IF(NOT(ISNUMBER(F8)),0,F8)+Table1[[#This Row],[Points]]/'Top 10 Hard'!$J$2 -> 0.42535999 | G9: Relentless Push East | H9: =IF(VLOOKUP($G9,List!$A:$O,15,FALSE)=0,"",VLOOKUP($G9,List!$A:$O,15,FALSE)) -> Y | I9: =VLOOKUP($G9,List!$A:$U,2,FALSE) -> Starting as a Russian nation, By 1600 own the East Siberian Coastline. | J9: =VLOOKUP($G9,List!$A:$U,3,FALSE) -> 0.026 | K9: =VLOOKUP($G9,List!$A:$U,4,FALSE) -> M | L9: =VLOOKUP($G9,List!$A:$U,5,FALSE) -> 68.5 | M9: =VLOOKUP($G9,List!$A:$U,17,FALSE) -> Culture group is *East Slavic* | N9: No | O9: =VLOOKUP($G9,List!$A:$U,18,FALSE) -> - Year is before 1601 - Own all port provinces in the *East Siberia* region These provinces are Kamchatka, Penzhina, Kagyrgyn, Gizhiga, Tauisk, Okhotsk and Jugjur. | P9: =VLOOKUP($G9,List!$A:$U,19,FALSE) -> - Note that it is not necessary to core the provinces. Even unfinished colonies count. - This achievement is pretty easy to reach as Muscovy and you can finish it 40 to 50 years before the deadline. It is recommended to form Russia and take advantage of their Siberian Frontier idea, helping idea groups like exploration and expansion will then be optional. But a colonist from these groups can be used to start colonies if the time runs out and one of the Siberian ports has already been cored or fully colonized.
A10: 003 | B10: Novgorod | C10: VH | D10: =SUMIFS($L:$L,$A:$A,$A10) -> 379.4 | E10: =D10/'Top 10 Hard'!$J$2 -> 0.010263458 | F10: =IF(NOT(ISNUMBER(F9)),0,F9)+Table1[[#This Row],[Points]]/'Top 10 Hard'!$J$2 -> 0.42592537 | G10: All belongs to Mother Russia | H10: =IF(VLOOKUP($G10,List!$A:$O,15,FALSE)=0,"",VLOOKUP($G10,List!$A:$O,15,FALSE)) -> Y | I10: =VLOOKUP($G10,List!$A:$U,2,FALSE) -> Start as a country of Russian culture and form Russia. | J10: =VLOOKUP($G10,List!$A:$U,3,FALSE) -> 0.091 | K10: =VLOOKUP($G10,List!$A:$U,4,FALSE) -> E | L10: =VLOOKUP($G10,List!$A:$U,5,FALSE) -> 20.9 | M10: =VLOOKUP($G10,List!$A:$U,17,FALSE) -> Primary culture is either *Muscovite*, *Ryazanian* or *Novgorodian* | N10: No | O10: =VLOOKUP($G10,List!$A:$U,18,FALSE) -> Is Russia | P10: =VLOOKUP($G10,List!$A:$U,19,FALSE) -> Easiest to do as Muscovy.
A11: 003 | B11: Novgorod | C11: VH | D11: =SUMIFS($L:$L,$A:$A,$A11) -> 379.4 | E11: =D11/'Top 10 Hard'!$J$2 -> 0.010263458 | F11: =IF(NOT(ISNUMBER(F10)),0,F10)+Table1[[#This Row],[Points]]/'Top 10 Hard'!$J$2 -> 0.4337704 | G11: Frozen Assets | H11: =IF(VLOOKUP($G11,List!$A:$O,15,FALSE)=0,"",VLOOKUP($G11,List!$A:$O,15,FALSE)) -> Y | I11: =VLOOKUP($G11,List!$A:$U,2,FALSE) -> Start as Novgorod and control 90% of the trade power in the White Sea trade node while it is the highest valued trade node in the world. | J11: =VLOOKUP($G11,List!$A:$U,3,FALSE) -> 0.01 | K11: =VLOOKUP($G11,List!$A:$U,4,FALSE) -> VH | L11: =VLOOKUP($G11,List!$A:$U,5,FALSE) -> 290 | M11: =VLOOKUP($G11,List!$A:$U,17,FALSE) -> Playing as Novgorod | N11: No | O11: =VLOOKUP($G11,List!$A:$U,18,FALSE) -> Have 90% trade share in White Sea and it's the highest valued trade node in the world. | P11: =VLOOKUP($G11,List!$A:$U,19,FALSE) -> - Note that "highest valued trade" means Total trade value *minus* outgoing trade. - Not too difficult once you become powerful. You should be able to steer most Asian trade towards the white sea. Trade and plutocratic ideas can be helpful, but are not necessary : trade companies, the Great Russian Federation reform, and monuments like Bam citadel will provide you as many merchants as you need. Building manufactories (not workshops) in downstream nodes like Girin, Beijing, Yumen, etc. will increase the trade value downstream drastically. Note that England gets an event (« The Muscovite trade company ») that gives them permanent +20 trade power in the White Sea ̦; it can be counterbalanced by building lots of light ships.
A12: 004 | B12: Papal State | C12: H | D12: =SUMIFS($L:$L,$A:$A,$A12) -> 212 | E12: =D12/'Top 10 Hard'!$J$2 -> 0.0057349842 | F12: =IF(NOT(ISNUMBER(F11)),0,F11)+Table1[[#This Row],[Points]]/'Top 10 Hard'!$J$2 -> 0.43765234 | G12: Holy Trinity | H12: =IF(VLOOKUP($G12,List!$A:$O,15,FALSE)=0,"",VLOOKUP($G12,List!$A:$O,15,FALSE)) -> Y | I12: =VLOOKUP($G12,List!$A:$U,2,FALSE) -> As the Papacy, own Jerusalem and have Livonian Order, Teutonic Order and The Knights as Marches. | J12: =VLOOKUP($G12,List!$A:$U,3,FALSE) -> 0.013 | K12: =VLOOKUP($G12,List!$A:$U,4,FALSE) -> H | L12: =VLOOKUP($G12,List!$A:$U,5,FALSE) -> 143.5 | M12: =VLOOKUP($G12,List!$A:$U,17,FALSE) -> Playing as The Papal State | N12: No | O12: =VLOOKUP($G12,List!$A:$U,18,FALSE) -> - is The Papal State - Own and core Jerusalem. - Have Livonian Order, Teutonic Order and The Knights as marches. | P12: =VLOOKUP($G12,List!$A:$U,19,FALSE) -> This achievement has several common pitfalls which would make it all but impossible to complete it if they happen. The strategy page for this achievement has a section which explains them and some ways to get out of these situations. The player is advised to read that before attempting the achievement.
A13: 004 | B13: Papal State | C13: H | D13: =SUMIFS($L:$L,$A:$A,$A13) -> 212 | E13: =D13/'Top 10 Hard'!$J$2 -> 0.0057349842 | F13: =IF(NOT(ISNUMBER(F12)),0,F12)+Table1[[#This Row],[Points]]/'Top 10 Hard'!$J$2 -> 0.43950538 | G13: Kingdom of God | H13: =IF(VLOOKUP($G13,List!$A:$O,15,FALSE)=0,"",VLOOKUP($G13,List!$A:$O,15,FALSE)) -> Y | I13: =VLOOKUP($G13,List!$A:$U,2,FALSE) -> Starting as the Papal State, become the Kingdom of God | J13: =VLOOKUP($G13,List!$A:$U,3,FALSE) -> 0.026 | K13: =VLOOKUP($G13,List!$A:$U,4,FALSE) -> M | L13: =VLOOKUP($G13,List!$A:$U,5,FALSE) -> 68.5 | M13: =VLOOKUP($G13,List!$A:$U,17,FALSE) -> - Playing as The Papal State - *Not* using a random New World | N13: No | O13: =VLOOKUP($G13,List!$A:$U,18,FALSE) -> Has enacted the decision Declare the Kingdom of God | P13: =VLOOKUP($G13,List!$A:$U,19,FALSE) -> 0
A14: 005 | B14: Ardabil | C14: VH | D14: =SUMIFS($L:$L,$A:$A,$A14) -> 492.5 | E14: =D14/'Top 10 Hard'!$J$2 -> 0.013323018 | F14: =IF(NOT(ISNUMBER(F13)),0,F13)+Table1[[#This Row],[Points]]/'Top 10 Hard'!$J$2 -> 0.44694463 | G14: Shahanshah | H14: =IF(VLOOKUP($G14,List!$A:$O,15,FALSE)=0,"",VLOOKUP($G14,List!$A:$O,15,FALSE)) -> Y | I14: =VLOOKUP($G14,List!$A:$U,2,FALSE) -> Start as Ardabil and form Persia or Eranshahr. | J14: =VLOOKUP($G14,List!$A:$U,3,FALSE) -> 0.025 | K14: =VLOOKUP($G14,List!$A:$U,4,FALSE) -> VH | L14: =VLOOKUP($G14,List!$A:$U,5,FALSE) -> 275 | M14: =VLOOKUP($G14,List!$A:$U,17,FALSE) -> Playing as Ardabil | N14: No | O14: =VLOOKUP($G14,List!$A:$U,18,FALSE) -> - *Not* playing as a released vassal - Is Persia*or*Eranshahr | P14: =VLOOKUP($G14,List!$A:$U,19,FALSE) -> It's possible to get Bahmanis in India as an ally by improving relations until you can royal marry them (which removes their "Unknown") relations modifier. This will deter nearby attackers as you expand opportunistically.
... A129: 179 | B129: Theodoro | C129: VH | D129: =SUMIFS($L:$L,$A:$A,$A129) -> 291 | E129: =D129/'Top 10 Hard'!$J$2 -> 0.0078720774 | F129: =IF(NOT(ISNUMBER(F128)),0,F128)+Table1[[#This Row],[Points]]/'Top 10 Hard'!$J$2 -> 0.80472649 | G129: Gothic Invasion | H129: =IF(VLOOKUP($G129,List!$A:$O,15,FALSE)=0,"",VLOOKUP($G129,List!$A:$O,15,FALSE)) | I129: =VLOOKUP($G129,List!$A:$U,2,FALSE) -> Start as Theodoro and conquer all Germanic culture provinces in Europe. | J129: =VLOOKUP($G129,List!$A:$U,3,FALSE) -> 0.009 | K129: =VLOOKUP($G129,List!$A:$U,4,FALSE) -> VH | L129: =VLOOKUP($G129,List!$A:$U,5,FALSE) -> 291 | M129: =VLOOKUP($G129,List!$A:$U,17,FALSE) -> Playing as Theodoro | N129: No | O129: =VLOOKUP($G129,List!$A:$U,18,FALSE) -> - *Not* playing as a released vassal - All provinces with *Germanic* culture group in Europe owned by Theodoro - Culture is either: - *Gothic* from the Byzantine culture group - *Gothic* from the Germanic culture group | P129: =VLOOKUP($G129,List!$A:$U,19,FALSE) -> Forming other nations will make this achievement much more difficult, because then all *Germanic* cultured provinces in Europe have to be converted to another culture to fulfill the requirements. This does not apply if the formed country is a Former colonial nation formable and Theodoro still has provinces in the old world, because forming such a country as Theodoro keeps Theodoro alive so the achievement can still be fulfilled by feeding all *Germanic* provinces in Europe to Theodoro if they are later vassalized. Note though that playing as a released colonial nation doesn't work, because it counts as playing as a released vassal.
A130: 180 | B130: Transoxiana | C130: =VLOOKUP($G130,List!$A:$U,4,FALSE) -> I | D130: =SUMIFS($L:$L,$A:$A,$A130) -> 1092.75 | E130: =D130/'Top 10 Hard'!$J$2 -> 0.029560868 | F130: =IF(NOT(ISNUMBER(F129)),0,F129)+Table1[[#This Row],[Points]]/'Top 10 Hard'!$J$2 -> 0.82834272 | G130: True Heir of Timur | H130: =IF(VLOOKUP($G130,List!$A:$O,15,FALSE)=0,"",VLOOKUP($G130,List!$A:$O,15,FALSE)) | I130: =VLOOKUP($G130,List!$A:$U,2,FALSE) -> Starting as a Timurid subject, form the Mughals and conquer India by 1550. | J130: =VLOOKUP($G130,List!$A:$U,3,FALSE) -> 0.009 | K130: =VLOOKUP($G130,List!$A:$U,4,FALSE) -> I | L130: =VLOOKUP($G130,List!$A:$U,5,FALSE) -> 873 | M130: =VLOOKUP($G130,List!$A:$U,17,FALSE) -> - Playing as one of the following: - Afghanistan - Sistan - Transoxiana - Khorasan - Fars | N130: No | O130: =VLOOKUP($G130,List!$A:$U,18,FALSE) -> - Is Mughals - The year is before 1550 - Every province in India superregion is owned by the country or a subject other than a tributary | P130: =VLOOKUP($G130,List!$A:$U,19,FALSE) -> Easier in recent patches than when added. The strongest contenders are Afghanistan, which is the closest to India, and Transoxiana, which starts the strongest. Recommended ideas include Administrative for extremely cheap coring and Diplomatic to manage aggressive expansion and to truce break more easily if necessary.
A131: 180 | B131: Transoxiana | C131: I | D131: =SUMIFS($L:$L,$A:$A,$A131) -> 1092.75 | E131: =D131/'Top 10 Hard'!$J$2 -> 0.029560868 | F131: =IF(NOT(ISNUMBER(F130)),0,F130)+Table1[[#This Row],[Points]]/'Top 10 Hard'!$J$2 -> 0.83235992 | G131: Baborg | H131: =IF(VLOOKUP($G131,List!$A:$O,15,FALSE)=0,"",VLOOKUP($G131,List!$A:$O,15,FALSE)) | I131: =VLOOKUP($G131,List!$A:$U,2,FALSE) -> As the Mughals, assimilate at least 12 culture groups. | J131: =VLOOKUP($G131,List!$A:$U,3,FALSE) -> 0.003 | K131: =VLOOKUP($G131,List!$A:$U,4,FALSE) -> H | L131: =VLOOKUP($G131,List!$A:$U,5,FALSE) -> 148.5 | M131: =VLOOKUP($G131,List!$A:$U,17,FALSE) -> 0 | N131: No | O131: =VLOOKUP($G131,List!$A:$U,18,FALSE) -> - Is Mughals - Has enacted the Mughal Diwan government reform - Has assimilated at least *12* culture groups | P131: =VLOOKUP($G131,List!$A:$U,19,FALSE) -> 0
A132: 180 | B132: Transoxiana | C132: I | D132: =SUMIFS($L:$L,$A:$A,$A132) -> 1092.75 | E132: =D132/'Top 10 Hard'!$J$2 -> 0.029560868 | F132: =IF(NOT(ISNUMBER(F131)),0,F131)+Table1[[#This Row],[Points]]/'Top 10 Hard'!$J$2 -> 0.83428736 | G132: Sweet Home Qaraqorum | H132: =IF(VLOOKUP($G132,List!$A:$O,15,FALSE)=0,"",VLOOKUP($G132,List!$A:$O,15,FALSE)) | I132: =VLOOKUP($G132,List!$A:$U,2,FALSE) -> As the Mughals assimilate Mongolian culture. | J132: =VLOOKUP($G132,List!$A:$U,3,FALSE) -> 0.015 | K132: =VLOOKUP($G132,List!$A:$U,4,FALSE) -> M | L132: =VLOOKUP($G132,List!$A:$U,5,FALSE) -> 71.25 | M132: =VLOOKUP($G132,List!$A:$U,17,FALSE) -> 0 | N132: No | O132: =VLOOKUP($G132,List!$A:$U,18,FALSE) -> - Is Mughals - Has the Mughal Diwan government reform - Have Mongol as accepted culture | P132: =VLOOKUP($G132,List!$A:$U,19,FALSE) -> Easiest by starting as the Timurids. Forming the Mughals should not be a problem as long as you keep your vassals loyal and conquer Delhi. After that you should carve your way up to the Mongolian culture area. Fabricate claims along the way and conquer the provinces needed to reach that area. Usually you can start by declaring war on Uzbek, followed by Oirat. The factions controlling those provinces differ from campaign to campaign. In order to assimilate you need to conquer ALL Mongolian culture provinces. With the Winds of Change DLC mission tree, staying as Timurids is advise to use their bonuses and permanent claim on the mongol region.
A133: 181 | B133: Timurids | C133: E | D133: =SUMIFS($L:$L,$A:$A,$A133) -> 29.7 | E133: =D133/'Top 10 Hard'!$J$2 -> 0.00080343883 | F133: =IF(NOT(ISNUMBER(F132)),0,F132)+Table1[[#This Row],[Points]]/'Top 10 Hard'!$J$2 -> 0.8350908 | G133: Timurizz | H133: =IF(VLOOKUP($G133,List!$A:$O,15,FALSE)=0,"",VLOOKUP($G133,List!$A:$O,15,FALSE)) | I133: =VLOOKUP($G133,List!$A:$U,2,FALSE) -> Starting as the Timurids, have 75 prestige, and 5 allies with 100 Trust and 150 opinion. | J133: =VLOOKUP($G133,List!$A:$U,3,FALSE) -> 0.003 | K133: =VLOOKUP($G133,List!$A:$U,4,FALSE) -> E | L133: =VLOOKUP($G133,List!$A:$U,5,FALSE) -> 29.7 | M133: =VLOOKUP($G133,List!$A:$U,17,FALSE) -> - Is Timurids | N133: No | O133: =VLOOKUP($G133,List!$A:$U,18,FALSE) -> - Prestige is at least *+75* - Has at least 5 allies with 100 trust which have at least *+150* opinion of our country | P133: =VLOOKUP($G133,List!$A:$U,19,FALSE) -> The allies which have the trust have to be the same allies which have the opinion Trust can be gained by honoring calls to arms or by using the *Influence nation* interaction as a great power, or with The Cossacks or Leviathan by trading favors for trust. If neither The Cossacks nor Leviathan are active, trust with allies grows slowly over time.
A134: 182 | B134: Georgia | C134: VH | D134: =SUMIFS($L:$L,$A:$A,$A134) -> 298 | E134: =D134/'Top 10 Hard'!$J$2 -> 0.0080614401 | F134: =IF(NOT(ISNUMBER(F133)),0,F133)+Table1[[#This Row],[Points]]/'Top 10 Hard'!$J$2 -> 0.84315224 | G134: Legacy of Saint George | H134: =IF(VLOOKUP($G134,List!$A:$O,15,FALSE)=0,"",VLOOKUP($G134,List!$A:$O,15,FALSE)) | I134: =VLOOKUP($G134,List!$A:$U,2,FALSE) -> As Georgia, have as vassals Genoa, Aragon, England and Trier or their successors, and control Wales. | J134: =VLOOKUP($G134,List!$A:$U,3,FALSE) -> 0.002 | K134: =VLOOKUP($G134,List!$A:$U,4,FALSE) -> VH | L134: =VLOOKUP($G134,List!$A:$U,5,FALSE) -> 298 | M134: =VLOOKUP($G134,List!$A:$U,17,FALSE) -> 0 | N134: No | O134: =VLOOKUP($G134,List!$A:$U,18,FALSE) -> - Is Georgia - Has the following countries (or countries formed by them) as vassals: - - Genoa - Aragon - England - Trier - All provinces in the Wales area: - Are owned by the country or its non-tributary subjects | P134: =VLOOKUP($G134,List!$A:$U,19,FALSE) -> If one of the countries forms another country(e.g. England forms Great Britain), the new country can be vassalized to get the achievement. If one of the countries dies, care must be taken that the cores don't expire, especially for Trier which is not the primary tag of its culture.
A135: 183 | B135: Mamluks | C135: VH | D135: =SUMIFS($L:$L,$A:$A,$A135) -> 296 | E135: =D135/'Top 10 Hard'!$J$2 -> 0.0080073365 | F135: =IF(NOT(ISNUMBER(F134)),0,F134)+Table1[[#This Row],[Points]]/'Top 10 Hard'!$J$2 -> 0.85115958 | G135: I don't like sand | H135: =IF(VLOOKUP($G135,List!$A:$O,15,FALSE)=0,"",VLOOKUP($G135,List!$A:$O,15,FALSE)) | I135: =VLOOKUP($G135,List!$A:$U,2,FALSE) -> Have the most development while owning no province with terrain other than desert or coastal desert. | J135: =VLOOKUP($G135,List!$A:$U,3,FALSE) -> 0.004 | K135: =VLOOKUP($G135,List!$A:$U,4,FALSE) -> VH | L135: =VLOOKUP($G135,List!$A:$U,5,FALSE) -> 296 | M135: =VLOOKUP($G135,List!$A:$U,17,FALSE) -> *Not* using a random New World | N135: No | O135: =VLOOKUP($G135,List!$A:$U,18,FALSE) -> - All provinces are either desert or coastal desert - No other country has a higher development than this country All desert and coastal desert provinces | P135: =VLOOKUP($G135,List!$A:$U,19,FALSE) -> Easiest as Ajuuraan or the Mamluks, because of their national ideas and the "Hydraulic Rights" estate privilege (which reduces the additional cost from developing deserts and coastal desert by half), that is unlocked through a mission in Origins DLC. Forming Arabia (possibly via Yemen to avoid the tech requirement) will unlock the similar "Oasis Development" privilege, which stacks with "Hydraulic Rights"
A136: 184 | B136: Kale | C136: I | D136: =SUMIFS($L:$L,$A:$A,$A136) -> 885 | E136: =D136/'Top 10 Hard'!$J$2 -> 0.023940854 | F136: =IF(NOT(ISNUMBER(F135)),0,F135)+Table1[[#This Row],[Points]]/'Top 10 Hard'!$J$2 -> 0.87510043 | G136: Eat your Greens | H136: =IF(VLOOKUP($G136,List!$A:$O,15,FALSE)=0,"",VLOOKUP($G136,List!$A:$O,15,FALSE)) | I136: =VLOOKUP($G136,List!$A:$U,2,FALSE) -> Control all Grasslands in Asia as Kale before the age of Absolutism. | J136: =VLOOKUP($G136,List!$A:$U,3,FALSE) -> 0.005 | K136: =VLOOKUP($G136,List!$A:$U,4,FALSE) -> I | L136: =VLOOKUP($G136,List!$A:$U,5,FALSE) -> 885 | M136: =VLOOKUP($G136,List!$A:$U,17,FALSE) -> Playing as Kale | N136: No | O136: =VLOOKUP($G136,List!$A:$U,18,FALSE) -> - It is *not* the Age of Absolutism or the Age of Revolutions - Every province in Asia with Grasslands terrain is owned by the player's country *or* its non-tributary subjects All grassland provinces in Asia | P136: =VLOOKUP($G136,List!$A:$U,19,FALSE) -> It is not required to keep playing as Kale to earn the achievement, but changing tag will hide it from the achievement tab. Start by subjugating and allying all Shan minors to complete the mission "Unite the Shan" to inherit them all and gain free cores (don't conquer any province from them as these would needlessly have to be cored; best to fully annex Ava and inherit all their tributaries). To limit AE and help with the endless conquests to come it is recommended you switch to horde government first, which is you should form Tibet and do the "Steppe Politics" mission. After choosing to invite one of the two Mongols switch culture back to Shan. Conquer enough of Indochina to form Siam for the ideas. Take Horde Ideas then Expansion then Diplomatic Ideas, don't delay colonizing Siberia. The colonies in the grassland provinces don't have to be finished, but you need to finish 3 colonies to reach the farthest province (2 if you conquer Onan Gol(1058) in Mongolia or Albazin (2102) in Manchuria instead of colonizing from the coast). The can be delayed by 30 years by ensuring that the highest valued trade node in the world contains no centers of trade at level 2 or higher, and no capital provinces.
A137: 185 | B137: Norway | C137: VH | D137: =SUMIFS($L:$L,$A:$A,$A137) -> 583 | E137: =D137/'Top 10 Hard'!$J$2 -> 0.015771207 | F137: =IF(NOT(ISNUMBER(F136)),0,F136)+Table1[[#This Row],[Points]]/'Top 10 Hard'!$J$2 -> 0.88299956 | G137: Norwegian Wood | H137: =IF(VLOOKUP($G137,List!$A:$O,15,FALSE)=0,"",VLOOKUP($G137,List!$A:$O,15,FALSE)) | I137: =VLOOKUP($G137,List!$A:$U,2,FALSE) -> Own or have a subject own all naval supplies provinces as Norway. | J137: =VLOOKUP($G137,List!$A:$U,3,FALSE) -> 0.008 | K137: =VLOOKUP($G137,List!$A:$U,4,FALSE) -> VH | L137: =VLOOKUP($G137,List!$A:$U,5,FALSE) -> 292 | M137: =VLOOKUP($G137,List!$A:$U,17,FALSE) -> Playing as Norway | N137: No | O137: =VLOOKUP($G137,List!$A:$U,18,FALSE) -> Own or have a non-tributary subject own all provinces with naval supplies. | P137: =VLOOKUP($G137,List!$A:$U,19,FALSE) -> Before patch 1.36.2, it was required that the provinces were owned by Norway or Norway's subjects, but since patch 1.36.2, they have to be owned by the player's country and its subjects, so the player can form any country and still get the achievement without having to get Norway back on the map.
A138: 185 | B138: Norway | C138: VH | D138: =SUMIFS($L:$L,$A:$A,$A138) -> 583 | E138: =D138/'Top 10 Hard'!$J$2 -> 0.015771207 | F138: =IF(NOT(ISNUMBER(F137)),0,F137)+Table1[[#This Row],[Points]]/'Top 10 Hard'!$J$2 -> 0.89087164 | G138: Rags and Riches | H138: =IF(VLOOKUP($G138,List!$A:$O,15,FALSE)=0,"",VLOOKUP($G138,List!$A:$O,15,FALSE)) | I138: =VLOOKUP($G138,List!$A:$U,2,FALSE) -> Have the highest income in the world while neither owning nor starting with a province with a development level higher than 10. | J138: =VLOOKUP($G138,List!$A:$U,3,FALSE) -> 0.009 | K138: =VLOOKUP($G138,List!$A:$U,4,FALSE) -> VH | L138: =VLOOKUP($G138,List!$A:$U,5,FALSE) -> 291 | M138: =VLOOKUP($G138,List!$A:$U,17,FALSE) -> - No owned province has more than 10 development at the start of the game | N138: No | O138: =VLOOKUP($G138,List!$A:$U,18,FALSE) -> - No owned province has more than 10 development - No other country has a higher income than this country | P138: =VLOOKUP($G138,List!$A:$U,19,FALSE) -> One possible start is Norway. Stay as a vassal under Denmark for protection, rush expansion ideas, then get exploration after you reach diplomatic tech 7, and colonize Newfoundland from there, triggering the Grand Banks Fisheries which will power your colonial nation of Vinland. After Vinland forms, you can release and choose to play as them well within the time-frame of Denmark beginning integration, bypassing the PU. From there, expand and build as many manufactories as possible, swapping into Canada or Quebec's ideas, or even the USA. An important thing to note is that you can have a 10+ development province after the start of the campaign, but not during the month you're trying to count the highest income. A great alternative start is Wolgast. Play the regular HRE game, expanding into Denmark and Russia. Exploit all provinces within 10-20 development (requires Cradle of Civilization), boost development of all provinces below 10. Eventually, your income from flat 10 dev provinces will be the highest in the world, especially if you consider expanding into the west and taking control over the Channel. Keep all high dev provinces like Lübeck under vassals. Another good variant is Kilwa. Having Feudalism makes your country a dominant power in region, and you can easily expand. Almost all conquered provinces have development below 11 dev, so you will not need to exploit them (it takes much time). You can get 5 provinces with gold at the start and another 2 in Ethiopia. Other provinces also have good resources like ivory. Also your home trade nodes (Zanzibar and Cape) are convenient for collecting – you can increase income by steering trade from India and Malacca. At the start you should rush to admin tech 5 and get colonists for colonizing coasts (especially Cape) before the Europeans. The game does its check for highest income on every monthly tick meaning you could release nations from all your provinces with more than ten development and still get the achievement even if the next monthly tick would see your income drop tremendously as long as on the previous month tick, you had the highest income.
A139: 186 | B139: Manipur | C139: VH | D139: =SUMIFS($L:$L,$A:$A,$A139) -> 365.25 | E139: =D139/'Top 10 Hard'!$J$2 -> 0.0098806745 | F139: =IF(NOT(ISNUMBER(F138)),0,F138)+Table1[[#This Row],[Points]]/'Top 10 Hard'!$J$2 -> 0.89877077 | G139: The Animal Kingdom | H139: =IF(VLOOKUP($G139,List!$A:$O,15,FALSE)=0,"",VLOOKUP($G139,List!$A:$O,15,FALSE)) | I139: =VLOOKUP($G139,List!$A:$U,2,FALSE) -> As Manipur, unite the Bengal region and convert it to Animism. | J139: =VLOOKUP($G139,List!$A:$U,3,FALSE) -> 0.008 | K139: =VLOOKUP($G139,List!$A:$U,4,FALSE) -> VH | L139: =VLOOKUP($G139,List!$A:$U,5,FALSE) -> 292 | M139: =VLOOKUP($G139,List!$A:$U,17,FALSE) -> Playing as Manipur | N139: No | O139: =VLOOKUP($G139,List!$A:$U,18,FALSE) -> - All provinces in the Bengal region are owned by the player's country *or* its non-tributary subjects. - All provinces in the Bengal region are Animist | P139: =VLOOKUP($G139,List!$A:$U,19,FALSE) -> As soon as you can, take on your western neighbours, Kachar and/or Tripura. You will not have much luck east from game start, as Ava will guard it's tributaries. Best option is to not conquer both provinces, but to take one as a vassal - and a second OPM vassal in india as soon as possible as well. You can force them to be animist and feed them Indian culture provinces that you conquer. Allies are hard to come by, and vassals will be obliged to help you, pay you, give you extra force limit, etc.. Look for an opportunity to eat nations up north such as Assam, Sadiya, Mong Kawng, and Koch before Bengal annexes them or Ming makes them a tributary. Delay becoming a tributary of Ming as long as possible (or never if you can), but do not be afraid to use it as an inroad for expansion east as Ming will have a lot of tributary states in that direction. Once you are set up, it's the same as any other OPM-to-#1-Great-Power game. Get religious ideas to make conversions faster, especially against Islamic provinces.
A140: 186 | B140: Manipur | C140: VH | D140: =SUMIFS($L:$L,$A:$A,$A140) -> 365.25 | E140: =D140/'Top 10 Hard'!$J$2 -> 0.0098806745 | F140: =IF(NOT(ISNUMBER(F139)),0,F139)+Table1[[#This Row],[Points]]/'Top 10 Hard'!$J$2 -> 0.90075231 | G140: Ganges Khan | H140: =IF(VLOOKUP($G140,List!$A:$O,15,FALSE)=0,"",VLOOKUP($G140,List!$A:$O,15,FALSE)) | I140: =VLOOKUP($G140,List!$A:$U,2,FALSE) -> Start as Tribal nation in India and become a Steppe Horde. | J140: =VLOOKUP($G140,List!$A:$U,3,FALSE) -> 0.007 | K140: =VLOOKUP($G140,List!$A:$U,4,FALSE) -> M | L140: =VLOOKUP($G140,List!$A:$U,5,FALSE) -> 73.25 | M140: =VLOOKUP($G140,List!$A:$U,17,FALSE) -> - Government type is Tribal - Capital is in India superregion | N140: No | O140: =VLOOKUP($G140,List!$A:$U,18,FALSE) -> - Has the Steppe Nomads government reform | P140: =VLOOKUP($G140,List!$A:$U,19,FALSE) -> - This achievement is only visible if the Dharma *or* Emperor DLC is enabled, but it can be completed without them. Eligible countries are: - Bastar - Bishnupur - Chanda - Garha - Garjat - Jangladesh - Jeypore - Jhalavad - Jharkhand - Junagarh - Kachar - Kalahandi - Keonhjar - Kutch - Ladakh - Manipur - Patna - Parlakhimidi - Porbandar - Ratanpur - Sadiya - Tripura
A141: 187 | B141: Ottomans/Saruhan | C141: H | D141: =SUMIFS($L:$L,$A:$A,$A141) -> 148 | E141: =D141/'Top 10 Hard'!$J$2 -> 0.0040036682 | F141: =IF(NOT(ISNUMBER(F140)),0,F140)+Table1[[#This Row],[Points]]/'Top 10 Hard'!$J$2 -> 0.90475598 | G141: One nation to rule them all | H141: =IF(VLOOKUP($G141,List!$A:$O,15,FALSE)=0,"",VLOOKUP($G141,List!$A:$O,15,FALSE)) | I141: =VLOOKUP($G141,List!$A:$U,2,FALSE) -> As Saruhan, have at least 9 loyal vassals with at least 100 development each. | J141: =VLOOKUP($G141,List!$A:$U,3,FALSE) -> 0.004 | K141: =VLOOKUP($G141,List!$A:$U,4,FALSE) -> H | L141: =VLOOKUP($G141,List!$A:$U,5,FALSE) -> 148 | M141: =VLOOKUP($G141,List!$A:$U,17,FALSE) -> 0 | N141: No | O141: =VLOOKUP($G141,List!$A:$U,18,FALSE) -> - Is Saruhan - 9 countries fulfill the following conditions: - is a vassal of Saruhan - has less than *50%* liberty desire - has at least *100* development | P141: =VLOOKUP($G141,List!$A:$U,19,FALSE) -> Saruhan's core starts under the control of the Ottomans. Suggested strategy: expand rapidly as you normally would with the Ottomans until you have ~1200 development. Then, plan to release-and-play as Saruhan, taking most of Otto's lands. To do this, you will need to release Saruhan as vassal, wait 10 years, start to annex (to designate cores), feed it land, finalize annexation, and then release-and-play. You can cheese the release-and-play by feeding past the point of loyalty and then applying all available annexation cost reductions (Acquire Subjects mission, Influence idea, Amirs privilege, as well as any possible Policies). Make sure you wait until the last day of the month to do this, or else annexation progress will drop and you will be unable to proceed. As long as your annexation progress is above 100 on the month tick, it won't matter if liberty desire is over 50%. Once you have reannexed, you will be able to release-and-play. Ideally you will then own almost all Ottoman lands, making independence relatively easy to pursue. From there, you need to obtain 9 loyal vassals (NOT marches, NOT client states) with 100+ development. Rather than directly subjugating enemies to meet the vassal count, it is suggested that the player conquer and then release vassals; this avoids the forced vassalization malus. To help reduce liberty desire and thus total development needed, choose the relevant policies, and be sure to get the Splendor abilities in the Age of Revolutions (Anti-Revolutionary Zeal + Loyal Subjects). Upon release, you will no longer have the Ottoman government form, and should choose Iqta. Then on your goverment tab choose Lenient Taxation, which provides another Liberty Desire reduction. Note that during the feeding of Saruhan and following your transition to playing as them, the Ottomans will likely be severely weakened and thus open to attack. Keep this in mind, perhaps securing treaties in advance or locking in allies (though too many allies for Otto will make subsequent independence harder). Ideally you will be able to secure independence support from a rival.
A142: 188 | B142: Karaman | C142: H | D142: =SUMIFS($L:$L,$A:$A,$A142) -> 143.5 | E142: =D142/'Top 10 Hard'!$J$2 -> 0.0038819351 | F142: =IF(NOT(ISNUMBER(F141)),0,F141)+Table1[[#This Row],[Points]]/'Top 10 Hard'!$J$2 -> 0.90863791 | G142: A Hero’s Welcome | H142: =IF(VLOOKUP($G142,List!$A:$O,15,FALSE)=0,"",VLOOKUP($G142,List!$A:$O,15,FALSE)) | I142: =VLOOKUP($G142,List!$A:$U,2,FALSE) -> Starting as Karaman, form the Sultanate of Rum. | J142: =VLOOKUP($G142,List!$A:$U,3,FALSE) -> 0.013 | K142: =VLOOKUP($G142,List!$A:$U,4,FALSE) -> H | L142: =VLOOKUP($G142,List!$A:$U,5,FALSE) -> 143.5 | M142: =VLOOKUP($G142,List!$A:$U,17,FALSE) -> Playing as Karaman | N142: No | O142: =VLOOKUP($G142,List!$A:$U,18,FALSE) -> Is Rûm | P142: =VLOOKUP($G142,List!$A:$U,19,FALSE) -> Initial moves for a success are for the player to ally Mamluks and later when possible Timurids. Expanding East and land locking the Ottomans in the Anatolia region by quick expansion east and north will in conjunction with your powerful allies forces the Ottomans to expand into Europe, once this occurs your best chance is to wait for a good opportunity strike with your allies when the ottomans are weak. Your main objective should be to get the provinces of Kocaeli and Biga, so that in next war you can build up your galley navy and block the straits.
... A152: 191 | B152: Austria | C152: I | D152: =SUMIFS($L:$L,$A:$A,$A152) -> 1133.5 | E152: =D152/'Top 10 Hard'!$J$2 -> 0.030663229 | F152: =IF(NOT(ISNUMBER(F151)),0,F151)+Table1[[#This Row],[Points]]/'Top 10 Hard'!$J$2 -> 0.98503223 | G152: One Faith | H152: =IF(VLOOKUP($G152,List!$A:$O,15,FALSE)=0,"",VLOOKUP($G152,List!$A:$O,15,FALSE)) | I152: =VLOOKUP($G152,List!$A:$U,2,FALSE) -> Have all non-wasteland land provinces in the world be of your religion. | J152: =VLOOKUP($G152,List!$A:$U,3,FALSE) -> 0.013 | K152: =VLOOKUP($G152,List!$A:$U,4,FALSE) -> I | L152: =VLOOKUP($G152,List!$A:$U,5,FALSE) -> 861 | M152: =VLOOKUP($G152,List!$A:$U,17,FALSE) -> 0 | N152: No | O152: =VLOOKUP($G152,List!$A:$U,18,FALSE) -> No colonized non-wasteland province has a different religion than this country. | P152: =VLOOKUP($G152,List!$A:$U,19,FALSE) -> - Using the random new world will drastically reduce the number of provinces, especially inland ones, making this easier than with the true new world. - Uncolonized provinces may still be of a different religion. The easiest choice is either Austria or Ottomans, as both tags can conquer the world easily and have religions that have lots of missionaries and missionary strength buffs. The hardest faiths to One Faith with are the Pagan faiths (Animist, Tengri…), and Confucian with Mandate of Heaven. If playing as a Fetishist or Hindu nation, choose Buddhadharma or Buddha, respectively, to be able to use the Buddha statues and Pagan temples. Najd is a possible starting nation, since its ideas are religiously focused, including access to +2 missionaries and +2% missionary strength, as well as its starting religion of Sunni granting *−2%* local missionary strength which would make these provinces harder to convert. Possible to combine with Jihad.

Sheet Run - Russia
